Workbook
Name Deal_Type: List!$A$1:$A$4
Name Deat_Type: #REF!
Name Employee: List!$O$1:$O$16
Name Quater: List!$B$19:$B$26

Sheet List
A1: Self-Prospected | F1: Reorder/resupply | K1: Commercial Director | L1: Gerardo Garcia | M1: Sales Engineer | N1: Carlos Tarazon | O1: Carlos T
A2: New Opportunity | D2: Self-Prospected | E2: New Opportunity | F2: Renewal | H2: Contract | M2: Sales Engineer | N2: Diego Martinez | O2: Diego M
A3: Renewal | C3: Sales Rep | D3: 0.03 | E3: 0.03 | F3: 0.01 | G3: Client/Team | H3: 0 | M3: Sales Engineer | N3: Dulce Ramirez | O3: Dulce R
A4: Contract | C4: KAS | D4: 0.03 | E4: 0.02 | F4: 0.005 | G4: Client/Team | H4: 0 | M4: Sales Engineer | N4: Oziel Garcia | O4: Oziel G
C5: App Eng (AE) | D5: 0.03 | E5: 0.02 | F5: 0.01 | G5: Over 10% net Profit | H5: 0 | K5: Application Manager | L5: Ian Trottier | M5: Applications Engineer/Site Manager | N5: Amanda Quiao | O5: Amanda Q
C6: FST | D6: 0.03 | E6: 0.01 | F6: 0 | H6: 0 | M6: Applications Engineer | N6: Leriel Reyes | O6: Leriel R
M7: Field Application Engineer | N7: Vacancy | O7: Vacancy
F8: 0.02 | G8: total Sales | M8: Applications Engineer | N8: Eduardo Talamantes | O8: Eduardo T
A9: New Companies 2025 | B9: mgr | C9: SALES | D9: 0.015 | K9: Sales Fullfilment Manager | L9: Marlene Martinez | M9: Service Technician | N9: Martin Calderon | O9: Martin C
A10: Freight Revenue | B10: mgr | C10: KAS | D10: 0.015 | M10: Key Account Specialist | N10: Alexis Gil | O10: Alexis G
B11: mgr | C11: APP | D11: 0.015 | M11: Key Account Specialist | N11: Wilka Nunez | O11: Wilka N
M12: Key Account Specialist | N12: Aleksandar Stankovic | O12: Aleksandar S
L13: Mariela de Jesus | M13: Field Service Engineer | N13: Pierre Dupuis | O13: Pierre D
N14: Ian Trottier | O14: Ian T
N15: Marlen Martinez | O15: Marlen M
A16: Dynapro_Commission_Policies_Slides.pptx | N16: Other | O16: Other
B19: 2501 | C19: Q1 2025
B20: 2502 | C20: Q2 2025
B21: 2503 | C21: Q3 2025
B22: 2504 | C22: Q4 2025
B23: 2601 | C23: Q1 2026
B24: 2602 | C24: Q2 2026
B25: 2603 | C25: Q3 2026
B26: 2604 | C26: Q4 2026
A39: Clients | B39: Sales P
A40: AGM Inc. | B40: Amanda Q
A41: Zijin Mining - Rosebel Goldmines N.V. | B41: Amanda Q
A42: Zijin Mining - Rosebel Goldmines N.V., Rosebel Gold Mines N.V. | B42: Amanda Q
A43: Mill-Right Mine Services Inc. | B43: Amanda Q
A44: First Bauxite Inc. | B44: Amanda Q

Sheet rate
A1: Divisa | B1: USD
A3: Row Labels | B3: Average of Tasa de divisa
A4: 1 | B4: 0.69467811
A5: 2 | B5: 0.7022845
A6: 3 | B6: 0.70001794
A7: 4 | B7: 0.71666178
A8: 5 | B8: 0.72192522
A9: 6 | B9: 0.73037887
A10: 7 | B10: 0.72955786
A11: 8 | B11: 0.72425848
A12: 9 | B12: 0.72208412
A13: 10 | B13: 0.71521853
A14: 11 | B14: 0.71452838
A15: 12 | B15: 0.72380448
A16: Grand Total | B16: 0.71631822

Sheet CASO
A1: Número de facturas | B1: Referencia de la orden | C1: Reference | D1: Cliente | E1: Fecha de creación | F1: Fecha de la orden | G1: Shipping Date | H1: Vendedor | I1: Divisa | J1: Tasa de divisa | K1: Total CAD | L1: Total MXP | M1: Total USD | N1: Importe sin impuestos | O1: Impuestos | P1: Total | Q1: Delivery Status | R1: Hubspot Deal Owner | S1: CASOPOInv | T1: Month Created
A2: 1 | B2: SO16348 | C2: 6500015792 | D2: Wesdome Gold Mines Ltd - Eagle River Mine | E2: 45659.4 | F2: 45663.596 | G2: 45664 | H2: Ian Trottier | I2: CAD | J2: 1 | K2: 20655.24 | L2: 0 | M2: 14381.876 | N2: 18278.97 | O2: 2376.27 | P2: 20655.24 | Q2: Delivered | S2: =VLOOKUP(B2,CASOPOInvCL!$B$1:$D$1600,1,FALSE) -> SO16348 | T2: =MONTH(E2) -> 1
A3: 1 | B3: SO16349 | C3: 2243313 | D3: Zijin Mining - Rosebel Goldmines N.V. | E3: 45659.435 | F3: 45660.647 | G3: 45815 | H3: Amanda Qiao | I3: USD | J3: 0.69331656 | K3: 16788.291 | L3: 0 | M3: 11639.6 | N3: 11639.6 | P3: 11639.6 | Q3: Delivered | S3: =VLOOKUP(B3,CASOPOInvCL!$B$1:$D$1600,1,FALSE) -> SO16349 | T3: =MONTH(E3) -> 1
A4: 1 | B4: SO16350 | C4: 4560061462 | D4: Alamos Gold Inc, Alamos Gold Inc Island Gold Division | E4: 45659.437 | F4: 45659.439 | G4: 45670 | H4: Ian Trottier | I4: CAD | J4: 1 | K4: 1540.6 | L4: 0 | M4: 1068.1235 | N4: 1363.36 | O4: 177.24 | P4: 1540.6 | Q4: Delivered | S4: =VLOOKUP(B4,CASOPOInvCL!$B$1:$D$1600,1,FALSE) -> SO16350 | T4: =MONTH(E4) -> 1
A5: 1 | B5: SO16353 | C5: PO-007646 | D5: Sling-Choker Manufacturing - Timmins | E5: 45659.574 | F5: 45659.707 | G5: 45673 | H5: Ian Trottier | I5: CAD | J5: 1 | K5: 2369.71 | L5: 0 | M5: 1642.9592 | N5: 2097.09 | O5: 272.62 | P5: 2369.71 | Q5: Delivered | S5: =VLOOKUP(B5,CASOPOInvCL!$B$1:$D$1600,1,FALSE) -> SO16353 | T5: =MONTH(E5) -> 1
A6: 1 | B6: SO16359 | C6: 5334612 | D6: Corrosion Fluid Products Corp., Corrosion Fluid Products Corp. - Chicago | E6: 45663.493 | F6: 45664.592 | G6: 45665 | H6: Ian Trottier | I6: USD | J6: 0.69628222 | K6: 144.20877 | L6: 0 | M6: 100.41 | N6: 100.41 | P6: 100.41 | Q6: Delivered | S6: =VLOOKUP(B6,CASOPOInvCL!$B$1:$D$1600,1,FALSE) -> SO16359 | T6: =MONTH(E6) -> 1
A7: 1 | B7: SO16360 | C7: 6633 | D7: Hyperflo | E7: 45663.509 | F7: 45663.583 | G7: 45664 | H7: Ian Trottier | I7: CAD | J7: 1 | K7: 1006.02 | L7: 0 | M7: 700.47384 | N7: 958.11 | O7: 47.91 | P7: 1006.02 | Q7: Delivered | S7: =VLOOKUP(B7,CASOPOInvCL!$B$1:$D$1600,1,FALSE) -> SO16360 | T7: =MONTH(E7) -> 1
A8: 1 | B8: SO16361 | C8: 007673 | D8: Sling-Choker Manufacturing - Timmins | E8: 45663.524 | F8: 45673.552 | G8: 45750 | H8: Ian Trottier | I8: CAD | J8: 1 | K8: 29994.38 | L8: 0 | M8: 20856.609 | N8: 26543.7 | O8: 3450.68 | P8: 29994.38 | Q8: Delivered | S8: =VLOOKUP(B8,CASOPOInvCL!$B$1:$D$1600,1,FALSE) -> SO16361 | T8: =MONTH(E8) -> 1
A9: 1 | B9: SO16362 | C9: P349617 | D9: Covia Corp - Junction City | E9: 45663.531 | F9: 45664.582 | G9: 45665 | H9: Marlen Martinez | I9: CAD | J9: 1 | K9: 8795 | L9: 0 | M9: 6131.3693 | N9: 8795 | P9: 8795 | Q9: Delivered | S9: =VLOOKUP(B9,CASOPOInvCL!$B$1:$D$1600,1,FALSE) -> SO16362 | T9: =MONTH(E9) -> 1
A10: 1 | B10: SO16363 | C10: 2961 | D10: Les Pompes du St-Laurent Inc. | E10: 45663.564 | F10: 45663.565 | G10: 45698 | H10: Ian Trottier | I10: CAD | J10: 1 | K10: 1135.51 | L10: 0 | M10: 790.63542 | N10: 1081.44 | O10: 54.07 | P10: 1135.51 | Q10: Delivered | S10: =VLOOKUP(B10,CASOPOInvCL!$B$1:$D$1600,1,FALSE) -> SO16363 | T10: =MONTH(E10) -> 1
A11: 1 | B11: SO16364 | C11: 003247 | D11: Eleazar General & Industrial Supplies Limited | E11: 45663.57 | F11: 45667.613 | G11: 45751 | H11: Ian Trottier | I11: USD | J11: 0.69455773 | K11: 1896.8762 | L11: 0 | M11: 1317.49 | N11: 1317.49 | P11: 1317.49 | Q11: Delivered | S11: =VLOOKUP(B11,CASOPOInvCL!$B$1:$D$1600,1,FALSE) -> SO16364 | T11: =MONTH(E11) -> 1
A12: 1 | B12: SO16368 | C12: M-083469 | D12: Grant Aggregate | E12: 45663.694 | F12: 45666.408 | G12: 45667 | H12: Ian Trottier | I12: CAD | J12: 1 | K12: 17048.1 | L12: 0 | M12: 11840.89 | N12: 15086.8 | O12: 1961.3 | P12: 17048.1 | Q12: Delivered | S12: =VLOOKUP(B12,CASOPOInvCL!$B$1:$D$1600,1,FALSE) -> SO16368 | T12: =MONTH(E12) -> 1
A13: 1 | B13: SO16369 | C13: PO13146 | D13: Manufacture Sling-Choker (Val-d’Or) Ltée | E13: 45664.409 | F13: 45664.622 | G13: 45665 | H13: Ian Trottier | I13: CAD | J13: 1 | K13: 117.99 | L13: 0 | M13: 82.255857 | N13: 112.37 | O13: 5.62 | P13: 117.99 | Q13: Delivered | S13: =VLOOKUP(B13,CASOPOInvCL!$B$1:$D$1600,1,FALSE) -> SO16369 | T13: =MONTH(E13) -> 1
A14: 1 | B14: SO16372 | C14: 2991 | D14: Les Pompes du St-Laurent Inc. | E14: 45664.491 | F14: 45673.632 | G14: 45720 | H14: Ian Trottier | I14: CAD | J14: 1 | K14: 1657.93 | L14: 0 | M14: 1152.8426 | N14: 1578.98 | O14: 78.95 | P14: 1657.93 | Q14: Delivered | S14: =VLOOKUP(B14,CASOPOInvCL!$B$1:$D$1600,1,FALSE) -> SO16372 | T14: =MONTH(E14) -> 1
A15: 1 | B15: SO16374 | C15: 2967 | D15: Les Pompes du St-Laurent Inc. | E15: 45664.533 | F15: 45665.677 | G15: 45666 | H15: Ian Trottier | I15: CAD | J15: 1 | K15: 3783.15 | L15: 0 | M15: 2631.4956 | N15: 3603 | O15: 180.15 | P15: 3783.15 | Q15: Delivered | S15: =VLOOKUP(B15,CASOPOInvCL!$B$1:$D$1600,1,FALSE) -> SO16374 | T15: =MONTH(E15) -> 1
A16: 1 | B16: SO16375 | C16: P349794 | D16: Covia Corp - Junction City | E16: 45664.545 | F16: 45665.577 | G16: 45666 | H16: Marlen Martinez | I16: CAD | J16: 1 | K16: 5506 | L16: 0 | M16: 3829.8811 | N16: 5506 | P16: 5506 | Q16: Delivered | S16: =VLOOKUP(B16,CASOPOInvCL!$B$1:$D$1600,1,FALSE) -> SO16375 | T16: =MONTH(E16) -> 1
A17: 1 | B17: SO16376 | C17: 007656 | D17: Sling-Choker Manufacturing - Timmins | E17: 45664.556 | F17: 45664.682 | G17: 45326 | H17: Ian Trottier | I17: CAD | J17: 1 | K17: 13951.67 | L17: 0 | M17: 9726.3036 | N17: 12346.61 | O17: 1605.06 | P17: 13951.67 | Q17: Delivered | S17: =VLOOKUP(B17,CASOPOInvCL!$B$1:$D$1600,1,FALSE) -> SO16376 | T17: =MONTH(E17) -> 1
A18: 1 | B18: SO16377 | C18: 316223 | D18: Gibraltar Mine (Canada) | E18: 45664.681 | F18: 45664.716 | G18: 45706 | H18: Ian Trottier | I18: CAD | J18: 1 | K18: 5367.86 | L18: 0 | M18: 3742.1639 | N18: 5112.25 | O18: 255.61 | P18: 5367.86 | Q18: Delivered | S18: =VLOOKUP(B18,CASOPOInvCL!$B$1:$D$1600,1,FALSE) -> SO16377 | T18: =MONTH(E18) -> 1
A19: 1 | B19: SO16378 | C19: BC78-00052101 | D19: Motion Industries Inc. (Canada) - Quesnel | E19: 45664.694 | F19: 45665.391 | G19: 45693 | H19: Ian Trottier | I19: CAD | J19: 1 | K19: 1036.94 | L19: 0 | M19: 721.27805 | N19: 987.57 | O19: 49.37 | P19: 1036.94 | Q19: Delivered | S19: =VLOOKUP(B19,CASOPOInvCL!$B$1:$D$1600,1,FALSE) -> SO16378 | T19: =MONTH(E19) -> 1
A20: 1 | B20: SO16379 | C20: PO-007657 | D20: Sling-Choker Manufacturing - Timmins | E20: 45665.302 | F20: 45665.377 | G20: 45665 | H20: Taylor Cook | I20: CAD | J20: 1 | K20: 2007.42 | L20: 0 | M20: 1396.3276 | N20: 1776.49 | O20: 230.93 | P20: 2007.42 | Q20: Delivered | S20: =VLOOKUP(B20,CASOPOInvCL!$B$1:$D$1600,1,FALSE) -> SO16379 | T20: =MONTH(E20) -> 1
A21: 3 | B21: SO16380 | C21: L63079-DS | D21: Wild Rows Pump & Compression LTD. | E21: 45665.427 | F21: 45665.651 | G21: 45777 | H21: Taylor Cook | I21: CAD | J21: 1 | K21: 4153.74 | L21: 0 | M21: 2889.2718 | N21: 3955.95 | O21: 197.79 | P21: 4153.74 | Q21: Delivered | S21: =VLOOKUP(B21,CASOPOInvCL!$B$1:$D$1600,1,FALSE) -> SO16380 | T21: =MONTH(E21) -> 1
A22: 1 | B22: SO16381 | C22: 6642 | D22: Hyperflo | E22: 45665.433 | F22: 45665.477 | G22: 45666 | H22: Ian Trottier | I22: CAD | J22: 1 | K22: 962.42 | L22: 0 | M22: 669.44319 | N22: 916.59 | O22: 45.83 | P22: 962.42 | Q22: Delivered | S22: =VLOOKUP(B22,CASOPOInvCL!$B$1:$D$1600,1,FALSE) -> SO16381 | T22: =MONTH(E22) -> 1
A23: 1 | B23: SO16382 | C23: 071736 | D23: Hoffman-Kane Distributors, Inc. | E23: 45665.456 | F23: 45665.459 | G23: 45666 | H23: Ian Trottier | I23: USD | J23: 0.69714261 | K23: 197.62097 | L23: 0 | M23: 137.77 | N23: 137.77 | P23: 137.77 | Q23: Delivered | S23: =VLOOKUP(B23,CASOPOInvCL!$B$1:$D$1600,1,FALSE) -> SO16382 | T23: =MONTH(E23) -> 1
A24: 1 | B24: SO16383 | C24: 4501080579 | D24: Barrick Gold - Pueblo Viejo Dominicana Corporation | E24: 45665.47 | F24: 45666.818 | G24: 45665 | H24: Jeff Bell | I24: USD | J24: 0.6955832 | K24: 15727.809 | L24: 0 | M24: 10940 | N24: 10940 | P24: 10940 | Q24: Delivered | S24: =VLOOKUP(B24,CASOPOInvCL!$B$1:$D$1600,1,FALSE) -> SO16383 | T24: =MONTH(E24) -> 1
A25: 1 | B25: SO16384 | C25: 2968 | D25: Les Pompes du St-Laurent Inc. | E25: 45665.494 | F25: 45665.681 | G25: 45791 | H25: Ian Trottier | I25: CAD | J25: 1 | K25: 2094.52 | L25: 0 | M25: 1456.9129 | N25: 1994.78 | O25: 99.74 | P25: 2094.52 | Q25: Delivered | S25: =VLOOKUP(B25,CASOPOInvCL!$B$1:$D$1600,1,FALSE) -> SO16384 | T25: =MONTH(E25) -> 1
A26: 1 | B26: SO16385 | C26: 11627 | D26: Les Pompes Diaspec Inc. | E26: 45665.501 | F26: 45686.418 | G26: 45687 | H26: Ian Trottier | I26: CAD | J26: 1 | K26: 12217.92 | L26: 12217.92 | M26: 12217.92 | N26: 11636.11 | O26: 581.81 | P26: 12217.92 | Q26: Delivered | S26: =VLOOKUP(B26,CASOPOInvCL!$B$1:$D$1600,1,FALSE) -> SO16385 | T26: =MONTH(E26) -> 1
A27: 1 | B27: SO16389 | C27: 6645 | D27: Hyperflo | E27: 45665.569 | F27: 45665.636 | G27: 45666 | H27: Taylor Cook | I27: CAD | J27: 1 | K27: 224.6 | L27: 0 | M27: 156.22799 | N27: 213.9 | O27: 10.7 | P27: 224.6 | Q27: Delivered | S27: =VLOOKUP(B27,CASOPOInvCL!$B$1:$D$1600,1,FALSE) -> SO16389 | T27: =MONTH(E27) -> 1
A28: 2 | B28: SO16390 | C28: 2969 | D28: Les Pompes du St-Laurent Inc. | E28: 45665.671 | F28: 45665.674 | G28: 45688 | H28: Ian Trottier | I28: CAD | J28: 1 | K28: 972.43 | L28: 0 | M28: 676.40597 | N28: 926.12 | O28: 46.31 | P28: 972.43 | Q28: Delivered | S28: =VLOOKUP(B28,CASOPOInvCL!$B$1:$D$1600,1,FALSE) -> SO16390 | T28: =MONTH(E28) -> 1
A29: 1 | B29: SO16392 | C29: 4500574897 | D29: Resolute Forest Products - Kenogami | E29: 45666.438 | F29: 45671.64 | G29: 45744 | H29: Ian Trottier | I29: CAD | J29: 1 | K29: 7778.54 | L29: 0 | M29: 5412.4629 | N29: 7408.13 | O29: 370.41 | P29: 7778.54 | Q29: Delivered | S29: =VLOOKUP(B29,CASOPOInvCL!$B$1:$D$1600,1,FALSE) -> SO16392 | T29: =MONTH(E29) -> 1
A30: 2 | B30: SO16393 | C30: 2051 | D30: FMI Products | E30: 45666.497 | F30: 45671.44 | G30: 45706 | H30: Ian Trottier | I30: CAD | J30: 1 | K30: 2482.17 | L30: 0 | M30: 1727.1433 | N30: 2363.97 | O30: 118.2 | P30: 2482.17 | Q30: Delivered | S30: =VLOOKUP(B30,CASOPOInvCL!$B$1:$D$1600,1,FALSE) -> SO16393 | T30: =MONTH(E30) -> 1
A31: 1 | B31: SO16397 | C31: 5345945 | D31: Corrosion Fluid Products Corp. | E31: 45666.711 | F31: 45719.694 | G31: 45733 | H31: Ian Trottier | I31: USD | J31: 0.69136666 | K31: 1339.7088 | L31: 0 | M31: 926.23 | N31: 926.23 | P31: 926.23 | Q31: Delivered | S31: =VLOOKUP(B31,CASOPOInvCL!$B$1:$D$1600,1,FALSE) -> SO16397 | T31: =MONTH(E31) -> 1
A32: 1 | B32: SO16399 | C32: 08840 | D32: Tantalum Mining Corporation of Canada | E32: 45667.393 | F32: 45672.575 | G32: 45673 | H32: Taylor Cook | I32: CAD | J32: 1 | K32: 904.12 | L32: 904.12 | M32: 904.12 | N32: 861.07 | O32: 43.05 | P32: 904.12 | Q32: Delivered | S32: =VLOOKUP(B32,CASOPOInvCL!$B$1:$D$1600,1,FALSE) -> SO16399 | T32: =MONTH(E32) -> 1
A33: 1 | B33: SO16400 | C33: 9569096 | D33: DXP Enterprises, Inc. - Pumping Solutions, Inc. - Hayward California | E33: 45667.397 | F33: 45672.521 | G33: 45707 | H33: Taylor Cook | I33: USD | J33: 0.6958199 | K33: 3105.4444 | L33: 0 | M33: 2160.83 | N33: 2160.83 | P33: 2160.83 | Q33: Delivered | S33: =VLOOKUP(B33,CASOPOInvCL!$B$1:$D$1600,1,FALSE) -> SO16400 | T33: =MONTH(E33) -> 1
A34: 1 | B34: SO16401 | C34: FC10-00114698 | D34: Motion Industries Inc. (U.S.) - Lakeland | E34: 45667.413 | F34: 45670.587 | G34: 45671 | H34: Taylor Cook | I34: USD | J34: 0.69462239 | K34: 120.92901 | L34: 0 | M34: 84 | N34: 84 | P34: 84 | Q34: Delivered | S34: =VLOOKUP(B34,CASOPOInvCL!$B$1:$D$1600,1,FALSE) -> SO16401 | T34: =MONTH(E34) -> 1
A35: 1 | B35: SO16402 | C35: 2243614 | D35: Zijin Mining - Rosebel Goldmines N.V. | E35: 45667.485 | F35: 45670.436 | G35: 45710 | H35: Amanda Qiao | I35: USD | J35: 0.69462239 | K35: 5373.711 | L35: 0 | M35: 3732.7 | N35: 3732.7 | P35: 3732.7 | Q35: Delivered | S35: =VLOOKUP(B35,CASOPOInvCL!$B$1:$D$1600,1,FALSE) -> SO16402 | T35: =MONTH(E35) -> 1
A36: 1 | B36: SO16403 | C36: MB21-00185834 | D36: Motion Industries Inc. (Canada) - Winnipeg | E36: 45667.524 | F36: 45667.608 | G36: 45670 | H36: Taylor Cook | I36: CAD | J36: 1 | K36: 540.3 | L36: 0 | M36: 374.24329 | N36: 540.3 | P36: 540.3 | Q36: Delivered | S36: =VLOOKUP(B36,CASOPOInvCL!$B$1:$D$1600,1,FALSE) -> SO16403 | T36: =MONTH(E36) -> 1
A37: 1 | B37: SO16405 | C37: 2100484115 | D37: Wajax Limited - Sorel-Tracy | E37: 45667.625 | F37: 45667.701 | G37: 45670 | H37: Taylor Cook | I37: CAD | J37: 1 | K37: 2138.66 | L37: 0 | M37: 1481.3607 | N37: 2036.82 | O37: 101.84 | P37: 2138.66 | Q37: Delivered | S37: =VLOOKUP(B37,CASOPOInvCL!$B$1:$D$1600,1,FALSE) -> SO16405 | T37: =MONTH(E37) -> 1
A38: 1 | B38: SO16406 | C38: 2981 | D38: Les Pompes du St-Laurent Inc. | E38: 45667.649 | F38: 45670.593 | G38: 45698 | H38: Ian Trottier | I38: CAD | J38: 1 | K38: 2358.51 | L38: 0 | M38: 1636.6784 | N38: 2246.2 | O38: 112.31 | P38: 2358.51 | Q38: Delivered | S38: =VLOOKUP(B38,CASOPOInvCL!$B$1:$D$1600,1,FALSE) -> SO16406 | T38: =MONTH(E38) -> 1
A39: 1 | B39: SO16408 | C39: P-11425 | D39: Cartledge & Associates Inc. | E39: 45670.403 | F39: 45671.538 | G39: 45672 | H39: Ian Trottier | I39: USD | J39: 0.6939459 | K39: 4614.279 | L39: 0 | M39: 3202.06 | N39: 3202.06 | P39: 3202.06 | Q39: Delivered | S39: =VLOOKUP(B39,CASOPOInvCL!$B$1:$D$1600,1,FALSE) -> SO16408 | T39: =MONTH(E39) -> 1
A40: 1 | B40: SO16409 | C40: PO-038220 | D40: Southeast Pump Specialist, Inc. | E40: 45670.409 | F40: 45670.43 | G40: 45671 | H40: Ian Trottier | I40: USD | J40: 0.69462239 | K40: 4344.1589 | L40: 0 | M40: 3017.55 | N40: 3017.55 | P40: 3017.55 | Q40: Delivered | S40: =VLOOKUP(B40,CASOPOInvCL!$B$1:$D$1600,1,FALSE) -> SO16409 | T40: =MONTH(E40) -> 1
A41: 1 | B41: SO16411 | C41: 2982 | D41: Les Pompes du St-Laurent Inc. | E41: 45670.481 | F41: 45670.62 | G41: 45671 | H41: Ian Trottier | I41: CAD | J41: 1 | K41: 2776.1 | L41: 0 | M41: 1926.4632 | N41: 2643.9 | O41: 132.2 | P41: 2776.1 | Q41: Delivered | S41: =VLOOKUP(B41,CASOPOInvCL!$B$1:$D$1600,1,FALSE) -> SO16411 | T41: =MONTH(E41) -> 1
A42: 1 | B42: SO16412 | C42: 4500554481 | D42: Glencore Canada Corporation - Rouyn-Noranda, Glencore Canada Corp. | E42: 45670.526 | F42: 45670.532 | G42: 45670 | H42: Ian Trottier | I42: CAD | J42: 1 | K42: 2453.49 | L42: 0 | M42: 1702.5893 | N42: 2336.66 | O42: 116.83 | P42: 2453.49 | Q42: Delivered | S42: =VLOOKUP(B42,CASOPOInvCL!$B$1:$D$1600,1,FALSE) -> SO16412 | T42: =MONTH(E42) -> 1
A43: 1 | B43: SO16413 | C43: AZ52-00108614 | D43: Motion Industries Inc. (U.S.) - Tucson | E43: 45670.539 | F43: 45671.513 | G43: 45672 | H43: Ian Trottier | I43: USD | J43: 0.6939459 | K43: 478.65402 | L43: 0 | M43: 332.16 | N43: 332.16 | P43: 332.16 | Q43: Delivered | S43: =VLOOKUP(B43,CASOPOInvCL!$B$1:$D$1600,1,FALSE) -> SO16413 | T43: =MONTH(E43) -> 1
A44: 1 | B44: SO16414 | C44: 0203793 - JRF | D44: Electric Pump | E44: 45670.543 | F44: 45674.552 | G44: 45676 | H44: Taylor Cook | I44: USD | J44: 0.69535056 | K44: 102.85459 | L44: 0 | M44: 71.52 | N44: 71.52 | P44: 71.52 | Q44: Delivered | S44: =VLOOKUP(B44,CASOPOInvCL!$B$1:$D$1600,1,FALSE) -> SO16414 | T44: =MONTH(E44) -> 1
A45: 1 | B45: SO16417 | C45: 1042 | D45: Mill-Right Mine Services Inc. | E45: 45670.66 | F45: 45672.474 | G45: 45749 | H45: Jeff Bell | I45: USD | J45: 0.6958199 | K45: 5734.2425 | L45: 0 | M45: 3990 | N45: 3990 | P45: 3990 | Q45: Delivered | S45: =VLOOKUP(B45,CASOPOInvCL!$B$1:$D$1600,1,FALSE) -> SO16417 | T45: =MONTH(E45) -> 1
A46: 1 | B46: SO16422 | C46: 316424 | D46: Gibraltar Mine (Canada) | E46: 45671.433 | F46: 45671.691 | G46: 45727 | H46: Ian Trottier | I46: CAD | J46: 1 | K46: 6106.39 | L46: 0 | M46: 4248.9477 | N46: 5815.61 | O46: 290.78 | P46: 6106.39 | Q46: Delivered | S46: =VLOOKUP(B46,CASOPOInvCL!$B$1:$D$1600,1,FALSE) -> SO16422 | T46: =MONTH(E46) -> 1
A47: 1 | B47: SO16423 | C47: P350633 | D47: Covia Corp - Camden | E47: 45671.519 | F47: 45673.685 | G47: 45677 | H47: Marlen Martinez | I47: CAD | J47: 1 | K47: 5986 | L47: 0 | M47: 4162.3685 | N47: 5986 | P47: 5986 | Q47: Delivered | S47: =VLOOKUP(B47,CASOPOInvCL!$B$1:$D$1600,1,FALSE) -> SO16423 | T47: =MONTH(E47) -> 1
A48: 1 | B48: SO16424 | C48: M-083550 | D48: Grant Aggregate | E48: 45671.533 | F48: 45698.559 | G48: 45699 | H48: Ian Trottier | I48: CAD | J48: 1 | K48: 24293.77 | L48: 0 | M48: 16965.429 | N48: 21498.92 | O48: 2794.85 | P48: 24293.77 | Q48: Delivered | S48: =VLOOKUP(B48,CASOPOInvCL!$B$1:$D$1600,1,FALSE) -> SO16424 | T48: =MONTH(E48) -> 1
A49: 1 | B49: SO16426 | C49: 16114 - Paid in Full $956.16 on February 28th 2025. | D49: Industrial Rigging & Supply | E49: 45671.563 | F49: 45715.641 | G49: 45716 | H49: Ian Trottier | I49: CAD | J49: 1 | K49: 956.16 | L49: 0 | M49: 663.0616 | N49: 846.16 | O49: 110 | P49: 956.16 | Q49: Delivered | S49: =VLOOKUP(B49,CASOPOInvCL!$B$1:$D$1600,1,FALSE) -> SO16426 | T49: =MONTH(E49) -> 1
A50: 1 | B50: SO16427 | C50: 6662 | D50: Hyperflo | E50: 45671.576 | F50: 45672.537 | G50: 45749 | H50: Ian Trottier | I50: CAD | J50: 1 | K50: 5081.07 | L50: 5081.07 | M50: 5081.07 | N50: 4839.11 | O50: 241.96 | P50: 5081.07 | Q50: Delivered | S50: =VLOOKUP(B50,CASOPOInvCL!$B$1:$D$1600,1,FALSE) -> SO16427 | T50: =MONTH(E50) -> 1
A51: 1 | B51: SO16429 | C51: 13188 | D51: Manufacture Sling-Choker (Val-d’Or) Ltée | E51: 45671.673 | F51: 45672.589 | G51: 45673 | H51: Taylor Cook | I51: CAD | J51: 1 | K51: 917.08 | L51: 917.08 | M51: 917.08 | N51: 873.41 | O51: 43.67 | P51: 917.08 | Q51: Delivered | S51: =VLOOKUP(B51,CASOPOInvCL!$B$1:$D$1600,1,FALSE) -> SO16429 | T51: =MONTH(E51) -> 1
A52: 0 | B52: SO16430 | C52: 3374 | D52: Les Pompes du St-Laurent Inc. | E52: 45671.754 | F52: 45961.598 | G52: 46045 | H52: Ian Trottier | I52: CAD | J52: 1 | K52: 12682.02 | L52: 0 | M52: 9050.9156 | N52: 12078.11 | O52: 603.91 | P52: 12682.02 | Q52: Processing | S52: =VLOOKUP(B52,CASOPOInvCL!$B$1:$D$1600,1,FALSE) -> SO16430 | T52: =MONTH(E52) -> 1
A53: 1 | B53: SO16432 | C53: OP-1500441 | D53: Agnico Eagle Mines Ltd. - Rouyn-Noranda, LaRonde secteur Penna (11102) | E53: 45672.439 | F53: 45679.399 | G53: 45680 | H53: Ian Trottier | I53: CAD | J53: 1 | K53: 523.72 | L53: 523.72 | M53: 523.72 | N53: 498.78 | O53: 24.94 | P53: 523.72 | Q53: Delivered | S53: =VLOOKUP(B53,CASOPOInvCL!$B$1:$D$1600,1,FALSE) -> SO16432 | T53: =MONTH(E53) -> 1
A54: 1 | B54: SO16433 | C54: 03260 | D54: Eleazar General & Industrial Supplies Limited | E54: 45672.525 | F54: 45684.628 | G54: 45685 | H54: Ian Trottier | I54: USD | J54: 0.69723104 | K54: 4777.1969 | L54: 0 | M54: 3330.81 | N54: 3330.81 | P54: 3330.81 | Q54: Delivered | S54: =VLOOKUP(B54,CASOPOInvCL!$B$1:$D$1600,1,FALSE) -> SO16433 | T54: =MONTH(E54) -> 1
A55: 1 | B55: SO16434 | C55: 6335 | D55: ProPart Pompes du Canada 9425-4380 Quebec Inc | E55: 45672.552 | F55: 45684.574 | G55: 45685 | H55: Ian Trottier | I55: CAD | J55: 1 | K55: 5733.49 | L55: 0 | M55: 3984.3183 | N55: 5460.46 | O55: 273.03 | P55: 5733.49 | Q55: Delivered | S55: =VLOOKUP(B55,CASOPOInvCL!$B$1:$D$1600,1,FALSE) -> SO16434 | T55: =MONTH(E55) -> 1
A56: 1 | B56: SO16435 | C56: 2100393819 | D56: Wajax Limited - Noranda | E56: 45672.552 | F56: 45672.641 | G56: 45673 | H56: Ian Trottier | I56: CAD | J56: 1 | K56: 2043.9 | L56: 2043.9 | M56: 2043.9 | N56: 1946.57 | O56: 97.33 | P56: 2043.9 | Q56: Delivered | S56: =VLOOKUP(B56,CASOPOInvCL!$B$1:$D$1600,1,FALSE) -> SO16435 | T56: =MONTH(E56) -> 1
A57: 1 | B57: SO16436 | C57: 5337984 | D57: Pierce Pump Company, Pierce Pump Company | E57: 45672.678 | F57: 45674.644 | G57: 45677 | H57: Ian Trottier | I57: USD | J57: 0.69535056 | K57: 2360.8667 | L57: 0 | M57: 1641.63 | N57: 1641.63 | P57: 1641.63 | Q57: Delivered | S57: =VLOOKUP(B57,CASOPOInvCL!$B$1:$D$1600,1,FALSE) -> SO16436 | T57: =MONTH(E57) -> 1
A58: 1 | B58: SO16437 | D58: Maham LLC | E58: 45672.717 | F58: 45707.601 | G58: 45709 | H58: Ian Trottier | I58: USD | J58: 0.70492347 | K58: 29586.19 | L58: 0 | M58: 20856 | N58: 20856 | P58: 20856 | Q58: Delivered | S58: =VLOOKUP(B58,CASOPOInvCL!$B$1:$D$1600,1,FALSE) -> SO16437 | T58: =MONTH(E58) -> 1
A59: 2 | B59: SO16438 | C59: 40-1012291 | D59: Canadian Bearings Ltd. | E59: 45673.429 | F59: 45674.729 | G59: 45695 | H59: Ian Trottier | I59: CAD | J59: 1 | K59: 702.05 | L59: 0 | M59: 486.7454 | N59: 621.28 | O59: 80.77 | P59: 702.05 | Q59: Delivered | S59: =VLOOKUP(B59,CASOPOInvCL!$B$1:$D$1600,1,FALSE) -> SO16438 | T59: =MONTH(E59) -> 1
A60: 1 | B60: SO16440 | C60: SUD1005983 | D60: Process and Steam Specialties, Process and Steam Specialties | E60: 45673.599 | F60: 45674.702 | G60: 45727 | H60: Ian Trottier | I60: CAD | J60: 1 | K60: 386.38 | L60: 0 | M60: 267.88504 | N60: 386.38 | P60: 386.38 | Q60: Delivered | S60: =VLOOKUP(B60,CASOPOInvCL!$B$1:$D$1600,1,FALSE) -> SO16440 | T60: =MONTH(E60) -> 1
A61: 1 | B61: SO16446 | C61: 2100488794 | D61: Wajax Limited - Timmins | E61: 45674.554 | F61: 45674.556 | G61: 45695 | H61: Ian Trottier | I61: CAD | J61: 1 | K61: 1693.27 | L61: 0 | M61: 1173.9782 | N61: 1498.47 | O61: 194.8 | P61: 1693.27 | Q61: Delivered | S61: =VLOOKUP(B61,CASOPOInvCL!$B$1:$D$1600,1,FALSE) -> SO16446 | T61: =MONTH(E61) -> 1
A62: 1 | B62: SO16448 | C62: 2885 | D62: Les Pompes du St-Laurent Inc. | E62: 45674.677 | F62: 45674.683 | G62: 45702 | H62: Ian Trottier | I62: CAD | J62: 1 | K62: 326.5 | L62: 0 | M62: 226.36903 | N62: 310.95 | O62: 15.55 | P62: 326.5 | Q62: Delivered | S62: =VLOOKUP(B62,CASOPOInvCL!$B$1:$D$1600,1,FALSE) -> SO16448 | T62: =MONTH(E62) -> 1
A63: 1 | B63: SO16449 | C63: BC65-00079319 | D63: Motion Industries Inc. (Canada) - Prince George | E63: 45674.743 | F63: 45680.694 | G63: 45681 | H63: Taylor Cook | I63: CAD | J63: 1 | K63: 12661.94 | L63: 0 | M63: 8817.2283 | N63: 12059 | O63: 602.94 | P63: 12661.94 | Q63: Delivered | S63: =VLOOKUP(B63,CASOPOInvCL!$B$1:$D$1600,1,FALSE) -> SO16449 | T63: =MONTH(E63) -> 1
A64: 1 | B64: SO16451 | C64: 4511512958 | D64: PT Vale Indonesia Tbk. | E64: 45677.476 | F64: 45677.477 | G64: 45678 | H64: Ian Trottier | I64: USD | J64: 0.69062015 | K64: 2835.0027 | L64: 0 | M64: 1957.91 | N64: 1957.91 | P64: 1957.91 | Q64: Delivered | S64: =VLOOKUP(B64,CASOPOInvCL!$B$1:$D$1600,1,FALSE) -> SO16451 | T64: =MONTH(E64) -> 1
A65: 1 | B65: SO16452 | C65: 4511512957 | D65: PT Vale Indonesia Tbk. | E65: 45677.488 | F65: 45677.489 | G65: 45678 | H65: Ian Trottier | I65: USD | J65: 0.69062015 | K65: 3716.8478 | L65: 0 | M65: 2566.93 | N65: 2566.93 | P65: 2566.93 | Q65: Delivered | S65: =VLOOKUP(B65,CASOPOInvCL!$B$1:$D$1600,1,FALSE) -> SO16452 | T65: =MONTH(E65) -> 1
A66: 1 | B66: SO16453 | C66: 4511512959 | D66: PT Vale Indonesia Tbk. | E66: 45677.493 | F66: 45677.494 | G66: 45678 | H66: Ian Trottier | I66: USD | J66: 0.69062015 | K66: 2728.9821 | L66: 0 | M66: 1884.69 | N66: 1884.69 | P66: 1884.69 | Q66: Delivered | S66: =VLOOKUP(B66,CASOPOInvCL!$B$1:$D$1600,1,FALSE) -> SO16453 | T66: =MONTH(E66) -> 1
A67: 1 | B67: SO16455 | C67: 63-02681 | D67: Quality Concrete Inc. | E67: 45677.629 | F67: 45679.703 | G67: 45805 | H67: Ian Trottier | I67: CAD | J67: 1 | K67: 25712.4 | L67: 25712.4 | M67: 25712.4 | N67: 24488 | O67: 1224.4 | P67: 25712.4 | Q67: Delivered | S67: =VLOOKUP(B67,CASOPOInvCL!$B$1:$D$1600,1,FALSE) -> SO16455 | T67: =MONTH(E67) -> 1
A68: 1 | B68: SO16457 | C68: 2100491932 | D68: Wajax Limited - Pointe-aux-Trembles, Wajax Limited | E68: 45677.656 | F68: 45679.387 | G68: 45680 | H68: Ian Trottier | I68: CAD | J68: 1 | K68: 243.8 | L68: 243.8 | M68: 243.8 | N68: 232.19 | O68: 11.61 | P68: 243.8 | Q68: Delivered | S68: =VLOOKUP(B68,CASOPOInvCL!$B$1:$D$1600,1,FALSE) -> SO16457 | T68: =MONTH(E68) -> 1
A69: 1 | B69: SO16462 | C69: 3071 | D69: Les Pompes du St-Laurent Inc. | E69: 45678.375 | F69: 45714.687 | G69: 45715 | H69: Ian Trottier | I69: CAD | J69: 1 | K69: 2023.65 | L69: 0 | M69: 1410.3205 | N69: 1927.29 | O69: 96.36 | P69: 2023.65 | Q69: Delivered | S69: =VLOOKUP(B69,CASOPOInvCL!$B$1:$D$1600,1,FALSE) -> SO16462 | T69: =MONTH(E69) -> 1
A70: 1 | B70: SO16464 | C70: 6686 | D70: Hyperflo | E70: 45678.391 | F70: 45678.625 | G70: 45679 | H70: Ian Trottier | I70: CAD | J70: 1 | K70: 1250.9 | L70: 0 | M70: 872.80937 | N70: 1191.33 | O70: 59.57 | P70: 1250.9 | Q70: Delivered | S70: =VLOOKUP(B70,CASOPOInvCL!$B$1:$D$1600,1,FALSE) -> SO16464 | T70: =MONTH(E70) -> 1
A71: 1 | B71: SO16466 | C71: 107881 | D71: Allen Bearings & Technologies Ltd. | E71: 45678.453 | F71: 45679.719 | G71: 45681 | H71: Taylor Cook | I71: CAD | J71: 1 | K71: 2386.02 | L71: 2386.02 | M71: 2386.02 | N71: 2272.41 | O71: 113.61 | P71: 2386.02 | Q71: Delivered | S71: =VLOOKUP(B71,CASOPOInvCL!$B$1:$D$1600,1,FALSE) -> SO16466 | T71: =MONTH(E71) -> 1
A72: 3 | B72: SO16467 | C72: L63301-DS | D72: Wild Rows Pump & Compression LTD. | E72: 45678.482 | F72: 45678.612 | G72: 45790 | H72: Taylor Cook | I72: CAD | J72: 1 | K72: 1078.24 | L72: 0 | M72: 752.3367 | N72: 1026.9 | O72: 51.34 | P72: 1078.24 | Q72: Delivered | S72: =VLOOKUP(B72,CASOPOInvCL!$B$1:$D$1600,1,FALSE) -> SO16467 | T72: =MONTH(E72) -> 1
A73: 2 | B73: SO16470 | C73: 4500574503 | D73: Resolute Forest Products - Saint-Felicien | E73: 45678.534 | F73: 45678.539 | G73: 45754 | H73: Ian Trottier | I73: CAD | J73: 1 | K73: 2068.01 | L73: 0 | M73: 1442.9439 | N73: 1969.52 | O73: 98.49 | P73: 2068.01 | Q73: Delivered | S73: =VLOOKUP(B73,CASOPOInvCL!$B$1:$D$1600,1,FALSE) -> SO16470 | T73: =MONTH(E73) -> 1
A74: 1 | B74: SO16471 | C74: 007693 | D74: Sling-Choker Manufacturing - Timmins | E74: 45678.617 | F74: 45678.619 | G74: 45679 | H74: Taylor Cook | I74: CAD | J74: 1 | K74: 140.76 | L74: 0 | M74: 98.214603 | N74: 124.57 | O74: 16.19 | P74: 140.76 | Q74: Delivered | S74: =VLOOKUP(B74,CASOPOInvCL!$B$1:$D$1600,1,FALSE) -> SO16471 | T74: =MONTH(E74) -> 1
A75: 1 | B75: SO16474 | C75: MB21-00186138 | D75: Motion Industries Inc. (Canada) - Winnipeg, Motion Industries Inc. (Canada) - Winnipeg | E75: 45679.439 | F75: 45679.525 | G75: 45680 | H75: Ian Trottier | I75: CAD | J75: 1 | K75: 720.84 | L75: 720.84 | M75: 720.84 | N75: 637.91 | O75: 82.93 | P75: 720.84 | Q75: Delivered | S75: =VLOOKUP(B75,CASOPOInvCL!$B$1:$D$1600,1,FALSE) -> SO16474 | T75: =MONTH(E75) -> 1
A76: 1 | B76: SO16475 | C76: MB21-00186141 | D76: Motion Industries Inc. (Canada) - Winnipeg | E76: 45679.444 | F76: 45679.585 | G76: 45749 | H76: Ian Trottier | I76: CAD | J76: 1 | K76: 5362.74 | L76: 5362.74 | M76: 5362.74 | N76: 5107.37 | O76: 255.37 | P76: 5362.74 | Q76: Delivered | S76: =VLOOKUP(B76,CASOPOInvCL!$B$1:$D$1600,1,FALSE) -> SO16475 | T76: =MONTH(E76) -> 1
A77: 2 | B77: SO16476 | C77: 40-1012558 | D77: Canadian Bearings Ltd. | E77: 45680.388 | F77: 45685.579 | G77: 45706 | H77: Taylor Cook | I77: CAD | J77: 1 | K77: 2227.14 | L77: 0 | M77: 1547.3465 | N77: 2121.09 | O77: 106.05 | P77: 2227.14 | Q77: Delivered | S77: =VLOOKUP(B77,CASOPOInvCL!$B$1:$D$1600,1,FALSE) -> SO16476 | T77: =MONTH(E77) -> 1
A78: 1 | B78: SO16477 | C78: 10223 | D78: Canadian Industrial Pumps Ltd | E78: 45680.455 | F78: 45686.747 | G78: 45687 | H78: Taylor Cook | I78: CAD | J78: 1 | K78: 2779.84 | L78: 2779.84 | M78: 2779.84 | N78: 2779.84 | P78: 2779.84 | Q78: Delivered | S78: =VLOOKUP(B78,CASOPOInvCL!$B$1:$D$1600,1,FALSE) -> SO16477 | T78: =MONTH(E78) -> 1
A79: 1 | B79: SO16479 | C79: P351540 | D79: Covia Corp - Junction City | E79: 45680.599 | F79: 45680.596 | G79: 45688 | H79: Marlen Martinez | I79: USD | J79: 0.69635682 | K79: 6792.4946 | L79: 0 | M79: 4730 | N79: 4730 | P79: 4730 | Q79: Delivered | S79: =VLOOKUP(B79,CASOPOInvCL!$B$1:$D$1600,1,FALSE) -> SO16479 | T79: =MONTH(E79) -> 1
A80: 1 | B80: SO16481 | C80: 2200067803 | D80: Wajax Limited - Val D'Or, Composants Industriels Wajax SC -57 | E80: 45680.711 | F80: 45681.711 | G80: 45684 | H80: Taylor Cook | I80: CAD | J80: 1 | K80: 240.03 | L80: 0 | M80: 167.42385 | N80: 228.6 | O80: 11.43 | P80: 240.03 | Q80: Delivered | S80: =VLOOKUP(B80,CASOPOInvCL!$B$1:$D$1600,1,FALSE) -> SO16481 | T80: =MONTH(E80) -> 1
A81: 1 | B81: SO16482 | C81: P-12425 | D81: Cartledge & Associates Inc. | E81: 45680.716 | F81: 45681.51 | G81: 45684 | H81: Ian Trottier | I81: USD | J81: 0.69635682 | K81: 3298.8116 | L81: 0 | M81: 2297.15 | N81: 2297.15 | P81: 2297.15 | Q81: Delivered | S81: =VLOOKUP(B81,CASOPOInvCL!$B$1:$D$1600,1,FALSE) -> SO16482 | T81: =MONTH(E81) -> 1
A82: 1 | B82: SO16485 | C82: 3053 | D82: Les Pompes du St-Laurent Inc. | E82: 45681.398 | F82: 45701.527 | G82: 45722 | H82: Ian Trottier | I82: CAD | J82: 1 | K82: 2009.99 | L82: 0 | M82: 1412.4725 | N82: 1914.28 | O82: 95.71 | P82: 2009.99 | Q82: Delivered | S82: =VLOOKUP(B82,CASOPOInvCL!$B$1:$D$1600,1,FALSE) -> SO16485 | T82: =MONTH(E82) -> 1
A83: 1 | B83: SO16486 | C83: 607548 | D83: Sealtrac Inc. | E83: 45681.407 | F83: 45684.61 | G83: 45685 | H83: Ian Trottier | I83: CAD | J83: 1 | K83: 924.84 | L83: 0 | M83: 642.69004 | N83: 818.44 | O83: 106.4 | P83: 924.84 | Q83: Delivered | S83: =VLOOKUP(B83,CASOPOInvCL!$B$1:$D$1600,1,FALSE) -> SO16486 | T83: =MONTH(E83) -> 1
A84: 1 | B84: SO16488 | C84: 2100495165 | D84: Wajax Limited - Noranda, Wajax Limited - Noranda | E84: 45681.489 | F84: 45681.682 | G84: 45684 | H84: Ian Trottier | I84: CAD | J84: 1 | K84: 1501.27 | L84: 0 | M84: 1047.1541 | N84: 1429.78 | O84: 71.49 | P84: 1501.27 | Q84: Delivered | S84: =VLOOKUP(B84,CASOPOInvCL!$B$1:$D$1600,1,FALSE) -> SO16488 | T84: =MONTH(E84) -> 1
A85: 1 | B85: SO16492 | C85: 4500577484 | D85: Resolute Forest Products - Saint-Felicien | E85: 45681.547 | F85: 45684.388 | G85: 45786 | H85: Ian Trottier | I85: CAD | J85: 1 | K85: 835.92 | L85: 0 | M85: 580.89773 | N85: 796.11 | O85: 39.81 | P85: 835.92 | Q85: Delivered | S85: =VLOOKUP(B85,CASOPOInvCL!$B$1:$D$1600,1,FALSE) -> SO16492 | T85: =MONTH(E85) -> 1
A86: 1 | B86: SO16494 | C86: 21276 | D86: DRN Industriel | E86: 45681.637 | F86: 45681.639 | G86: 45758 | H86: Ian Trottier | I86: CAD | J86: 1 | K86: 1254.61 | L86: 0 | M86: 875.10578 | N86: 1194.87 | O86: 59.74 | P86: 1254.61 | Q86: Delivered | S86: =VLOOKUP(B86,CASOPOInvCL!$B$1:$D$1600,1,FALSE) -> SO16494 | T86: =MONTH(E86) -> 1
A87: 1 | B87: SO16495 | C87: 2056 | D87: FMI Products | E87: 45681.696 | F87: 45684.687 | G87: 45685 | H87: Taylor Cook | I87: CAD | J87: 1 | K87: 166.72 | L87: 0 | M87: 115.8571 | N87: 158.78 | O87: 7.94 | P87: 166.72 | Q87: Delivered | S87: =VLOOKUP(B87,CASOPOInvCL!$B$1:$D$1600,1,FALSE) -> SO16495 | T87: =MONTH(E87) -> 1
A88: 2 | B88: SO16496 | C88: 6336 | D88: ProPart Pompes du Canada 9425-4380 Quebec Inc | E88: 45684.515 | F88: 45684.524 | G88: 45705 | H88: Ian Trottier | I88: CAD | J88: 1 | K88: 9975.87 | L88: 0 | M88: 6932.4341 | N88: 9500.83 | O88: 475.04 | P88: 9975.87 | Q88: Delivered | S88: =VLOOKUP(B88,CASOPOInvCL!$B$1:$D$1600,1,FALSE) -> SO16496 | T88: =MONTH(E88) -> 1
A89: 1 | B89: SO16497 | C89: PONV-25-0210 | D89: Tech-Flow | E89: 45684.643 | F89: 45686.559 | G89: 45756 | H89: Ian Trottier | I89: USD | J89: 0.69492025 | K89: 3672.3351 | L89: 0 | M89: 2551.98 | N89: 2551.98 | P89: 2551.98 | Q89: Delivered | S89: =VLOOKUP(B89,CASOPOInvCL!$B$1:$D$1600,1,FALSE) -> SO16497 | T89: =MONTH(E89) -> 1
A90: 1 | B90: SO16498 | C90: 007708 | D90: Sling-Choker Manufacturing - Timmins | E90: 45685.307 | F90: 45685.404 | G90: 45686 | H90: Ian Trottier | I90: CAD | J90: 1 | K90: 5751.01 | L90: 0 | M90: 3995.6202 | N90: 5089.39 | O90: 661.62 | P90: 5751.01 | Q90: Delivered | S90: =VLOOKUP(B90,CASOPOInvCL!$B$1:$D$1600,1,FALSE) -> SO16498 | T90: =MONTH(E90) -> 1
A91: 1 | B91: SO16499 | C91: 6500016472 | D91: Wesdome Gold Mines Ltd - Eagle River Mine | E91: 45685.393 | F91: 45686.699 | G91: 45687 | H91: Ian Trottier | I91: CAD | J91: 1 | K91: 4138.54 | L91: 4138.54 | M91: 4138.54 | N91: 3662.42 | O91: 476.12 | P91: 4138.54 | Q91: Delivered | S91: =VLOOKUP(B91,CASOPOInvCL!$B$1:$D$1600,1,FALSE) -> SO16499 | T91: =MONTH(E91) -> 1
A92: 2 | B92: SO16501 | C92: M-083516 | D92: Grant Aggregate | E92: 45685.55 | F92: 45686.407 | G92: 45687 | H92: Ian Trottier | I92: CAD | J92: 1 | K92: 6676.97 | L92: 6676.97 | M92: 6676.97 | N92: 5908.82 | O92: 768.15 | P92: 6676.97 | Q92: To Deliver | S92: =VLOOKUP(B92,CASOPOInvCL!$B$1:$D$1600,1,FALSE) -> SO16501 | T92: =MONTH(E92) -> 1
A93: 1 | B93: SO16503 | C93: MB21-00186347 | D93: Motion Industries Inc. (Canada) - Winnipeg | E93: 45685.626 | F93: 45686.384 | G93: 45687 | H93: Taylor Cook | I93: CAD | J93: 1 | K93: 132.43 | L93: 132.43 | M93: 132.43 | N93: 126.12 | O93: 6.31 | P93: 132.43 | Q93: Delivered | S93: =VLOOKUP(B93,CASOPOInvCL!$B$1:$D$1600,1,FALSE) -> SO16503 | T93: =MONTH(E93) -> 1
A94: 1 | B94: SO16504 | C94: OC00142 | D94: Dynapro Pumps México S de RL de CV | E94: 45685.679 | F94: 45685.679 | G94: 45723 | H94: Yannett Yeomans | I94: USD | J94: 0.69492025 | K94: 661.94646 | L94: 0 | M94: 460 | N94: 460 | P94: 460 | Q94: Delivered | S94: =VLOOKUP(B94,CASOPOInvCL!$B$1:$D$1600,1,FALSE) -> SO16504 | T94: =MONTH(E94) -> 1
A95: 1 | B95: SO16505 | C95: 21292 | D95: DRN Industriel | E95: 45685.718 | F95: 45685.723 | G95: 45686 | H95: Taylor Cook | I95: CAD | J95: 1 | K95: 1254.61 | L95: 0 | M95: 871.66341 | N95: 1194.87 | O95: 59.74 | P95: 1254.61 | Q95: Delivered | S95: =VLOOKUP(B95,CASOPOInvCL!$B$1:$D$1600,1,FALSE) -> SO16505 | T95: =MONTH(E95) -> 1
A96: 1 | B96: SO16509 | C96: P351539 | D96: Covia Corp - Junction City | E96: 45686.498 | F96: 45686.498 | G96: 45686 | H96: Marlen Martinez | I96: USD | J96: 0.69492025 | K96: 5157.4263 | L96: 0 | M96: 3584 | N96: 3584 | P96: 3584 | Q96: Delivered | S96: =VLOOKUP(B96,CASOPOInvCL!$B$1:$D$1600,1,FALSE) -> SO16509 | T96: =MONTH(E96) -> 1
A97: 1 | B97: SO16511 | C97: P351588 | D97: Covia Corp - Junction City | E97: 45686.517 | F97: 45686.52 | G97: 45790 | H97: Marlen Martinez | I97: USD | J97: 0.69492025 | K97: 8749.9969 | L97: 0 | M97: 6080.55 | N97: 6080.55 | P97: 6080.55 | Q97: Delivered | S97: =VLOOKUP(B97,CASOPOInvCL!$B$1:$D$1600,1,FALSE) -> SO16511 | T97: =MONTH(E97) -> 1
A98: 1 | B98: SO16512 | C98: M-083523 | D98: Grant Aggregate | E98: 45686.567 | F98: 45687.447 | G98: 45706 | H98: Ian Trottier | I98: CAD | J98: 1 | K98: 1988.36 | L98: 0 | M98: 1379.3862 | N98: 1759.61 | O98: 228.75 | P98: 1988.36 | Q98: Delivered | S98: =VLOOKUP(B98,CASOPOInvCL!$B$1:$D$1600,1,FALSE) -> SO16512 | T98: =MONTH(E98) -> 1
A99: 2 | B99: SO16513 | C99: 3113 | D99: Les Pompes du St-Laurent Inc. | E99: 45686.582 | F99: 45747.679 | G99: 45765 | H99: Ian Trottier | I99: CAD | J99: 1 | K99: 17592.46 | L99: 0 | M99: 12257.645 | N99: 16754.72 | O99: 837.74 | P99: 17592.46 | Q99: Delivered | S99: =VLOOKUP(B99,CASOPOInvCL!$B$1:$D$1600,1,FALSE) -> SO16513 | T99: =MONTH(E99) -> 1
A100: 2 | B100: SO16515 | C100: 40-1012759 | D100: Canadian Bearings Ltd. | E100: 45686.729 | F100: 45691.599 | G100: 45747 | H100: Ian Trottier | I100: CAD | J100: 1 | K100: 1456.77 | L100: 0 | M100: 997.73293 | N100: 1387.4 | O100: 69.37 | P100: 1456.77 | Q100: Delivered | S100: =VLOOKUP(B100,CASOPOInvCL!$B$1:$D$1600,1,FALSE) -> SO16515 | T100: =MONTH(E100) -> 1
...

Sheet InvBal
A1: Zero | B1: XX
F3: Values
A4: SO | B4: INV | C4: Client | D4: Curr | E4: Paid | F4: Odoo CAD | G4: Odoo USA | H4: Xero CAD | I4: Xero USD | J4: Cur | K4: Len | L4: SO 1 | M4: CAD | N4: USD | O4: Paid | P4: Freight | Q4: Yes Two
A5: SO16380 | B5: INV12496 | C5: Wild Rows Pump & Compression LTD. | D5: CAD | E5: Yes | F5: 3955.95 | G5: 2751.6924 | H5: -1827.63 | I5: 0 | J5: =IF(K5=13,D4,"") | K5: =LEN(A5) -> 7 | L5: =IF(K5=13,LEFT(A5,7),"") | M5: =IF(AND(K5=13,D4="CAD"),ROUND(F5+H5,2),0) -> 0 | N5: =IF(AND(K5=13,D4="USD"),ROUND(G5+I5,2),0) -> 0 | O5: =IF(K5=13,IF(M5+N5=0,"Yes",0),0) -> 0 | P5: =IFERROR(VLOOKUP(B5,'Receivable Invoice Detail'!$S$1:$U$3014,3,FALSE),0) -> 0
B6: INV12584 | C6: Wild Rows Pump & Compression LTD. | D6: CAD | E6: Yes | F6: 0 | G6: 0 | H6: -857.76 | I6: 0 | J6: =IF(K6=13,D5,"") | K6: =LEN(A6) -> 0 | L6: =IF(K6=13,LEFT(A6,7),"") | M6: =IF(AND(K6=13,D5="CAD"),ROUND(F6+H6,2),0) -> 0 | N6: =IF(AND(K6=13,D5="USD"),ROUND(G6+I6,2),0) -> 0 | O6: =IF(K6=13,IF(M6+N6=0,"Yes",0),0) -> 0 | P6: =IFERROR(VLOOKUP(B6,'Receivable Invoice Detail'!$S$1:$U$3014,3,FALSE),0) -> 0
B7: INV12953 | C7: Wild Rows Pump & Compression LTD. | D7: CAD | E7: Yes | F7: 0 | G7: 0 | H7: -1270.56 | I7: 0 | J7: =IF(K7=13,D6,"") | K7: =LEN(A7) -> 0 | L7: =IF(K7=13,LEFT(A7,7),"") | M7: =IF(AND(K7=13,D6="CAD"),ROUND(F7+H7,2),0) -> 0 | N7: =IF(AND(K7=13,D6="USD"),ROUND(G7+I7,2),0) -> 0 | O7: =IF(K7=13,IF(M7+N7=0,"Yes",0),0) -> 0 | P7: =IFERROR(VLOOKUP(B7,'Receivable Invoice Detail'!$S$1:$U$3014,3,FALSE),0) -> 0
A8: SO16380 Total | F8: 3955.95 | G8: 2751.6924 | H8: -3955.95 | I8: 0 | J8: =IF(K8=13,D7,"") -> CAD | K8: =LEN(A8) -> 13 | L8: =IF(K8=13,LEFT(A8,7),"") -> SO16380 | M8: =IF(AND(K8=13,D7="CAD"),ROUND(F8+H8,2),0) -> 0 | N8: =IF(AND(K8=13,D7="USD"),ROUND(G8+I8,2),0) -> 0 | O8: =IF(K8=13,IF(M8+N8=0,"Yes",0),0) -> Yes | P8: =IFERROR(VLOOKUP(B8,'Receivable Invoice Detail'!$S$1:$U$3014,3,FALSE),0) -> 0
A9: SO16390 | B9: INV12506 | C9: Les Pompes du St-Laurent Inc. | D9: CAD | E9: Yes | F9: 0 | G9: 0 | H9: -463.06 | I9: 0 | J9: =IF(K9=13,D8,"") | K9: =LEN(A9) -> 7 | L9: =IF(K9=13,LEFT(A9,7),"") | M9: =IF(AND(K9=13,D8="CAD"),ROUND(F9+H9,2),0) -> 0 | N9: =IF(AND(K9=13,D8="USD"),ROUND(G9+I9,2),0) -> 0 | O9: =IF(K9=13,IF(M9+N9=0,"Yes",0),0) -> 0 | P9: =IFERROR(VLOOKUP(B9,'Receivable Invoice Detail'!$S$1:$U$3014,3,FALSE),0) -> 0
B10: INV12631 | C10: Les Pompes du St-Laurent Inc. | D10: CAD | E10: Yes | F10: 926.12 | G10: 644.19352 | H10: -463.06 | I10: 0 | J10: =IF(K10=13,D9,"") | K10: =LEN(A10) -> 0 | L10: =IF(K10=13,LEFT(A10,7),"") | M10: =IF(AND(K10=13,D9="CAD"),ROUND(F10+H10,2),0) -> 0 | N10: =IF(AND(K10=13,D9="USD"),ROUND(G10+I10,2),0) -> 0 | O10: =IF(K10=13,IF(M10+N10=0,"Yes",0),0) -> 0 | P10: =IFERROR(VLOOKUP(B10,'Receivable Invoice Detail'!$S$1:$U$3014,3,FALSE),0) -> 0
A11: SO16390 Total | F11: 926.12 | G11: 644.19352 | H11: -926.12 | I11: 0 | J11: =IF(K11=13,D10,"") -> CAD | K11: =LEN(A11) -> 13 | L11: =IF(K11=13,LEFT(A11,7),"") -> SO16390 | M11: =IF(AND(K11=13,D10="CAD"),ROUND(F11+H11,2),0) -> 0 | N11: =IF(AND(K11=13,D10="USD"),ROUND(G11+I11,2),0) -> 0 | O11: =IF(K11=13,IF(M11+N11=0,"Yes",0),0) -> Yes | P11: =IFERROR(VLOOKUP(B11,'Receivable Invoice Detail'!$S$1:$U$3014,3,FALSE),0) -> 0
A12: SO16393 | B12: INV12541 | C12: FMI Products | D12: CAD | E12: Yes | F12: 0 | G12: 0 | H12: -701.83 | I12: 0 | J12: =IF(K12=13,D11,"") | K12: =LEN(A12) -> 7 | L12: =IF(K12=13,LEFT(A12,7),"") | M12: =IF(AND(K12=13,D11="CAD"),ROUND(F12+H12,2),0) -> 0 | N12: =IF(AND(K12=13,D11="USD"),ROUND(G12+I12,2),0) -> 0 | O12: =IF(K12=13,IF(M12+N12=0,"Yes",0),0) -> 0 | P12: =IFERROR(VLOOKUP(B12,'Receivable Invoice Detail'!$S$1:$U$3014,3,FALSE),0) -> 0
B13: INV12704 | C13: FMI Products | D13: CAD | E13: Yes | F13: 2363.97 | G13: 1644.8974 | H13: -1662.14 | I13: 0 | J13: =IF(K13=13,D12,"") | K13: =LEN(A13) -> 0 | L13: =IF(K13=13,LEFT(A13,7),"") | M13: =IF(AND(K13=13,D12="CAD"),ROUND(F13+H13,2),0) -> 0 | N13: =IF(AND(K13=13,D12="USD"),ROUND(G13+I13,2),0) -> 0 | O13: =IF(K13=13,IF(M13+N13=0,"Yes",0),0) -> 0 | P13: =IFERROR(VLOOKUP(B13,'Receivable Invoice Detail'!$S$1:$U$3014,3,FALSE),0) -> 0
A14: SO16393 Total | F14: 2363.97 | G14: 1644.8974 | H14: -2363.97 | I14: 0 | J14: =IF(K14=13,D13,"") -> CAD | K14: =LEN(A14) -> 13 | L14: =IF(K14=13,LEFT(A14,7),"") -> SO16393 | M14: =IF(AND(K14=13,D13="CAD"),ROUND(F14+H14,2),0) -> 0 | N14: =IF(AND(K14=13,D13="USD"),ROUND(G14+I14,2),0) -> 0 | O14: =IF(K14=13,IF(M14+N14=0,"Yes",0),0) -> Yes | P14: =IFERROR(VLOOKUP(B14,'Receivable Invoice Detail'!$S$1:$U$3014,3,FALSE),0) -> 0
A15: SO16438 | B15: INV12550 | C15: Canadian Bearings Ltd. | D15: CAD | E15: Yes | F15: 621.28 | G15: 430.74594 | H15: -587.3 | I15: 0 | J15: =IF(K15=13,D14,"") | K15: =LEN(A15) -> 7 | L15: =IF(K15=13,LEFT(A15,7),"") | M15: =IF(AND(K15=13,D14="CAD"),ROUND(F15+H15,2),0) -> 0 | N15: =IF(AND(K15=13,D14="USD"),ROUND(G15+I15,2),0) -> 0 | O15: =IF(K15=13,IF(M15+N15=0,"Yes",0),0) -> 0 | P15: =IFERROR(VLOOKUP(B15,'Receivable Invoice Detail'!$S$1:$U$3014,3,FALSE),0) -> 0
B16: INV12677 | C16: Canadian Bearings Ltd. | D16: CAD | E16: Yes | F16: 0 | G16: 0 | H16: -33.98 | I16: 0 | J16: =IF(K16=13,D15,"") | K16: =LEN(A16) -> 0 | L16: =IF(K16=13,LEFT(A16,7),"") | M16: =IF(AND(K16=13,D15="CAD"),ROUND(F16+H16,2),0) -> 0 | N16: =IF(AND(K16=13,D15="USD"),ROUND(G16+I16,2),0) -> 0 | O16: =IF(K16=13,IF(M16+N16=0,"Yes",0),0) -> 0 | P16: =IFERROR(VLOOKUP(B16,'Receivable Invoice Detail'!$S$1:$U$3014,3,FALSE),0) -> 0
A17: SO16438 Total | F17: 621.28 | G17: 430.74594 | H17: -621.28 | I17: 0 | J17: =IF(K17=13,D16,"") -> CAD | K17: =LEN(A17) -> 13 | L17: =IF(K17=13,LEFT(A17,7),"") -> SO16438 | M17: =IF(AND(K17=13,D16="CAD"),ROUND(F17+H17,2),0) -> 0 | N17: =IF(AND(K17=13,D16="USD"),ROUND(G17+I17,2),0) -> 0 | O17: =IF(K17=13,IF(M17+N17=0,"Yes",0),0) -> Yes | P17: =IFERROR(VLOOKUP(B17,'Receivable Invoice Detail'!$S$1:$U$3014,3,FALSE),0) -> 0
A18: SO16467 | B18: INV12582 | C18: Wild Rows Pump & Compression LTD. | D18: CAD | E18: Yes | F18: 0 | G18: 0 | H18: -50 | I18: 0 | J18: =IF(K18=13,D17,"") | K18: =LEN(A18) -> 7 | L18: =IF(K18=13,LEFT(A18,7),"") | M18: =IF(AND(K18=13,D17="CAD"),ROUND(F18+H18,2),0) -> 0 | N18: =IF(AND(K18=13,D17="USD"),ROUND(G18+I18,2),0) -> 0 | O18: =IF(K18=13,IF(M18+N18=0,"Yes",0),0) -> 0 | P18: =IFERROR(VLOOKUP(B18,'Receivable Invoice Detail'!$S$1:$U$3014,3,FALSE),0) -> 0
B19: INV12585 | C19: Wild Rows Pump & Compression LTD. | D19: CAD | E19: Yes | F19: 0 | G19: 0 | H19: -129.88 | I19: 0 | J19: =IF(K19=13,D18,"") | K19: =LEN(A19) -> 0 | L19: =IF(K19=13,LEFT(A19,7),"") | M19: =IF(AND(K19=13,D18="CAD"),ROUND(F19+H19,2),0) -> 0 | N19: =IF(AND(K19=13,D18="USD"),ROUND(G19+I19,2),0) -> 0 | O19: =IF(K19=13,IF(M19+N19=0,"Yes",0),0) -> 0 | P19: =IFERROR(VLOOKUP(B19,'Receivable Invoice Detail'!$S$1:$U$3014,3,FALSE),0) -> 0
B20: INV12954 | C20: Wild Rows Pump & Compression LTD. | D20: CAD | E20: Yes | F20: 1026.9 | G20: 716.51446 | H20: -847.02 | I20: 0 | J20: =IF(K20=13,D19,"") | K20: =LEN(A20) -> 0 | L20: =IF(K20=13,LEFT(A20,7),"") | M20: =IF(AND(K20=13,D19="CAD"),ROUND(F20+H20,2),0) -> 0 | N20: =IF(AND(K20=13,D19="USD"),ROUND(G20+I20,2),0) -> 0 | O20: =IF(K20=13,IF(M20+N20=0,"Yes",0),0) -> 0 | P20: =IFERROR(VLOOKUP(B20,'Receivable Invoice Detail'!$S$1:$U$3014,3,FALSE),0) -> 0
A21: SO16467 Total | F21: 1026.9 | G21: 716.51446 | H21: -1026.9 | I21: 0 | J21: =IF(K21=13,D20,"") -> CAD | K21: =LEN(A21) -> 13 | L21: =IF(K21=13,LEFT(A21,7),"") -> SO16467 | M21: =IF(AND(K21=13,D20="CAD"),ROUND(F21+H21,2),0) -> 0 | N21: =IF(AND(K21=13,D20="USD"),ROUND(G21+I21,2),0) -> 0 | O21: =IF(K21=13,IF(M21+N21=0,"Yes",0),0) -> Yes | P21: =IFERROR(VLOOKUP(B21,'Receivable Invoice Detail'!$S$1:$U$3014,3,FALSE),0) -> 0
A22: SO16470 | B22: INV12549 | C22: Resolute Forest Products - Saint-Felicien | D22: CAD | E22: Yes | F22: 1969.52 | G22: 1374.223 | H22: -784.42 | I22: 0 | J22: =IF(K22=13,D21,"") | K22: =LEN(A22) -> 7 | L22: =IF(K22=13,LEFT(A22,7),"") | M22: =IF(AND(K22=13,D21="CAD"),ROUND(F22+H22,2),0) -> 0 | N22: =IF(AND(K22=13,D21="USD"),ROUND(G22+I22,2),0) -> 0 | O22: =IF(K22=13,IF(M22+N22=0,"Yes",0),0) -> 0 | P22: =IFERROR(VLOOKUP(B22,'Receivable Invoice Detail'!$S$1:$U$3014,3,FALSE),0) -> 0
B23: INV12697 | C23: Resolute Forest Products - Saint-Felicien | D23: CAD | E23: Yes | F23: 0 | G23: 0 | H23: -1185.1 | I23: 0 | J23: =IF(K23=13,D22,"") | K23: =LEN(A23) -> 0 | L23: =IF(K23=13,LEFT(A23,7),"") | M23: =IF(AND(K23=13,D22="CAD"),ROUND(F23+H23,2),0) -> 0 | N23: =IF(AND(K23=13,D22="USD"),ROUND(G23+I23,2),0) -> 0 | O23: =IF(K23=13,IF(M23+N23=0,"Yes",0),0) -> 0 | P23: =IFERROR(VLOOKUP(B23,'Receivable Invoice Detail'!$S$1:$U$3014,3,FALSE),0) -> 0
A24: SO16470 Total | F24: 1969.52 | G24: 1374.223 | H24: -1969.52 | I24: 0 | J24: =IF(K24=13,D23,"") -> CAD | K24: =LEN(A24) -> 13 | L24: =IF(K24=13,LEFT(A24,7),"") -> SO16470 | M24: =IF(AND(K24=13,D23="CAD"),ROUND(F24+H24,2),0) -> 0 | N24: =IF(AND(K24=13,D23="USD"),ROUND(G24+I24,2),0) -> 0 | O24: =IF(K24=13,IF(M24+N24=0,"Yes",0),0) -> Yes | P24: =IFERROR(VLOOKUP(B24,'Receivable Invoice Detail'!$S$1:$U$3014,3,FALSE),0) -> 0
A25: SO16476 | B25: INV12578 | C25: Canadian Bearings Ltd. | D25: CAD | E25: Yes | F25: 0 | G25: 0 | H25: -80.04 | I25: 0 | J25: =IF(K25=13,D24,"") | K25: =LEN(A25) -> 7 | L25: =IF(K25=13,LEFT(A25,7),"") | M25: =IF(AND(K25=13,D24="CAD"),ROUND(F25+H25,2),0) -> 0 | N25: =IF(AND(K25=13,D24="USD"),ROUND(G25+I25,2),0) -> 0 | O25: =IF(K25=13,IF(M25+N25=0,"Yes",0),0) -> 0 | P25: =IFERROR(VLOOKUP(B25,'Receivable Invoice Detail'!$S$1:$U$3014,3,FALSE),0) -> 0
B26: INV12614 | C26: Canadian Bearings Ltd. | D26: CAD | E26: Yes | F26: 2121.09 | G26: 1473.6664 | H26: -2041.05 | I26: 0 | J26: =IF(K26=13,D25,"") | K26: =LEN(A26) -> 0 | L26: =IF(K26=13,LEFT(A26,7),"") | M26: =IF(AND(K26=13,D25="CAD"),ROUND(F26+H26,2),0) -> 0 | N26: =IF(AND(K26=13,D25="USD"),ROUND(G26+I26,2),0) -> 0 | O26: =IF(K26=13,IF(M26+N26=0,"Yes",0),0) -> 0 | P26: =IFERROR(VLOOKUP(B26,'Receivable Invoice Detail'!$S$1:$U$3014,3,FALSE),0) -> 0
A27: SO16476 Total | F27: 2121.09 | G27: 1473.6664 | H27: -2121.09 | I27: 0 | J27: =IF(K27=13,D26,"") -> CAD | K27: =LEN(A27) -> 13 | L27: =IF(K27=13,LEFT(A27,7),"") -> SO16476 | M27: =IF(AND(K27=13,D26="CAD"),ROUND(F27+H27,2),0) -> 0 | N27: =IF(AND(K27=13,D26="USD"),ROUND(G27+I27,2),0) -> 0 | O27: =IF(K27=13,IF(M27+N27=0,"Yes",0),0) -> Yes | P27: =IFERROR(VLOOKUP(B27,'Receivable Invoice Detail'!$S$1:$U$3014,3,FALSE),0) -> 0
A28: SO16496 | B28: INV12596 | C28: ProPart Pompes du Canada 9425-4380 Quebec Inc | D28: CAD | E28: Yes | F28: 9500.83 | G28: 6602.3191 | H28: -8614.85 | I28: 0 | J28: =IF(K28=13,D27,"") | K28: =LEN(A28) -> 7 | L28: =IF(K28=13,LEFT(A28,7),"") | M28: =IF(AND(K28=13,D27="CAD"),ROUND(F28+H28,2),0) -> 0 | N28: =IF(AND(K28=13,D27="USD"),ROUND(G28+I28,2),0) -> 0 | O28: =IF(K28=13,IF(M28+N28=0,"Yes",0),0) -> 0 | P28: =IFERROR(VLOOKUP(B28,'Receivable Invoice Detail'!$S$1:$U$3014,3,FALSE),0) -> 0
B29: INV12620 | C29: ProPart Pompes du Canada 9425-4380 Quebec Inc | D29: CAD | E29: Yes | F29: 0 | G29: 0 | H29: -885.98 | I29: 0 | J29: =IF(K29=13,D28,"") | K29: =LEN(A29) -> 0 | L29: =IF(K29=13,LEFT(A29,7),"") | M29: =IF(AND(K29=13,D28="CAD"),ROUND(F29+H29,2),0) -> 0 | N29: =IF(AND(K29=13,D28="USD"),ROUND(G29+I29,2),0) -> 0 | O29: =IF(K29=13,IF(M29+N29=0,"Yes",0),0) -> 0 | P29: =IFERROR(VLOOKUP(B29,'Receivable Invoice Detail'!$S$1:$U$3014,3,FALSE),0) -> 0
A30: SO16496 Total | F30: 9500.83 | G30: 6602.3191 | H30: -9500.83 | I30: 0 | J30: =IF(K30=13,D29,"") -> CAD | K30: =LEN(A30) -> 13 | L30: =IF(K30=13,LEFT(A30,7),"") -> SO16496 | M30: =IF(AND(K30=13,D29="CAD"),ROUND(F30+H30,2),0) -> 0 | N30: =IF(AND(K30=13,D29="USD"),ROUND(G30+I30,2),0) -> 0 | O30: =IF(K30=13,IF(M30+N30=0,"Yes",0),0) -> Yes | P30: =IFERROR(VLOOKUP(B30,'Receivable Invoice Detail'!$S$1:$U$3014,3,FALSE),0) -> 0
A31: SO16501 | B31: INV12581 | C31: Grant Aggregate | D31: CAD | E31: Yes | F31: 0 | G31: 0 | H31: -7811.79 | I31: 0 | J31: =IF(K31=13,D30,"") | K31: =LEN(A31) -> 7 | L31: =IF(K31=13,LEFT(A31,7),"") | M31: =IF(AND(K31=13,D30="CAD"),ROUND(F31+H31,2),0) -> 0 | N31: =IF(AND(K31=13,D30="USD"),ROUND(G31+I31,2),0) -> 0 | O31: =IF(K31=13,IF(M31+N31=0,"Yes",0),0) -> 0 | P31: =IFERROR(VLOOKUP(B31,'Receivable Invoice Detail'!$S$1:$U$3014,3,FALSE),0) -> 0
B32: RINV/2025/00001 (Reversal of: INV12581) | C32: Grant Aggregate | D32: CAD | E32: Pend | F32: 5908.82 | G32: 4104.7279 | H32: 0 | I32: 0 | J32: =IF(K32=13,D31,"") | K32: =LEN(A32) -> 0 | L32: =IF(K32=13,LEFT(A32,7),"") | M32: =IF(AND(K32=13,D31="CAD"),ROUND(F32+H32,2),0) -> 0 | N32: =IF(AND(K32=13,D31="USD"),ROUND(G32+I32,2),0) -> 0 | O32: =IF(K32=13,IF(M32+N32=0,"Yes",0),0) -> 0 | P32: =IFERROR(VLOOKUP(B32,'Receivable Invoice Detail'!$S$1:$U$3014,3,FALSE),0) -> 0
A33: SO16501 Total | F33: 5908.82 | G33: 4104.7279 | H33: -7811.79 | I33: 0 | J33: =IF(K33=13,D32,"") -> CAD | K33: =LEN(A33) -> 13 | L33: =IF(K33=13,LEFT(A33,7),"") -> SO16501 | M33: =IF(AND(K33=13,D32="CAD"),ROUND(F33+H33,2),0) -> -1902.97 | N33: =IF(AND(K33=13,D32="USD"),ROUND(G33+I33,2),0) -> 0 | O33: =IF(K33=13,IF(M33+N33=0,"Yes",0),0) -> 0 | P33: =IFERROR(VLOOKUP(B33,'Receivable Invoice Detail'!$S$1:$U$3014,3,FALSE),0) -> 0
A34: SO16513 | B34: INV12833 | C34: Les Pompes du St-Laurent Inc. | D34: CAD | E34: Yes | F34: 0 | G34: 0 | H34: -10755.87 | I34: 0 | J34: =IF(K34=13,D33,"") | K34: =LEN(A34) -> 7 | L34: =IF(K34=13,LEFT(A34,7),"") | M34: =IF(AND(K34=13,D33="CAD"),ROUND(F34+H34,2),0) -> 0 | N34: =IF(AND(K34=13,D33="USD"),ROUND(G34+I34,2),0) -> 0 | O34: =IF(K34=13,IF(M34+N34=0,"Yes",0),0) -> 0 | P34: =IFERROR(VLOOKUP(B34,'Receivable Invoice Detail'!$S$1:$U$3014,3,FALSE),0) -> 0
B35: INV12915 | C35: Les Pompes du St-Laurent Inc. | D35: CAD | E35: Yes | F35: 16754.72 | G35: 11673.945 | H35: -5998.85 | I35: 0 | J35: =IF(K35=13,D34,"") | K35: =LEN(A35) -> 0 | L35: =IF(K35=13,LEFT(A35,7),"") | M35: =IF(AND(K35=13,D34="CAD"),ROUND(F35+H35,2),0) -> 0 | N35: =IF(AND(K35=13,D34="USD"),ROUND(G35+I35,2),0) -> 0 | O35: =IF(K35=13,IF(M35+N35=0,"Yes",0),0) -> 0 | P35: =IFERROR(VLOOKUP(B35,'Receivable Invoice Detail'!$S$1:$U$3014,3,FALSE),0) -> 0
A36: SO16513 Total | F36: 16754.72 | G36: 11673.945 | H36: -16754.72 | I36: 0 | J36: =IF(K36=13,D35,"") -> CAD | K36: =LEN(A36) -> 13 | L36: =IF(K36=13,LEFT(A36,7),"") -> SO16513 | M36: =IF(AND(K36=13,D35="CAD"),ROUND(F36+H36,2),0) -> 0 | N36: =IF(AND(K36=13,D35="USD"),ROUND(G36+I36,2),0) -> 0 | O36: =IF(K36=13,IF(M36+N36=0,"Yes",0),0) -> Yes | P36: =IFERROR(VLOOKUP(B36,'Receivable Invoice Detail'!$S$1:$U$3014,3,FALSE),0) -> 0
A37: SO16515 | B37: INV12615 | C37: Canadian Bearings Ltd. | D37: CAD | E37: Yes | F37: 1387.4 | G37: 950.22184 | H37: -158.34 | I37: 0 | J37: =IF(K37=13,D36,"") | K37: =LEN(A37) -> 7 | L37: =IF(K37=13,LEFT(A37,7),"") | M37: =IF(AND(K37=13,D36="CAD"),ROUND(F37+H37,2),0) -> 0 | N37: =IF(AND(K37=13,D36="USD"),ROUND(G37+I37,2),0) -> 0 | O37: =IF(K37=13,IF(M37+N37=0,"Yes",0),0) -> 0 | P37: =IFERROR(VLOOKUP(B37,'Receivable Invoice Detail'!$S$1:$U$3014,3,FALSE),0) -> 0
B38: INV12676 | C38: Canadian Bearings Ltd. | D38: CAD | E38: Yes | F38: 0 | G38: 0 | H38: -1229.06 | I38: 0 | J38: =IF(K38=13,D37,"") | K38: =LEN(A38) -> 0 | L38: =IF(K38=13,LEFT(A38,7),"") | M38: =IF(AND(K38=13,D37="CAD"),ROUND(F38+H38,2),0) -> 0 | N38: =IF(AND(K38=13,D37="USD"),ROUND(G38+I38,2),0) -> 0 | O38: =IF(K38=13,IF(M38+N38=0,"Yes",0),0) -> 0 | P38: =IFERROR(VLOOKUP(B38,'Receivable Invoice Detail'!$S$1:$U$3014,3,FALSE),0) -> 0
A39: SO16515 Total | F39: 1387.4 | G39: 950.22184 | H39: -1387.4 | I39: 0 | J39: =IF(K39=13,D38,"") -> CAD | K39: =LEN(A39) -> 13 | L39: =IF(K39=13,LEFT(A39,7),"") -> SO16515 | M39: =IF(AND(K39=13,D38="CAD"),ROUND(F39+H39,2),0) -> 0 | N39: =IF(AND(K39=13,D38="USD"),ROUND(G39+I39,2),0) -> 0 | O39: =IF(K39=13,IF(M39+N39=0,"Yes",0),0) -> Yes | P39: =IFERROR(VLOOKUP(B39,'Receivable Invoice Detail'!$S$1:$U$3014,3,FALSE),0) -> 0
A40: SO16516 | B40: INV12638 | C40: Canadian Bearings Ltd. | D40: CAD | E40: Yes | F40: 183.84 | G40: 128.48035 | H40: -126.5 | I40: 0 | J40: =IF(K40=13,D39,"") | K40: =LEN(A40) -> 7 | L40: =IF(K40=13,LEFT(A40,7),"") | M40: =IF(AND(K40=13,D39="CAD"),ROUND(F40+H40,2),0) -> 0 | N40: =IF(AND(K40=13,D39="USD"),ROUND(G40+I40,2),0) -> 0 | O40: =IF(K40=13,IF(M40+N40=0,"Yes",0),0) -> 0 | P40: =IFERROR(VLOOKUP(B40,'Receivable Invoice Detail'!$S$1:$U$3014,3,FALSE),0) -> 0
B41: INV12675 | C41: Canadian Bearings Ltd. | D41: CAD | E41: Yes | F41: 0 | G41: 0 | H41: -57.34 | I41: 0 | J41: =IF(K41=13,D40,"") | K41: =LEN(A41) -> 0 | L41: =IF(K41=13,LEFT(A41,7),"") | M41: =IF(AND(K41=13,D40="CAD"),ROUND(F41+H41,2),0) -> 0 | N41: =IF(AND(K41=13,D40="USD"),ROUND(G41+I41,2),0) -> 0 | O41: =IF(K41=13,IF(M41+N41=0,"Yes",0),0) -> 0 | P41: =IFERROR(VLOOKUP(B41,'Receivable Invoice Detail'!$S$1:$U$3014,3,FALSE),0) -> 0
A42: SO16516 Total | F42: 183.84 | G42: 128.48035 | H42: -183.84 | I42: 0 | J42: =IF(K42=13,D41,"") -> CAD | K42: =LEN(A42) -> 13 | L42: =IF(K42=13,LEFT(A42,7),"") -> SO16516 | M42: =IF(AND(K42=13,D41="CAD"),ROUND(F42+H42,2),0) -> 0 | N42: =IF(AND(K42=13,D41="USD"),ROUND(G42+I42,2),0) -> 0 | O42: =IF(K42=13,IF(M42+N42=0,"Yes",0),0) -> Yes | P42: =IFERROR(VLOOKUP(B42,'Receivable Invoice Detail'!$S$1:$U$3014,3,FALSE),0) -> 0
A43: SO16522 | B43: INV12625 | C43: D&H Materials Inc | D43: USD | E43: Yes | F43: 1011.6319 | G43: 701.8 | H43: 0 | I43: -331.92 | J43: =IF(K43=13,D42,"") | K43: =LEN(A43) -> 7 | L43: =IF(K43=13,LEFT(A43,7),"") | M43: =IF(AND(K43=13,D42="CAD"),ROUND(F43+H43,2),0) -> 0 | N43: =IF(AND(K43=13,D42="USD"),ROUND(G43+I43,2),0) -> 0 | O43: =IF(K43=13,IF(M43+N43=0,"Yes",0),0) -> 0 | P43: =IFERROR(VLOOKUP(B43,'Receivable Invoice Detail'!$S$1:$U$3014,3,FALSE),0) -> 0
B44: INV12921 | C44: D&H Materials Inc | D44: USD | E44: Yes | F44: 0 | G44: 0 | H44: 0 | I44: -369.88 | J44: =IF(K44=13,D43,"") | K44: =LEN(A44) -> 0 | L44: =IF(K44=13,LEFT(A44,7),"") | M44: =IF(AND(K44=13,D43="CAD"),ROUND(F44+H44,2),0) -> 0 | N44: =IF(AND(K44=13,D43="USD"),ROUND(G44+I44,2),0) -> 0 | O44: =IF(K44=13,IF(M44+N44=0,"Yes",0),0) -> 0 | P44: =IFERROR(VLOOKUP(B44,'Receivable Invoice Detail'!$S$1:$U$3014,3,FALSE),0) -> 0
A45: SO16522 Total | F45: 1011.6319 | G45: 701.8 | H45: 0 | I45: -701.8 | J45: =IF(K45=13,D44,"") -> USD | K45: =LEN(A45) -> 13 | L45: =IF(K45=13,LEFT(A45,7),"") -> SO16522 | M45: =IF(AND(K45=13,D44="CAD"),ROUND(F45+H45,2),0) -> 0 | N45: =IF(AND(K45=13,D44="USD"),ROUND(G45+I45,2),0) -> 0 | O45: =IF(K45=13,IF(M45+N45=0,"Yes",0),0) -> Yes | P45: =IFERROR(VLOOKUP(B45,'Receivable Invoice Detail'!$S$1:$U$3014,3,FALSE),0) -> 0
A46: SO16525 | B46: INV12604 | C46: Cartledge & Associates Inc. | D46: USD | E46: Yes | F46: 0 | G46: 0 | H46: 0 | I46: -3458.61 | J46: =IF(K46=13,D45,"") | K46: =LEN(A46) -> 7 | L46: =IF(K46=13,LEFT(A46,7),"") | M46: =IF(AND(K46=13,D45="CAD"),ROUND(F46+H46,2),0) -> 0 | N46: =IF(AND(K46=13,D45="USD"),ROUND(G46+I46,2),0) -> 0 | O46: =IF(K46=13,IF(M46+N46=0,"Yes",0),0) -> 0 | P46: =IFERROR(VLOOKUP(B46,'Receivable Invoice Detail'!$S$1:$U$3014,3,FALSE),0) -> 605
B47: INV12830 | C47: Cartledge & Associates Inc. | D47: USD | E47: Yes | F47: 10249.502 | G47: 7054.91 | H47: 0 | I47: -4239.3 | J47: =IF(K47=13,D46,"") | K47: =LEN(A47) -> 0 | L47: =IF(K47=13,LEFT(A47,7),"") | M47: =IF(AND(K47=13,D46="CAD"),ROUND(F47+H47,2),0) -> 0 | N47: =IF(AND(K47=13,D46="USD"),ROUND(G47+I47,2),0) -> 0 | O47: =IF(K47=13,IF(M47+N47=0,"Yes",0),0) -> 0 | P47: =IFERROR(VLOOKUP(B47,'Receivable Invoice Detail'!$S$1:$U$3014,3,FALSE),0) -> 643
A48: SO16525 Total | F48: 10249.502 | G48: 7054.91 | H48: 0 | I48: -7697.91 | J48: =IF(K48=13,D47,"") -> USD | K48: =LEN(A48) -> 13 | L48: =IF(K48=13,LEFT(A48,7),"") -> SO16525 | M48: =IF(AND(K48=13,D47="CAD"),ROUND(F48+H48,2),0) -> 0 | N48: =IF(AND(K48=13,D47="USD"),ROUND(G48+I48,2),0) -> -643 | O48: =IF(K48=13,IF(M48+N48=0,"Yes",0),0) -> 0 | P48: =IFERROR(VLOOKUP(B48,'Receivable Invoice Detail'!$S$1:$U$3014,3,FALSE),0) -> 0 | Q48: Yes | R48: 12830 | S48: Freight
A49: SO16527 | B49: INV12624 | C49: Resolute Forest Products - Saint-Felicien | D49: CAD | E49: Yes | F49: 0 | G49: 0 | H49: -678.09 | I49: 0 | J49: =IF(K49=13,D48,"") | K49: =LEN(A49) -> 7 | L49: =IF(K49=13,LEFT(A49,7),"") | M49: =IF(AND(K49=13,D48="CAD"),ROUND(F49+H49,2),0) -> 0 | N49: =IF(AND(K49=13,D48="USD"),ROUND(G49+I49,2),0) -> 0 | O49: =IF(K49=13,IF(M49+N49=0,"Yes",0),0) -> 0 | P49: =IFERROR(VLOOKUP(B49,'Receivable Invoice Detail'!$S$1:$U$3014,3,FALSE),0) -> 0
B50: INV13100 | C50: Resolute Forest Products - Saint-Felicien | D50: CAD | E50: Yes | F50: 6392.94 | G50: 4474.1661 | H50: -5714.85 | I50: 0 | J50: =IF(K50=13,D49,"") | K50: =LEN(A50) -> 0 | L50: =IF(K50=13,LEFT(A50,7),"") | M50: =IF(AND(K50=13,D49="CAD"),ROUND(F50+H50,2),0) -> 0 | N50: =IF(AND(K50=13,D49="USD"),ROUND(G50+I50,2),0) -> 0 | O50: =IF(K50=13,IF(M50+N50=0,"Yes",0),0) -> 0 | P50: =IFERROR(VLOOKUP(B50,'Receivable Invoice Detail'!$S$1:$U$3014,3,FALSE),0) -> 0
A51: SO16527 Total | F51: 6392.94 | G51: 4474.1661 | H51: -6392.94 | I51: 0 | J51: =IF(K51=13,D50,"") -> CAD | K51: =LEN(A51) -> 13 | L51: =IF(K51=13,LEFT(A51,7),"") -> SO16527 | M51: =IF(AND(K51=13,D50="CAD"),ROUND(F51+H51,2),0) -> 0 | N51: =IF(AND(K51=13,D50="USD"),ROUND(G51+I51,2),0) -> 0 | O51: =IF(K51=13,IF(M51+N51=0,"Yes",0),0) -> Yes | P51: =IFERROR(VLOOKUP(B51,'Receivable Invoice Detail'!$S$1:$U$3014,3,FALSE),0) -> 0
A52: SO16531 | B52: INV12749 | C52: Kumtor Gold Company | D52: USD | E52: Yes | F52: 55151.892 | G52: 38515.04 | H52: 0 | I52: -23141.73 | J52: =IF(K52=13,D51,"") | K52: =LEN(A52) -> 7 | L52: =IF(K52=13,LEFT(A52,7),"") | M52: =IF(AND(K52=13,D51="CAD"),ROUND(F52+H52,2),0) -> 0 | N52: =IF(AND(K52=13,D51="USD"),ROUND(G52+I52,2),0) -> 0 | O52: =IF(K52=13,IF(M52+N52=0,"Yes",0),0) -> 0 | P52: =IFERROR(VLOOKUP(B52,'Receivable Invoice Detail'!$S$1:$U$3014,3,FALSE),0) -> 0
B53: INV12782 | C53: Kumtor Gold Company | D53: USD | E53: Yes | F53: 0 | G53: 0 | H53: 0 | I53: -468.06 | J53: =IF(K53=13,D52,"") | K53: =LEN(A53) -> 0 | L53: =IF(K53=13,LEFT(A53,7),"") | M53: =IF(AND(K53=13,D52="CAD"),ROUND(F53+H53,2),0) -> 0 | N53: =IF(AND(K53=13,D52="USD"),ROUND(G53+I53,2),0) -> 0 | O53: =IF(K53=13,IF(M53+N53=0,"Yes",0),0) -> 0 | P53: =IFERROR(VLOOKUP(B53,'Receivable Invoice Detail'!$S$1:$U$3014,3,FALSE),0) -> 0
B54: INV12822 | C54: Kumtor Gold Company | D54: USD | E54: Yes | F54: 0 | G54: 0 | H54: 0 | I54: -14156.31 | J54: =IF(K54=13,D53,"") | K54: =LEN(A54) -> 0 | L54: =IF(K54=13,LEFT(A54,7),"") | M54: =IF(AND(K54=13,D53="CAD"),ROUND(F54+H54,2),0) -> 0 | N54: =IF(AND(K54=13,D53="USD"),ROUND(G54+I54,2),0) -> 0 | O54: =IF(K54=13,IF(M54+N54=0,"Yes",0),0) -> 0 | P54: =IFERROR(VLOOKUP(B54,'Receivable Invoice Detail'!$S$1:$U$3014,3,FALSE),0) -> 0
B55: INV13035 | C55: Kumtor Gold Company | D55: USD | E55: Yes | F55: 0 | G55: 0 | H55: 0 | I55: -748.94 | J55: =IF(K55=13,D54,"") | K55: =LEN(A55) -> 0 | L55: =IF(K55=13,LEFT(A55,7),"") | M55: =IF(AND(K55=13,D54="CAD"),ROUND(F55+H55,2),0) -> 0 | N55: =IF(AND(K55=13,D54="USD"),ROUND(G55+I55,2),0) -> 0 | O55: =IF(K55=13,IF(M55+N55=0,"Yes",0),0) -> 0 | P55: =IFERROR(VLOOKUP(B55,'Receivable Invoice Detail'!$S$1:$U$3014,3,FALSE),0) -> 0
A56: SO16531 Total | F56: 55151.892 | G56: 38515.04 | H56: 0 | I56: -38515.04 | J56: =IF(K56=13,D55,"") -> USD | K56: =LEN(A56) -> 13 | L56: =IF(K56=13,LEFT(A56,7),"") -> SO16531 | M56: =IF(AND(K56=13,D55="CAD"),ROUND(F56+H56,2),0) -> 0 | N56: =IF(AND(K56=13,D55="USD"),ROUND(G56+I56,2),0) -> 0 | O56: =IF(K56=13,IF(M56+N56=0,"Yes",0),0) -> Yes | P56: =IFERROR(VLOOKUP(B56,'Receivable Invoice Detail'!$S$1:$U$3014,3,FALSE),0) -> 0
A57: SO16534 | B57: INV12618 | C57: Kumtor Gold Company | D57: USD | E57: Yes | F57: 77306.715 | G57: 52946.9 | H57: 0 | I57: -16104.77 | J57: =IF(K57=13,D56,"") | K57: =LEN(A57) -> 7 | L57: =IF(K57=13,LEFT(A57,7),"") | M57: =IF(AND(K57=13,D56="CAD"),ROUND(F57+H57,2),0) -> 0 | N57: =IF(AND(K57=13,D56="USD"),ROUND(G57+I57,2),0) -> 0 | O57: =IF(K57=13,IF(M57+N57=0,"Yes",0),0) -> 0 | P57: =IFERROR(VLOOKUP(B57,'Receivable Invoice Detail'!$S$1:$U$3014,3,FALSE),0) -> 0
B58: INV12747 | C58: Kumtor Gold Company | D58: USD | E58: Yes | F58: 0 | G58: 0 | H58: 0 | I58: -1452.39 | J58: =IF(K58=13,D57,"") | K58: =LEN(A58) -> 0 | L58: =IF(K58=13,LEFT(A58,7),"") | M58: =IF(AND(K58=13,D57="CAD"),ROUND(F58+H58,2),0) -> 0 | N58: =IF(AND(K58=13,D57="USD"),ROUND(G58+I58,2),0) -> 0 | O58: =IF(K58=13,IF(M58+N58=0,"Yes",0),0) -> 0 | P58: =IFERROR(VLOOKUP(B58,'Receivable Invoice Detail'!$S$1:$U$3014,3,FALSE),0) -> 0
B59: INV12840 | C59: Kumtor Gold Company | D59: USD | E59: Yes | F59: 0 | G59: 0 | H59: 0 | I59: -18751.86 | J59: =IF(K59=13,D58,"") | K59: =LEN(A59) -> 0 | L59: =IF(K59=13,LEFT(A59,7),"") | M59: =IF(AND(K59=13,D58="CAD"),ROUND(F59+H59,2),0) -> 0 | N59: =IF(AND(K59=13,D58="USD"),ROUND(G59+I59,2),0) -> 0 | O59: =IF(K59=13,IF(M59+N59=0,"Yes",0),0) -> 0 | P59: =IFERROR(VLOOKUP(B59,'Receivable Invoice Detail'!$S$1:$U$3014,3,FALSE),0) -> 0
B60: INV12860 | C60: Kumtor Gold Company | D60: USD | E60: Yes | F60: 0 | G60: 0 | H60: 0 | I60: -7261.95 | J60: =IF(K60=13,D59,"") | K60: =LEN(A60) -> 0 | L60: =IF(K60=13,LEFT(A60,7),"") | M60: =IF(AND(K60=13,D59="CAD"),ROUND(F60+H60,2),0) -> 0 | N60: =IF(AND(K60=13,D59="USD"),ROUND(G60+I60,2),0) -> 0 | O60: =IF(K60=13,IF(M60+N60=0,"Yes",0),0) -> 0 | P60: =IFERROR(VLOOKUP(B60,'Receivable Invoice Detail'!$S$1:$U$3014,3,FALSE),0) -> 0
B61: INV13074 | C61: Kumtor Gold Company | D61: USD | E61: Yes | F61: 0 | G61: 0 | H61: 0 | I61: -9375.93 | J61: =IF(K61=13,D60,"") | K61: =LEN(A61) -> 0 | L61: =IF(K61=13,LEFT(A61,7),"") | M61: =IF(AND(K61=13,D60="CAD"),ROUND(F61+H61,2),0) -> 0 | N61: =IF(AND(K61=13,D60="USD"),ROUND(G61+I61,2),0) -> 0 | O61: =IF(K61=13,IF(M61+N61=0,"Yes",0),0) -> 0 | P61: =IFERROR(VLOOKUP(B61,'Receivable Invoice Detail'!$S$1:$U$3014,3,FALSE),0) -> 0
A62: SO16534 Total | F62: 77306.715 | G62: 52946.9 | H62: 0 | I62: -52946.9 | J62: =IF(K62=13,D61,"") -> USD | K62: =LEN(A62) -> 13 | L62: =IF(K62=13,LEFT(A62,7),"") -> SO16534 | M62: =IF(AND(K62=13,D61="CAD"),ROUND(F62+H62,2),0) -> 0 | N62: =IF(AND(K62=13,D61="USD"),ROUND(G62+I62,2),0) -> 0 | O62: =IF(K62=13,IF(M62+N62=0,"Yes",0),0) -> Yes | P62: =IFERROR(VLOOKUP(B62,'Receivable Invoice Detail'!$S$1:$U$3014,3,FALSE),0) -> 0
A63: SO16537 | B63: INV12605 | C63: Cartledge & Associates Inc. | D63: USD | E63: Yes | F63: 0 | G63: 0 | H63: 0 | I63: -1023.3 | J63: =IF(K63=13,D62,"") | K63: =LEN(A63) -> 7 | L63: =IF(K63=13,LEFT(A63,7),"") | M63: =IF(AND(K63=13,D62="CAD"),ROUND(F63+H63,2),0) -> 0 | N63: =IF(AND(K63=13,D62="USD"),ROUND(G63+I63,2),0) -> 0 | O63: =IF(K63=13,IF(M63+N63=0,"Yes",0),0) -> 0 | P63: =IFERROR(VLOOKUP(B63,'Receivable Invoice Detail'!$S$1:$U$3014,3,FALSE),0) -> 0
B64: INV12832 | C64: Cartledge & Associates Inc. | D64: USD | E64: Yes | F64: 5976.3999 | G64: 4093.2 | H64: 0 | I64: -3069.9 | J64: =IF(K64=13,D63,"") | K64: =LEN(A64) -> 0 | L64: =IF(K64=13,LEFT(A64,7),"") | M64: =IF(AND(K64=13,D63="CAD"),ROUND(F64+H64,2),0) -> 0 | N64: =IF(AND(K64=13,D63="USD"),ROUND(G64+I64,2),0) -> 0 | O64: =IF(K64=13,IF(M64+N64=0,"Yes",0),0) -> 0 | P64: =IFERROR(VLOOKUP(B64,'Receivable Invoice Detail'!$S$1:$U$3014,3,FALSE),0) -> 0
A65: SO16537 Total | F65: 5976.3999 | G65: 4093.2 | H65: 0 | I65: -4093.2 | J65: =IF(K65=13,D64,"") -> USD | K65: =LEN(A65) -> 13 | L65: =IF(K65=13,LEFT(A65,7),"") -> SO16537 | M65: =IF(AND(K65=13,D64="CAD"),ROUND(F65+H65,2),0) -> 0 | N65: =IF(AND(K65=13,D64="USD"),ROUND(G65+I65,2),0) -> 0 | O65: =IF(K65=13,IF(M65+N65=0,"Yes",0),0) -> Yes | P65: =IFERROR(VLOOKUP(B65,'Receivable Invoice Detail'!$S$1:$U$3014,3,FALSE),0) -> 0
A66: SO16544 | B66: INV12940 | C66: Motion Industries Inc. (Canada) - Winnipeg | D66: CAD | E66: Yes | F66: 7490.32 | G66: 5408.7722 | H66: -92.22 | I66: 0 | J66: =IF(K66=13,D65,"") | K66: =LEN(A66) -> 7 | L66: =IF(K66=13,LEFT(A66,7),"") | M66: =IF(AND(K66=13,D65="CAD"),ROUND(F66+H66,2),0) -> 0 | N66: =IF(AND(K66=13,D65="USD"),ROUND(G66+I66,2),0) -> 0 | O66: =IF(K66=13,IF(M66+N66=0,"Yes",0),0) -> 0 | P66: =IFERROR(VLOOKUP(B66,'Receivable Invoice Detail'!$S$1:$U$3014,3,FALSE),0) -> 0
B67: INV13261 | C67: Motion Industries Inc. (Canada) - Winnipeg | D67: CAD | E67: Yes | F67: 0 | G67: 0 | H67: -7398.1 | I67: 0 | J67: =IF(K67=13,D66,"") | K67: =LEN(A67) -> 0 | L67: =IF(K67=13,LEFT(A67,7),"") | M67: =IF(AND(K67=13,D66="CAD"),ROUND(F67+H67,2),0) -> 0 | N67: =IF(AND(K67=13,D66="USD"),ROUND(G67+I67,2),0) -> 0 | O67: =IF(K67=13,IF(M67+N67=0,"Yes",0),0) -> 0 | P67: =IFERROR(VLOOKUP(B67,'Receivable Invoice Detail'!$S$1:$U$3014,3,FALSE),0) -> 0
A68: SO16544 Total | F68: 7490.32 | G68: 5408.7722 | H68: -7490.32 | I68: 0 | J68: =IF(K68=13,D67,"") -> CAD | K68: =LEN(A68) -> 13 | L68: =IF(K68=13,LEFT(A68,7),"") -> SO16544 | M68: =IF(AND(K68=13,D67="CAD"),ROUND(F68+H68,2),0) -> 0 | N68: =IF(AND(K68=13,D67="USD"),ROUND(G68+I68,2),0) -> 0 | O68: =IF(K68=13,IF(M68+N68=0,"Yes",0),0) -> Yes | P68: =IFERROR(VLOOKUP(B68,'Receivable Invoice Detail'!$S$1:$U$3014,3,FALSE),0) -> 0
A69: SO16554 | B69: INV12765 | C69: Barrick Gold - Pueblo Viejo Dominicana Corporation | D69: USD | E69: Yes | F69: 0 | G69: 0 | H69: 0 | I69: -2925.09 | J69: =IF(K69=13,D68,"") | K69: =LEN(A69) -> 7 | L69: =IF(K69=13,LEFT(A69,7),"") | M69: =IF(AND(K69=13,D68="CAD"),ROUND(F69+H69,2),0) -> 0 | N69: =IF(AND(K69=13,D68="USD"),ROUND(G69+I69,2),0) -> 0 | O69: =IF(K69=13,IF(M69+N69=0,"Yes",0),0) -> 0 | P69: =IFERROR(VLOOKUP(B69,'Receivable Invoice Detail'!$S$1:$U$3014,3,FALSE),0) -> 0
B70: INV13151 | C70: Barrick Gold - Pueblo Viejo Dominicana Corporation | D70: USD | E70: Yes | F70: 45189.049 | G70: 31557.54 | H70: 0 | I70: -28632.45 | J70: =IF(K70=13,D69,"") | K70: =LEN(A70) -> 0 | L70: =IF(K70=13,LEFT(A70,7),"") | M70: =IF(AND(K70=13,D69="CAD"),ROUND(F70+H70,2),0) -> 0 | N70: =IF(AND(K70=13,D69="USD"),ROUND(G70+I70,2),0) -> 0 | O70: =IF(K70=13,IF(M70+N70=0,"Yes",0),0) -> 0 | P70: =IFERROR(VLOOKUP(B70,'Receivable Invoice Detail'!$S$1:$U$3014,3,FALSE),0) -> 0
A71: SO16554 Total | F71: 45189.049 | G71: 31557.54 | H71: 0 | I71: -31557.54 | J71: =IF(K71=13,D70,"") -> USD | K71: =LEN(A71) -> 13 | L71: =IF(K71=13,LEFT(A71,7),"") -> SO16554 | M71: =IF(AND(K71=13,D70="CAD"),ROUND(F71+H71,2),0) -> 0 | N71: =IF(AND(K71=13,D70="USD"),ROUND(G71+I71,2),0) -> 0 | O71: =IF(K71=13,IF(M71+N71=0,"Yes",0),0) -> Yes | P71: =IFERROR(VLOOKUP(B71,'Receivable Invoice Detail'!$S$1:$U$3014,3,FALSE),0) -> 0
A72: SO16564 | B72: INV12664 | C72: Sling-Choker Manufacturing - Timmins | D72: CAD | E72: Yes | F72: 0 | G72: 0 | H72: -1031.46 | I72: 0 | J72: =IF(K72=13,D71,"") | K72: =LEN(A72) -> 7 | L72: =IF(K72=13,LEFT(A72,7),"") | M72: =IF(AND(K72=13,D71="CAD"),ROUND(F72+H72,2),0) -> 0 | N72: =IF(AND(K72=13,D71="USD"),ROUND(G72+I72,2),0) -> 0 | O72: =IF(K72=13,IF(M72+N72=0,"Yes",0),0) -> 0 | P72: =IFERROR(VLOOKUP(B72,'Receivable Invoice Detail'!$S$1:$U$3014,3,FALSE),0) -> 0
B73: INV12880 | C73: Sling-Choker Manufacturing - Timmins | D73: CAD | E73: Yes | F73: 13281.16 | G73: 9281.8106 | H73: -12249.7 | I73: 0 | J73: =IF(K73=13,D72,"") | K73: =LEN(A73) -> 0 | L73: =IF(K73=13,LEFT(A73,7),"") | M73: =IF(AND(K73=13,D72="CAD"),ROUND(F73+H73,2),0) -> 0 | N73: =IF(AND(K73=13,D72="USD"),ROUND(G73+I73,2),0) -> 0 | O73: =IF(K73=13,IF(M73+N73=0,"Yes",0),0) -> 0 | P73: =IFERROR(VLOOKUP(B73,'Receivable Invoice Detail'!$S$1:$U$3014,3,FALSE),0) -> 0
A74: SO16564 Total | F74: 13281.16 | G74: 9281.8106 | H74: -13281.16 | I74: 0 | J74: =IF(K74=13,D73,"") -> CAD | K74: =LEN(A74) -> 13 | L74: =IF(K74=13,LEFT(A74,7),"") -> SO16564 | M74: =IF(AND(K74=13,D73="CAD"),ROUND(F74+H74,2),0) -> 0 | N74: =IF(AND(K74=13,D73="USD"),ROUND(G74+I74,2),0) -> 0 | O74: =IF(K74=13,IF(M74+N74=0,"Yes",0),0) -> Yes | P74: =IFERROR(VLOOKUP(B74,'Receivable Invoice Detail'!$S$1:$U$3014,3,FALSE),0) -> 0
A75: SO16570 | B75: INV12628 | C75: Eleazar General & Industrial Supplies Limited | D75: USD | E75: Yes | F75: 6885.1912 | G75: 4853.48 | H75: 0 | I75: -1098.59 | J75: =IF(K75=13,D74,"") | K75: =LEN(A75) -> 7 | L75: =IF(K75=13,LEFT(A75,7),"") | M75: =IF(AND(K75=13,D74="CAD"),ROUND(F75+H75,2),0) -> 0 | N75: =IF(AND(K75=13,D74="USD"),ROUND(G75+I75,2),0) -> 0 | O75: =IF(K75=13,IF(M75+N75=0,"Yes",0),0) -> 0 | P75: =IFERROR(VLOOKUP(B75,'Receivable Invoice Detail'!$S$1:$U$3014,3,FALSE),0) -> 0
B76: INV12836 | C76: Eleazar General & Industrial Supplies Limited | D76: USD | E76: Yes | F76: 0 | G76: 0 | H76: 0 | I76: -3754.89 | J76: =IF(K76=13,D75,"") | K76: =LEN(A76) -> 0 | L76: =IF(K76=13,LEFT(A76,7),"") | M76: =IF(AND(K76=13,D75="CAD"),ROUND(F76+H76,2),0) -> 0 | N76: =IF(AND(K76=13,D75="USD"),ROUND(G76+I76,2),0) -> 0 | O76: =IF(K76=13,IF(M76+N76=0,"Yes",0),0) -> 0 | P76: =IFERROR(VLOOKUP(B76,'Receivable Invoice Detail'!$S$1:$U$3014,3,FALSE),0) -> 0
A77: SO16570 Total | F77: 6885.1912 | G77: 4853.48 | H77: 0 | I77: -4853.48 | J77: =IF(K77=13,D76,"") -> USD | K77: =LEN(A77) -> 13 | L77: =IF(K77=13,LEFT(A77,7),"") -> SO16570 | M77: =IF(AND(K77=13,D76="CAD"),ROUND(F77+H77,2),0) -> 0 | N77: =IF(AND(K77=13,D76="USD"),ROUND(G77+I77,2),0) -> 0 | O77: =IF(K77=13,IF(M77+N77=0,"Yes",0),0) -> Yes | P77: =IFERROR(VLOOKUP(B77,'Receivable Invoice Detail'!$S$1:$U$3014,3,FALSE),0) -> 0
A78: SO16581 | B78: INV13188 | C78: AGM Inc. | D78: USD | E78: Yes | F78: 0 | G78: 0 | H78: 0 | I78: -15930 | J78: =IF(K78=13,D77,"") | K78: =LEN(A78) -> 7 | L78: =IF(K78=13,LEFT(A78,7),"") | M78: =IF(AND(K78=13,D77="CAD"),ROUND(F78+H78,2),0) -> 0 | N78: =IF(AND(K78=13,D77="USD"),ROUND(G78+I78,2),0) -> 0 | O78: =IF(K78=13,IF(M78+N78=0,"Yes",0),0) -> 0 | P78: =IFERROR(VLOOKUP(B78,'Receivable Invoice Detail'!$S$1:$U$3014,3,FALSE),0) -> 0
B79: INV13214 | C79: AGM Inc. | D79: USD | E79: Yes | F79: 44264.603 | G79: 31860 | H79: 0 | I79: -15930 | J79: =IF(K79=13,D78,"") | K79: =LEN(A79) -> 0 | L79: =IF(K79=13,LEFT(A79,7),"") | M79: =IF(AND(K79=13,D78="CAD"),ROUND(F79+H79,2),0) -> 0 | N79: =IF(AND(K79=13,D78="USD"),ROUND(G79+I79,2),0) -> 0 | O79: =IF(K79=13,IF(M79+N79=0,"Yes",0),0) -> 0 | P79: =IFERROR(VLOOKUP(B79,'Receivable Invoice Detail'!$S$1:$U$3014,3,FALSE),0) -> 0
A80: SO16581 Total | F80: 44264.603 | G80: 31860 | H80: 0 | I80: -31860 | J80: =IF(K80=13,D79,"") -> USD | K80: =LEN(A80) -> 13 | L80: =IF(K80=13,LEFT(A80,7),"") -> SO16581 | M80: =IF(AND(K80=13,D79="CAD"),ROUND(F80+H80,2),0) -> 0 | N80: =IF(AND(K80=13,D79="USD"),ROUND(G80+I80,2),0) -> 0 | O80: =IF(K80=13,IF(M80+N80=0,"Yes",0),0) -> Yes | P80: =IFERROR(VLOOKUP(B80,'Receivable Invoice Detail'!$S$1:$U$3014,3,FALSE),0) -> 0
A81: SO16586 | B81: INV12717 | C81: Motion Industries Inc. (Canada) - Winnipeg | D81: CAD | E81: Yes | F81: 0 | G81: 0 | H81: -92.22 | I81: 0 | J81: =IF(K81=13,D80,"") | K81: =LEN(A81) -> 7 | L81: =IF(K81=13,LEFT(A81,7),"") | M81: =IF(AND(K81=13,D80="CAD"),ROUND(F81+H81,2),0) -> 0 | N81: =IF(AND(K81=13,D80="USD"),ROUND(G81+I81,2),0) -> 0 | O81: =IF(K81=13,IF(M81+N81=0,"Yes",0),0) -> 0 | P81: =IFERROR(VLOOKUP(B81,'Receivable Invoice Detail'!$S$1:$U$3014,3,FALSE),0) -> 0
B82: INV12904 | C82: Motion Industries Inc. (Canada) - Winnipeg | D82: CAD | E82: Yes | F82: 122.96 | G82: 85.453651 | H82: -30.74 | I82: 0 | J82: =IF(K82=13,D81,"") | K82: =LEN(A82) -> 0 | L82: =IF(K82=13,LEFT(A82,7),"") | M82: =IF(AND(K82=13,D81="CAD"),ROUND(F82+H82,2),0) -> 0 | N82: =IF(AND(K82=13,D81="USD"),ROUND(G82+I82,2),0) -> 0 | O82: =IF(K82=13,IF(M82+N82=0,"Yes",0),0) -> 0 | P82: =IFERROR(VLOOKUP(B82,'Receivable Invoice Detail'!$S$1:$U$3014,3,FALSE),0) -> 0
A83: SO16586 Total | F83: 122.96 | G83: 85.453651 | H83: -122.96 | I83: 0 | J83: =IF(K83=13,D82,"") -> CAD | K83: =LEN(A83) -> 13 | L83: =IF(K83=13,LEFT(A83,7),"") -> SO16586 | M83: =IF(AND(K83=13,D82="CAD"),ROUND(F83+H83,2),0) -> 0 | N83: =IF(AND(K83=13,D82="USD"),ROUND(G83+I83,2),0) -> 0 | O83: =IF(K83=13,IF(M83+N83=0,"Yes",0),0) -> Yes | P83: =IFERROR(VLOOKUP(B83,'Receivable Invoice Detail'!$S$1:$U$3014,3,FALSE),0) -> 0
A84: SO16612 | B84: INV12705 | C84: FMI Products | D84: CAD | E84: Yes | F84: 1188.04 | G84: 837.47728 | H84: -622.95 | I84: 0 | J84: =IF(K84=13,D83,"") | K84: =LEN(A84) -> 7 | L84: =IF(K84=13,LEFT(A84,7),"") | M84: =IF(AND(K84=13,D83="CAD"),ROUND(F84+H84,2),0) -> 0 | N84: =IF(AND(K84=13,D83="USD"),ROUND(G84+I84,2),0) -> 0 | O84: =IF(K84=13,IF(M84+N84=0,"Yes",0),0) -> 0 | P84: =IFERROR(VLOOKUP(B84,'Receivable Invoice Detail'!$S$1:$U$3014,3,FALSE),0) -> 0
B85: INV13052 | C85: FMI Products | D85: CAD | E85: Yes | F85: 0 | G85: 0 | H85: -565.09 | I85: 0 | J85: =IF(K85=13,D84,"") | K85: =LEN(A85) -> 0 | L85: =IF(K85=13,LEFT(A85,7),"") | M85: =IF(AND(K85=13,D84="CAD"),ROUND(F85+H85,2),0) -> 0 | N85: =IF(AND(K85=13,D84="USD"),ROUND(G85+I85,2),0) -> 0 | O85: =IF(K85=13,IF(M85+N85=0,"Yes",0),0) -> 0 | P85: =IFERROR(VLOOKUP(B85,'Receivable Invoice Detail'!$S$1:$U$3014,3,FALSE),0) -> 0
A86: SO16612 Total | F86: 1188.04 | G86: 837.47728 | H86: -1188.04 | I86: 0 | J86: =IF(K86=13,D85,"") -> CAD | K86: =LEN(A86) -> 13 | L86: =IF(K86=13,LEFT(A86,7),"") -> SO16612 | M86: =IF(AND(K86=13,D85="CAD"),ROUND(F86+H86,2),0) -> 0 | N86: =IF(AND(K86=13,D85="USD"),ROUND(G86+I86,2),0) -> 0 | O86: =IF(K86=13,IF(M86+N86=0,"Yes",0),0) -> Yes | P86: =IFERROR(VLOOKUP(B86,'Receivable Invoice Detail'!$S$1:$U$3014,3,FALSE),0) -> 0
A87: SO16617 | B87: INV12680 | C87: Southeast Pump Specialist, Inc. | D87: USD | E87: Yes | F87: 4742.5097 | G87: 3343.07 | H87: 0 | I87: -339.52 | J87: =IF(K87=13,D86,"") | K87: =LEN(A87) -> 7 | L87: =IF(K87=13,LEFT(A87,7),"") | M87: =IF(AND(K87=13,D86="CAD"),ROUND(F87+H87,2),0) -> 0 | N87: =IF(AND(K87=13,D86="USD"),ROUND(G87+I87,2),0) -> 0 | O87: =IF(K87=13,IF(M87+N87=0,"Yes",0),0) -> 0 | P87: =IFERROR(VLOOKUP(B87,'Receivable Invoice Detail'!$S$1:$U$3014,3,FALSE),0) -> 0
B88: INV12965 | C88: Southeast Pump Specialist, Inc. | D88: USD | E88: Yes | F88: 0 | G88: 0 | H88: 0 | I88: -3003.55 | J88: =IF(K88=13,D87,"") | K88: =LEN(A88) -> 0 | L88: =IF(K88=13,LEFT(A88,7),"") | M88: =IF(AND(K88=13,D87="CAD"),ROUND(F88+H88,2),0) -> 0 | N88: =IF(AND(K88=13,D87="USD"),ROUND(G88+I88,2),0) -> 0 | O88: =IF(K88=13,IF(M88+N88=0,"Yes",0),0) -> 0 | P88: =IFERROR(VLOOKUP(B88,'Receivable Invoice Detail'!$S$1:$U$3014,3,FALSE),0) -> 589
A89: SO16617 Total | F89: 4742.5097 | G89: 3343.07 | H89: 0 | I89: -3343.07 | J89: =IF(K89=13,D88,"") -> USD | K89: =LEN(A89) -> 13 | L89: =IF(K89=13,LEFT(A89,7),"") -> SO16617 | M89: =IF(AND(K89=13,D88="CAD"),ROUND(F89+H89,2),0) -> 0 | N89: =IF(AND(K89=13,D88="USD"),ROUND(G89+I89,2),0) -> 0 | O89: =IF(K89=13,IF(M89+N89=0,"Yes",0),0) -> Yes | P89: =IFERROR(VLOOKUP(B89,'Receivable Invoice Detail'!$S$1:$U$3014,3,FALSE),0) -> 0
A90: SO16628 | B90: INV12668 | C90: Fabrene Inc. | D90: CAD | E90: Yes | F90: 463.71 | G90: 325.69911 | H90: -444.46 | I90: 0 | J90: =IF(K90=13,D89,"") | K90: =LEN(A90) -> 7 | L90: =IF(K90=13,LEFT(A90,7),"") | M90: =IF(AND(K90=13,D89="CAD"),ROUND(F90+H90,2),0) -> 0 | N90: =IF(AND(K90=13,D89="USD"),ROUND(G90+I90,2),0) -> 0 | O90: =IF(K90=13,IF(M90+N90=0,"Yes",0),0) -> 0 | P90: =IFERROR(VLOOKUP(B90,'Receivable Invoice Detail'!$S$1:$U$3014,3,FALSE),0) -> 0
B91: INV12724 | C91: Fabrene Inc. | D91: CAD | E91: Yes | F91: 0 | G91: 0 | H91: -19.25 | I91: 0 | J91: =IF(K91=13,D90,"") | K91: =LEN(A91) -> 0 | L91: =IF(K91=13,LEFT(A91,7),"") | M91: =IF(AND(K91=13,D90="CAD"),ROUND(F91+H91,2),0) -> 0 | N91: =IF(AND(K91=13,D90="USD"),ROUND(G91+I91,2),0) -> 0 | O91: =IF(K91=13,IF(M91+N91=0,"Yes",0),0) -> 0 | P91: =IFERROR(VLOOKUP(B91,'Receivable Invoice Detail'!$S$1:$U$3014,3,FALSE),0) -> 0
A92: SO16628 Total | F92: 463.71 | G92: 325.69911 | H92: -463.71 | I92: 0 | J92: =IF(K92=13,D91,"") -> CAD | K92: =LEN(A92) -> 13 | L92: =IF(K92=13,LEFT(A92,7),"") -> SO16628 | M92: =IF(AND(K92=13,D91="CAD"),ROUND(F92+H92,2),0) -> 0 | N92: =IF(AND(K92=13,D91="USD"),ROUND(G92+I92,2),0) -> 0 | O92: =IF(K92=13,IF(M92+N92=0,"Yes",0),0) -> Yes | P92: =IFERROR(VLOOKUP(B92,'Receivable Invoice Detail'!$S$1:$U$3014,3,FALSE),0) -> 0
A93: SO16630 | B93: INV12671 | C93: Motion Industries Inc. (Canada) - Prince George | D93: CAD | E93: Yes | F93: 0 | G93: 0 | H93: -290.88 | I93: 0 | J93: =IF(K93=13,D92,"") | K93: =LEN(A93) -> 7 | L93: =IF(K93=13,LEFT(A93,7),"") | M93: =IF(AND(K93=13,D92="CAD"),ROUND(F93+H93,2),0) -> 0 | N93: =IF(AND(K93=13,D92="USD"),ROUND(G93+I93,2),0) -> 0 | O93: =IF(K93=13,IF(M93+N93=0,"Yes",0),0) -> 0 | P93: =IFERROR(VLOOKUP(B93,'Receivable Invoice Detail'!$S$1:$U$3014,3,FALSE),0) -> 0
B94: INV12952 | C94: Motion Industries Inc. (Canada) - Prince George | D94: CAD | E94: Yes | F94: 313.66 | G94: 220.30748 | H94: -22.78 | I94: 0 | J94: =IF(K94=13,D93,"") | K94: =LEN(A94) -> 0 | L94: =IF(K94=13,LEFT(A94,7),"") | M94: =IF(AND(K94=13,D93="CAD"),ROUND(F94+H94,2),0) -> 0 | N94: =IF(AND(K94=13,D93="USD"),ROUND(G94+I94,2),0) -> 0 | O94: =IF(K94=13,IF(M94+N94=0,"Yes",0),0) -> 0 | P94: =IFERROR(VLOOKUP(B94,'Receivable Invoice Detail'!$S$1:$U$3014,3,FALSE),0) -> 0
A95: SO16630 Total | F95: 313.66 | G95: 220.30748 | H95: -313.66 | I95: 0 | J95: =IF(K95=13,D94,"") -> CAD | K95: =LEN(A95) -> 13 | L95: =IF(K95=13,LEFT(A95,7),"") -> SO16630 | M95: =IF(AND(K95=13,D94="CAD"),ROUND(F95+H95,2),0) -> 0 | N95: =IF(AND(K95=13,D94="USD"),ROUND(G95+I95,2),0) -> 0 | O95: =IF(K95=13,IF(M95+N95=0,"Yes",0),0) -> Yes | P95: =IFERROR(VLOOKUP(B95,'Receivable Invoice Detail'!$S$1:$U$3014,3,FALSE),0) -> 0
A96: SO16645 | B96: INV13221 | C96: Corrosion Fluid Products Corp., Corrosion Fluid Products Corp. - Chicago | D96: USD | E96: Yes | F96: 61849.473 | G96: 43006.8 | H96: 0 | I96: -42594 | J96: =IF(K96=13,D95,"") | K96: =LEN(A96) -> 7 | L96: =IF(K96=13,LEFT(A96,7),"") | M96: =IF(AND(K96=13,D95="CAD"),ROUND(F96+H96,2),0) -> 0 | N96: =IF(AND(K96=13,D95="USD"),ROUND(G96+I96,2),0) -> 0 | O96: =IF(K96=13,IF(M96+N96=0,"Yes",0),0) -> 0 | P96: =IFERROR(VLOOKUP(B96,'Receivable Invoice Detail'!$S$1:$U$3014,3,FALSE),0) -> 0
B97: INV13247 | C97: Corrosion Fluid Products Corp., Corrosion Fluid Products Corp. - Chicago | D97: USD | E97: Yes | F97: 0 | G97: 0 | H97: 0 | I97: -412.8 | J97: =IF(K97=13,D96,"") | K97: =LEN(A97) -> 0 | L97: =IF(K97=13,LEFT(A97,7),"") | M97: =IF(AND(K97=13,D96="CAD"),ROUND(F97+H97,2),0) -> 0 | N97: =IF(AND(K97=13,D96="USD"),ROUND(G97+I97,2),0) -> 0 | O97: =IF(K97=13,IF(M97+N97=0,"Yes",0),0) -> 0 | P97: =IFERROR(VLOOKUP(B97,'Receivable Invoice Detail'!$S$1:$U$3014,3,FALSE),0) -> 0
A98: SO16645 Total | F98: 61849.473 | G98: 43006.8 | H98: 0 | I98: -43006.8 | J98: =IF(K98=13,D97,"") -> USD | K98: =LEN(A98) -> 13 | L98: =IF(K98=13,LEFT(A98,7),"") -> SO16645 | M98: =IF(AND(K98=13,D97="CAD"),ROUND(F98+H98,2),0) -> 0 | N98: =IF(AND(K98=13,D97="USD"),ROUND(G98+I98,2),0) -> 0 | O98: =IF(K98=13,IF(M98+N98=0,"Yes",0),0) -> Yes | P98: =IFERROR(VLOOKUP(B98,'Receivable Invoice Detail'!$S$1:$U$3014,3,FALSE),0) -> 0
A99: SO16651 | B99: INV12886 | C99: AGM Inc. | D99: USD | E99: Yes | F99: 0 | G99: 0 | H99: 0 | I99: -13983.47 | J99: =IF(K99=13,D98,"") | K99: =LEN(A99) -> 7 | L99: =IF(K99=13,LEFT(A99,7),"") | M99: =IF(AND(K99=13,D98="CAD"),ROUND(F99+H99,2),0) -> 0 | N99: =IF(AND(K99=13,D98="USD"),ROUND(G99+I99,2),0) -> 0 | O99: =IF(K99=13,IF(M99+N99=0,"Yes",0),0) -> 0 | P99: =IFERROR(VLOOKUP(B99,'Receivable Invoice Detail'!$S$1:$U$3014,3,FALSE),0) -> 0
B100: INV12985 | C100: AGM Inc. | D100: USD | E100: Yes | F100: 0 | G100: 0 | H100: 0 | I100: -14651.3 | J100: =IF(K100=13,D99,"") | K100: =LEN(A100) -> 0 | L100: =IF(K100=13,LEFT(A100,7),"") | M100: =IF(AND(K100=13,D99="CAD"),ROUND(F100+H100,2),0) -> 0 | N100: =IF(AND(K100=13,D99="USD"),ROUND(G100+I100,2),0) -> 0 | O100: =IF(K100=13,IF(M100+N100=0,"Yes",0),0) -> 0 | P100: =IFERROR(VLOOKUP(B100,'Receivable Invoice Detail'!$S$1:$U$3014,3,FALSE),0) -> 0
B101: INV13189 | C101: AGM Inc. | D101: USD | E101: Yes | F101: 77514.783 | G101: 54023.42 | H101: 0 | I101: -23970.9 | J101: =IF(K101=13,D100,"") | K101: =LEN(A101) -> 0 | L101: =IF(K101=13,LEFT(A101,7),"") | M101: =IF(AND(K101=13,D100="CAD"),ROUND(F101+H101,2),0) -> 0 | N101: =IF(AND(K101=13,D100="USD"),ROUND(G101+I101,2),0) -> 0 | O101: =IF(K101=13,IF(M101+N101=0,"Yes",0),0) -> 0 | P101: =IFERROR(VLOOKUP(B101,'Receivable Invoice Detail'!$S$1:$U$3014,3,FALSE),0) -> 0
...

Sheet CASOPOInvCL
A1: Número de facturas | B1: Referencia de la orden | C1: Reference | D1: Facturas | E1: Cliente | F1: Fecha de creación | G1: Fecha de la orden | H1: Shipping Date | I1: Vendedor | J1: Divisa | K1: Tasa de divisa | L1: Total CAD | M1: Total MXP | N1: Total USD | O1: Importe sin impuestos | P1: Impuestos | Q1: Total | R1: Delivery Status | S1: Hubspot Deal Owner | T1: Cant de Fact | U1: Month Created | V1: Year Created | W1: Month Paid | X1: Year Paid | Y1: Rate 1 | Z1: SO | AA1: SODate | AB1: INV | AC1: INVStatus | AD1: Date Paid | AE1: PO | AF1: Client | AG1: Curr | AH1: Odoo CAD | AI1: Odoo USA | AJ1: Rate 2 | AK1: Xero CAD | AL1: Xero USD | AM1: Dif CAD | AN1: Dif USD | AO1: Paid | AP1: Zero | AQ1: One | AR1: Two | AS1: Fully Paid | AT1: Delivered | AU1: TO be Paid | AV1: Freight | AW1: Commissionable amount in USD
A2: 1 | B2: SO16348 | C2: 6500015792 | D2: INV12491 | E2: Wesdome Gold Mines Ltd - Eagle River Mine | F2: 45659.4 | G2: 45663.596 | H2: 45664 | I2: Ian Trottier | J2: CAD | K2: 1 | L2: 20655.24 | M2: 0 | N2: 14381.876 | O2: 18278.97 | P2: 2376.27 | Q2: 20655.24 | R2: Delivered | T2: =IF(A2="",T1,A2) -> 1 | U2: =IF(F2="",U1,MONTH(F2)) -> 1 | V2: =IF(F2="",V1,YEAR(F2)) -> 2025 | W2: =IF(AC2="Paid",MONTH(AD2),"") -> 2 | X2: =IF(AC2="Paid",YEAR(AD2),"") -> 2025 | Y2: =IF(C2="",Y1,N2/L2) -> 0.69628222 | Z2: =IF(B2="",Z1,B2) -> SO16348 | AA2: =IF(F2="",AA1,F2) -> 45659.4 | AB2: =IF(D2="","No Inv",D2) -> INV12491 | AC2: =IFERROR(VLOOKUP(D2,CAARStatus!$A$2:$AA$1600,22,FALSE),"Not invoiced") -> Paid | AD2: =IF(AC2="Paid",IFERROR(VLOOKUP(D2,CAARStatus!$A$2:$AA$1600,6,FALSE),"Pending"),"Pending") -> 45692 | AE2: =IF(C2="",AE1,C2) -> 6500015792 | AF2: =IF(E2="",AF1,E2) -> Wesdome Gold Mines Ltd - Eagle River Mine | AG2: =IF(J2="",AG1,J2) -> CAD | AH2: =IFERROR(IF(AG2="CAD",O2,O2/K2),0) -> 18278.97 | AI2: =IF(L2-N2=0,VLOOKUP(U2,rate!A$4:B$15,2,FALSE)*AH2,IF(AG2="USD",O2,AH2*Y2)) -> 12727.322 | AJ2: =IFERROR(AI2/AH2,0) -> 0.69628222 | AK2: =-IF(AG2="CAD",IFERROR(VLOOKUP(D2,CAARStatus!$A$1:$Y$1600,16,FALSE),0),0) -> -18278.97 | AL2: =-IF(AG2="USD",IFERROR(VLOOKUP(D2,CAARStatus!$A$1:$Y$1600,11,FALSE),0),0) -> 0 | AM2: =IF(AG2="CAD",AH2+AK2,"") -> 0 | AN2: =IF(AG2="USD",AI2+AL2,"") | AO2: =IF(AC2="Paid","Yes","Pend") -> Yes | AP2: =IF(AND(AO2="Pend",T2<2),"Pend",IF(T2=1,"Yes","XX")) -> Yes | AQ2: =IFERROR(VLOOKUP(B2,InvBal!$L$4:$P$600,4,FALSE),"Pend") -> Pend | AR2: =IFERROR(VLOOKUP(D2,Manual!$C$1:$E$22,2,FALSE),"Pend") -> Pend | AS2: =IF(OR(AP2="Yes",AQ2="Yes",AR2="Yes"),"Yes","") -> Yes | AT2: =IF(R2="Delivered","Yes","") -> Yes | AU2: =IF(AND(AS2="Yes",AT2="Yes"),"Yes","") -> Yes | AV2: =IFERROR(VLOOKUP(D2,'Receivable Invoice Detail'!$S$1:$U$3014,3,FALSE),0) -> 0 | AW2: =IF(AU2="Yes",AI2-AV2,0) -> 12727.322
A3: 1 | B3: SO16349 | C3: 2243313 | D3: INV12951 | E3: Zijin Mining - Rosebel Goldmines N.V. | F3: 45659.435 | G3: 45660.647 | H3: 45815 | I3: Amanda Qiao | J3: USD | K3: 0.69331656 | L3: 16788.291 | M3: 0 | N3: 11639.6 | O3: 11639.6 | Q3: 11639.6 | R3: Delivered | T3: =IF(A3="",T2,A3) -> 1 | U3: =IF(F3="",U2,MONTH(F3)) -> 1 | V3: =IF(F3="",V2,YEAR(F3)) -> 2025 | W3: =IF(AC3="Paid",MONTH(AD3),"") -> 7 | X3: =IF(AC3="Paid",YEAR(AD3),"") -> 2025 | Y3: =IF(C3="",Y2,N3/L3) -> 0.69331656 | Z3: =IF(B3="",Z2,B3) -> SO16349 | AA3: =IF(F3="",AA2,F3) -> 45659.435 | AB3: =IF(D3="","No Inv",D3) -> INV12951 | AC3: =IFERROR(VLOOKUP(D3,CAARStatus!$A$2:$AA$1600,22,FALSE),"Not invoiced") -> Paid | AD3: =IF(AC3="Paid",IFERROR(VLOOKUP(D3,CAARStatus!$A$2:$AA$1600,6,FALSE),"Pending"),"Pending") -> 45849 | AE3: =IF(C3="",AE2,C3) -> 2243313 | AF3: =IF(E3="",AF2,E3) -> Zijin Mining - Rosebel Goldmines N.V. | AG3: =IF(J3="",AG2,J3) -> USD | AH3: =IFERROR(IF(AG3="CAD",O3,O3/K3),0) -> 16788.291 | AI3: =IF(L3-N3=0,VLOOKUP(U3,rate!A$4:B$15,2,FALSE)*AH3,IF(AG3="USD",O3,AH3*Y3)) -> 11639.6 | AJ3: =IFERROR(AI3/AH3,0) -> 0.69331656 | AK3: =-IF(AG3="CAD",IFERROR(VLOOKUP(D3,CAARStatus!$A$1:$Y$1600,16,FALSE),0),0) -> 0 | AL3: =-IF(AG3="USD",IFERROR(VLOOKUP(D3,CAARStatus!$A$1:$Y$1600,11,FALSE),0),0) -> -11639.6 | AM3: =IF(AG3="CAD",AH3+AK3,"") | AN3: =IF(AG3="USD",AI3+AL3,"") -> 0 | AO3: =IF(AC3="Paid","Yes","Pend") -> Yes | AP3: =IF(AND(AO3="Pend",T3<2),"Pend",IF(T3=1,"Yes","XX")) -> Yes | AQ3: =IFERROR(VLOOKUP(Z3,InvBal!$L$4:$P$600,4,FALSE),"Pend") -> Pend | AR3: =IFERROR(VLOOKUP(D3,Manual!$C$1:$E$22,2,FALSE),"Pend") -> Pend | AS3: =IF(OR(AP3="Yes",AQ3="Yes",AR3="Yes"),"Yes","") -> Yes | AT3: =IF(R3="Delivered","Yes","") -> Yes | AU3: =IF(AND(AS3="Yes",AT3="Yes"),"Yes","") -> Yes | AV3: =IFERROR(VLOOKUP(D3,'Receivable Invoice Detail'!$S$1:$U$3014,3,FALSE),0) -> 0 | AW3: =IF(AU3="Yes",AI3-AV3,0) -> 11639.6
A4: 1 | B4: SO16350 | C4: 4560061462 | D4: INV12497 | E4: Alamos Gold Inc, Alamos Gold Inc Island Gold Division | F4: 45659.437 | G4: 45659.439 | H4: 45670 | I4: Ian Trottier | J4: CAD | K4: 1 | L4: 1540.6 | M4: 0 | N4: 1068.1235 | O4: 1363.36 | P4: 177.24 | Q4: 1540.6 | R4: Delivered | T4: =IF(A4="",T3,A4) -> 1 | U4: =IF(F4="",U3,MONTH(F4)) -> 1 | V4: =IF(F4="",V3,YEAR(F4)) -> 2025 | W4: =IF(AC4="Paid",MONTH(AD4),"") -> 2 | X4: =IF(AC4="Paid",YEAR(AD4),"") -> 2025 | Y4: =IF(C4="",Y3,N4/L4) -> 0.69331656 | Z4: =IF(B4="",Z3,B4) -> SO16350 | AA4: =IF(F4="",AA3,F4) -> 45659.437 | AB4: =IF(D4="","No Inv",D4) -> INV12497 | AC4: =IFERROR(VLOOKUP(D4,CAARStatus!$A$2:$AA$1600,22,FALSE),"Not invoiced") -> Paid | AD4: =IF(AC4="Paid",IFERROR(VLOOKUP(D4,CAARStatus!$A$2:$AA$1600,6,FALSE),"Pending"),"Pending") -> 45698 | AE4: =IF(C4="",AE3,C4) -> 4560061462 | AF4: =IF(E4="",AF3,E4) -> Alamos Gold Inc, Alamos Gold Inc Island Gold Division | AG4: =IF(J4="",AG3,J4) -> CAD | AH4: =IFERROR(IF(AG4="CAD",O4,O4/K4),0) -> 1363.36 | AI4: =IF(L4-N4=0,VLOOKUP(U4,rate!A$4:B$15,2,FALSE)*AH4,IF(AG4="USD",O4,AH4*Y4)) -> 945.24006 | AJ4: =IFERROR(AI4/AH4,0) -> 0.69331656 | AK4: =-IF(AG4="CAD",IFERROR(VLOOKUP(D4,CAARStatus!$A$1:$Y$1600,16,FALSE),0),0) -> -1363.36 | AL4: =-IF(AG4="USD",IFERROR(VLOOKUP(D4,CAARStatus!$A$1:$Y$1600,11,FALSE),0),0) -> 0 | AM4: =IF(AG4="CAD",AH4+AK4,"") -> 0 | AN4: =IF(AG4="USD",AI4+AL4,"") | AO4: =IF(AC4="Paid","Yes","Pend") -> Yes | AP4: =IF(AND(AO4="Pend",T4<2),"Pend",IF(T4=1,"Yes","XX")) -> Yes | AQ4: =IFERROR(VLOOKUP(Z4,InvBal!$L$4:$P$600,4,FALSE),"Pend") -> Pend | AR4: =IFERROR(VLOOKUP(D4,Manual!$C$1:$E$22,2,FALSE),"Pend") -> Pend | AS4: =IF(OR(AP4="Yes",AQ4="Yes",AR4="Yes"),"Yes","") -> Yes | AT4: =IF(R4="Delivered","Yes","") -> Yes | AU4: =IF(AND(AS4="Yes",AT4="Yes"),"Yes","") -> Yes | AV4: =IFERROR(VLOOKUP(D4,'Receivable Invoice Detail'!$S$1:$U$3014,3,FALSE),0) -> 0 | AW4: =IF(AU4="Yes",AI4-AV4,0) -> 945.24006
A5: 1 | B5: SO16353 | C5: PO-007646 | D5: INV12591 | E5: Sling-Choker Manufacturing - Timmins | F5: 45659.574 | G5: 45659.707 | H5: 45673 | I5: Ian Trottier | J5: CAD | K5: 1 | L5: 2369.71 | M5: 0 | N5: 1642.9592 | O5: 2097.09 | P5: 272.62 | Q5: 2369.71 | R5: Delivered | T5: =IF(A5="",T4,A5) -> 1 | U5: =IF(F5="",U4,MONTH(F5)) -> 1 | V5: =IF(F5="",V4,YEAR(F5)) -> 2025 | W5: =IF(AC5="Paid",MONTH(AD5),"") -> 2 | X5: =IF(AC5="Paid",YEAR(AD5),"") -> 2025 | Y5: =IF(C5="",Y4,N5/L5) -> 0.69331656 | Z5: =IF(B5="",Z4,B5) -> SO16353 | AA5: =IF(F5="",AA4,F5) -> 45659.574 | AB5: =IF(D5="","No Inv",D5) -> INV12591 | AC5: =IFERROR(VLOOKUP(D5,CAARStatus!$A$2:$AA$1600,22,FALSE),"Not invoiced") -> Paid | AD5: =IF(AC5="Paid",IFERROR(VLOOKUP(D5,CAARStatus!$A$2:$AA$1600,6,FALSE),"Pending"),"Pending") -> 45707 | AE5: =IF(C5="",AE4,C5) -> PO-007646 | AF5: =IF(E5="",AF4,E5) -> Sling-Choker Manufacturing - Timmins | AG5: =IF(J5="",AG4,J5) -> CAD | AH5: =IFERROR(IF(AG5="CAD",O5,O5/K5),0) -> 2097.09 | AI5: =IF(L5-N5=0,VLOOKUP(U5,rate!A$4:B$15,2,FALSE)*AH5,IF(AG5="USD",O5,AH5*Y5)) -> 1453.9472 | AJ5: =IFERROR(AI5/AH5,0) -> 0.69331656 | AK5: =-IF(AG5="CAD",IFERROR(VLOOKUP(D5,CAARStatus!$A$1:$Y$1600,16,FALSE),0),0) -> -2097.09 | AL5: =-IF(AG5="USD",IFERROR(VLOOKUP(D5,CAARStatus!$A$1:$Y$1600,11,FALSE),0),0) -> 0 | AM5: =IF(AG5="CAD",AH5+AK5,"") -> 0 | AN5: =IF(AG5="USD",AI5+AL5,"") | AO5: =IF(AC5="Paid","Yes","Pend") -> Yes | AP5: =IF(AND(AO5="Pend",T5<2),"Pend",IF(T5=1,"Yes","XX")) -> Yes | AQ5: =IFERROR(VLOOKUP(Z5,InvBal!$L$4:$P$600,4,FALSE),"Pend") -> Pend | AR5: =IFERROR(VLOOKUP(D5,Manual!$C$1:$E$22,2,FALSE),"Pend") -> Pend | AS5: =IF(OR(AP5="Yes",AQ5="Yes",AR5="Yes"),"Yes","") -> Yes | AT5: =IF(R5="Delivered","Yes","") -> Yes | AU5: =IF(AND(AS5="Yes",AT5="Yes"),"Yes","") -> Yes | AV5: =IFERROR(VLOOKUP(D5,'Receivable Invoice Detail'!$S$1:$U$3014,3,FALSE),0) -> 0 | AW5: =IF(AU5="Yes",AI5-AV5,0) -> 1453.9472
A6: 1 | B6: SO16359 | C6: 5334612 | D6: INV12502 | E6: Corrosion Fluid Products Corp., Corrosion Fluid Products Corp. - Chicago | F6: 45663.493 | G6: 45664.592 | H6: 45665 | I6: Ian Trottier | J6: USD | K6: 0.69628222 | L6: 144.20877 | M6: 0 | N6: 100.41 | O6: 100.41 | Q6: 100.41 | R6: Delivered | T6: =IF(A6="",T5,A6) -> 1 | U6: =IF(F6="",U5,MONTH(F6)) -> 1 | V6: =IF(F6="",V5,YEAR(F6)) -> 2025 | W6: =IF(AC6="Paid",MONTH(AD6),"") -> 2 | X6: =IF(AC6="Paid",YEAR(AD6),"") -> 2025 | Y6: =IF(C6="",Y5,N6/L6) -> 0.69628222 | Z6: =IF(B6="",Z5,B6) -> SO16359 | AA6: =IF(F6="",AA5,F6) -> 45663.493 | AB6: =IF(D6="","No Inv",D6) -> INV12502 | AC6: =IFERROR(VLOOKUP(D6,CAARStatus!$A$2:$AA$1600,22,FALSE),"Not invoiced") -> Paid | AD6: =IF(AC6="Paid",IFERROR(VLOOKUP(D6,CAARStatus!$A$2:$AA$1600,6,FALSE),"Pending"),"Pending") -> 45701 | AE6: =IF(C6="",AE5,C6) -> 5334612 | AF6: =IF(E6="",AF5,E6) -> Corrosion Fluid Products Corp., Corrosion Fluid Products Corp. - Chicago | AG6: =IF(J6="",AG5,J6) -> USD | AH6: =IFERROR(IF(AG6="CAD",O6,O6/K6),0) -> 144.20877 | AI6: =IF(L6-N6=0,VLOOKUP(U6,rate!A$4:B$15,2,FALSE)*AH6,IF(AG6="USD",O6,AH6*Y6)) -> 100.41 | AJ6: =IFERROR(AI6/AH6,0) -> 0.69628222 | AK6: =-IF(AG6="CAD",IFERROR(VLOOKUP(D6,CAARStatus!$A$1:$Y$1600,16,FALSE),0),0) -> 0 | AL6: =-IF(AG6="USD",IFERROR(VLOOKUP(D6,CAARStatus!$A$1:$Y$1600,11,FALSE),0),0) -> -100.41 | AM6: =IF(AG6="CAD",AH6+AK6,"") | AN6: =IF(AG6="USD",AI6+AL6,"") -> 0 | AO6: =IF(AC6="Paid","Yes","Pend") -> Yes | AP6: =IF(AND(AO6="Pend",T6<2),"Pend",IF(T6=1,"Yes","XX")) -> Yes | AQ6: =IFERROR(VLOOKUP(Z6,InvBal!$L$4:$P$600,4,FALSE),"Pend") -> Pend | AR6: =IFERROR(VLOOKUP(D6,Manual!$C$1:$E$22,2,FALSE),"Pend") -> Pend | AS6: =IF(OR(AP6="Yes",AQ6="Yes",AR6="Yes"),"Yes","") -> Yes | AT6: =IF(R6="Delivered","Yes","") -> Yes | AU6: =IF(AND(AS6="Yes",AT6="Yes"),"Yes","") -> Yes | AV6: =IFERROR(VLOOKUP(D6,'Receivable Invoice Detail'!$S$1:$U$3014,3,FALSE),0) -> 0 | AW6: =IF(AU6="Yes",AI6-AV6,0) -> 100.41
A7: 1 | B7: SO16360 | C7: 6633 | D7: INV12492 | E7: Hyperflo | F7: 45663.509 | G7: 45663.583 | H7: 45664 | I7: Ian Trottier | J7: CAD | K7: 1 | L7: 1006.02 | M7: 0 | N7: 700.47384 | O7: 958.11 | P7: 47.91 | Q7: 1006.02 | R7: Delivered | T7: =IF(A7="",T6,A7) -> 1 | U7: =IF(F7="",U6,MONTH(F7)) -> 1 | V7: =IF(F7="",V6,YEAR(F7)) -> 2025 | W7: =IF(AC7="Paid",MONTH(AD7),"") -> 2 | X7: =IF(AC7="Paid",YEAR(AD7),"") -> 2025 | Y7: =IF(C7="",Y6,N7/L7) -> 0.69628222 | Z7: =IF(B7="",Z6,B7) -> SO16360 | AA7: =IF(F7="",AA6,F7) -> 45663.509 | AB7: =IF(D7="","No Inv",D7) -> INV12492 | AC7: =IFERROR(VLOOKUP(D7,CAARStatus!$A$2:$AA$1600,22,FALSE),"Not invoiced") -> Paid | AD7: =IF(AC7="Paid",IFERROR(VLOOKUP(D7,CAARStatus!$A$2:$AA$1600,6,FALSE),"Pending"),"Pending") -> 45709 | AE7: =IF(C7="",AE6,C7) -> 6633 | AF7: =IF(E7="",AF6,E7) -> Hyperflo | AG7: =IF(J7="",AG6,J7) -> CAD | AH7: =IFERROR(IF(AG7="CAD",O7,O7/K7),0) -> 958.11 | AI7: =IF(L7-N7=0,VLOOKUP(U7,rate!A$4:B$15,2,FALSE)*AH7,IF(AG7="USD",O7,AH7*Y7)) -> 667.11496 | AJ7: =IFERROR(AI7/AH7,0) -> 0.69628222 | AK7: =-IF(AG7="CAD",IFERROR(VLOOKUP(D7,CAARStatus!$A$1:$Y$1600,16,FALSE),0),0) -> -958.11 | AL7: =-IF(AG7="USD",IFERROR(VLOOKUP(D7,CAARStatus!$A$1:$Y$1600,11,FALSE),0),0) -> 0 | AM7: =IF(AG7="CAD",AH7+AK7,"") -> 0 | AN7: =IF(AG7="USD",AI7+AL7,"") | AO7: =IF(AC7="Paid","Yes","Pend") -> Yes | AP7: =IF(AND(AO7="Pend",T7<2),"Pend",IF(T7=1,"Yes","XX")) -> Yes | AQ7: =IFERROR(VLOOKUP(Z7,InvBal!$L$4:$P$600,4,FALSE),"Pend") -> Pend | AR7: =IFERROR(VLOOKUP(D7,Manual!$C$1:$E$22,2,FALSE),"Pend") -> Pend | AS7: =IF(OR(AP7="Yes",AQ7="Yes",AR7="Yes"),"Yes","") -> Yes | AT7: =IF(R7="Delivered","Yes","") -> Yes | AU7: =IF(AND(AS7="Yes",AT7="Yes"),"Yes","") -> Yes | AV7: =IFERROR(VLOOKUP(D7,'Receivable Invoice Detail'!$S$1:$U$3014,3,FALSE),0) -> 0 | AW7: =IF(AU7="Yes",AI7-AV7,0) -> 667.11496
A8: 1 | B8: SO16361 | C8: 007673 | D8: INV12901 | E8: Sling-Choker Manufacturing - Timmins | F8: 45663.524 | G8: 45673.552 | H8: 45750 | I8: Ian Trottier | J8: CAD | K8: 1 | L8: 29994.38 | M8: 0 | N8: 20856.609 | O8: 26543.7 | P8: 3450.68 | Q8: 29994.38 | R8: Delivered | T8: =IF(A8="",T7,A8) -> 1 | U8: =IF(F8="",U7,MONTH(F8)) -> 1 | V8: =IF(F8="",V7,YEAR(F8)) -> 2025 | W8: =IF(AC8="Paid",MONTH(AD8),"") -> 5 | X8: =IF(AC8="Paid",YEAR(AD8),"") -> 2025 | Y8: =IF(C8="",Y7,N8/L8) -> 0.69535056 | Z8: =IF(B8="",Z7,B8) -> SO16361 | AA8: =IF(F8="",AA7,F8) -> 45663.524 | AB8: =IF(D8="","No Inv",D8) -> INV12901 | AC8: =IFERROR(VLOOKUP(D8,CAARStatus!$A$2:$AA$1600,22,FALSE),"Not invoiced") -> Paid | AD8: =IF(AC8="Paid",IFERROR(VLOOKUP(D8,CAARStatus!$A$2:$AA$1600,6,FALSE),"Pending"),"Pending") -> 45798 | AE8: =IF(C8="",AE7,C8) -> 007673 | AF8: =IF(E8="",AF7,E8) -> Sling-Choker Manufacturing - Timmins | AG8: =IF(J8="",AG7,J8) -> CAD | AH8: =IFERROR(IF(AG8="CAD",O8,O8/K8),0) -> 26543.7 | AI8: =IF(L8-N8=0,VLOOKUP(U8,rate!A$4:B$15,2,FALSE)*AH8,IF(AG8="USD",O8,AH8*Y8)) -> 18457.177 | AJ8: =IFERROR(AI8/AH8,0) -> 0.69535056 | AK8: =-IF(AG8="CAD",IFERROR(VLOOKUP(D8,CAARStatus!$A$1:$Y$1600,16,FALSE),0),0) -> -26543.7 | AL8: =-IF(AG8="USD",IFERROR(VLOOKUP(D8,CAARStatus!$A$1:$Y$1600,11,FALSE),0),0) -> 0 | AM8: =IF(AG8="CAD",AH8+AK8,"") -> 0 | AN8: =IF(AG8="USD",AI8+AL8,"") | AO8: =IF(AC8="Paid","Yes","Pend") -> Yes | AP8: =IF(AND(AO8="Pend",T8<2),"Pend",IF(T8=1,"Yes","XX")) -> Yes | AQ8: =IFERROR(VLOOKUP(Z8,InvBal!$L$4:$P$600,4,FALSE),"Pend") -> Pend | AR8: =IFERROR(VLOOKUP(D8,Manual!$C$1:$E$22,2,FALSE),"Pend") -> Pend | AS8: =IF(OR(AP8="Yes",AQ8="Yes",AR8="Yes"),"Yes","") -> Yes | AT8: =IF(R8="Delivered","Yes","") -> Yes | AU8: =IF(AND(AS8="Yes",AT8="Yes"),"Yes","") -> Yes | AV8: =IFERROR(VLOOKUP(D8,'Receivable Invoice Detail'!$S$1:$U$3014,3,FALSE),0) -> 0 | AW8: =IF(AU8="Yes",AI8-AV8,0) -> 18457.177
A9: 1 | B9: SO16362 | C9: P349617 | D9: INV12503 | E9: Covia Corp - Junction City | F9: 45663.531 | G9: 45664.582 | H9: 45665 | I9: Marlen Martinez | J9: CAD | K9: 1 | L9: 8795 | M9: 0 | N9: 6131.3693 | O9: 8795 | Q9: 8795 | R9: Delivered | T9: =IF(A9="",T8,A9) -> 1 | U9: =IF(F9="",U8,MONTH(F9)) -> 1 | V9: =IF(F9="",V8,YEAR(F9)) -> 2025 | W9: =IF(AC9="Paid",MONTH(AD9),"") -> 4 | X9: =IF(AC9="Paid",YEAR(AD9),"") -> 2025 | Y9: =IF(C9="",Y8,N9/L9) -> 0.69714261 | Z9: =IF(B9="",Z8,B9) -> SO16362 | AA9: =IF(F9="",AA8,F9) -> 45663.531 | AB9: =IF(D9="","No Inv",D9) -> INV12503 | AC9: =IFERROR(VLOOKUP(D9,CAARStatus!$A$2:$AA$1600,22,FALSE),"Not invoiced") -> Paid | AD9: =IF(AC9="Paid",IFERROR(VLOOKUP(D9,CAARStatus!$A$2:$AA$1600,6,FALSE),"Pending"),"Pending") -> 45754 | AE9: =IF(C9="",AE8,C9) -> P349617 | AF9: =IF(E9="",AF8,E9) -> Covia Corp - Junction City | AG9: =IF(J9="",AG8,J9) -> CAD | AH9: =IFERROR(IF(AG9="CAD",O9,O9/K9),0) -> 8795 | AI9: =IF(L9-N9=0,VLOOKUP(U9,rate!A$4:B$15,2,FALSE)*AH9,IF(AG9="USD",O9,AH9*Y9)) -> 6131.3693 | AJ9: =IFERROR(AI9/AH9,0) -> 0.69714261 | AK9: =-IF(AG9="CAD",IFERROR(VLOOKUP(D9,CAARStatus!$A$1:$Y$1600,16,FALSE),0),0) -> -12684.334 | AL9: =-IF(AG9="USD",IFERROR(VLOOKUP(D9,CAARStatus!$A$1:$Y$1600,11,FALSE),0),0) -> 0 | AM9: =IF(AG9="CAD",AH9+AK9,"") -> -3889.3339 | AN9: =IF(AG9="USD",AI9+AL9,"") | AO9: =IF(AC9="Paid","Yes","Pend") -> Yes | AP9: =IF(AND(AO9="Pend",T9<2),"Pend",IF(T9=1,"Yes","XX")) -> Yes | AQ9: =IFERROR(VLOOKUP(Z9,InvBal!$L$4:$P$600,4,FALSE),"Pend") -> Pend | AR9: =IFERROR(VLOOKUP(D9,Manual!$C$1:$E$22,2,FALSE),"Pend") -> Pend | AS9: =IF(OR(AP9="Yes",AQ9="Yes",AR9="Yes"),"Yes","") -> Yes | AT9: =IF(R9="Delivered","Yes","") -> Yes | AU9: =IF(AND(AS9="Yes",AT9="Yes"),"Yes","") -> Yes | AV9: =IFERROR(VLOOKUP(D9,'Receivable Invoice Detail'!$S$1:$U$3014,3,FALSE),0) -> 845 | AW9: =IF(AU9="Yes",AI9-AV9,0) -> 5286.3693
A10: 1 | B10: SO16363 | C10: 2961 | D10: INV12685 | E10: Les Pompes du St-Laurent Inc. | F10: 45663.564 | G10: 45663.565 | H10: 45698 | I10: Ian Trottier | J10: CAD | K10: 1 | L10: 1135.51 | M10: 0 | N10: 790.63542 | O10: 1081.44 | P10: 54.07 | Q10: 1135.51 | R10: Delivered | T10: =IF(A10="",T9,A10) -> 1 | U10: =IF(F10="",U9,MONTH(F10)) -> 1 | V10: =IF(F10="",V9,YEAR(F10)) -> 2025 | W10: =IF(AC10="Paid",MONTH(AD10),"") -> 4 | X10: =IF(AC10="Paid",YEAR(AD10),"") -> 2025 | Y10: =IF(C10="",Y9,N10/L10) -> 0.69628222 | Z10: =IF(B10="",Z9,B10) -> SO16363 | AA10: =IF(F10="",AA9,F10) -> 45663.564 | AB10: =IF(D10="","No Inv",D10) -> INV12685 | AC10: =IFERROR(VLOOKUP(D10,CAARStatus!$A$2:$AA$1600,22,FALSE),"Not invoiced") -> Paid | AD10: =IF(AC10="Paid",IFERROR(VLOOKUP(D10,CAARStatus!$A$2:$AA$1600,6,FALSE),"Pending"),"Pending") -> 45768 | AE10: =IF(C10="",AE9,C10) -> 2961 | AF10: =IF(E10="",AF9,E10) -> Les Pompes du St-Laurent Inc. | AG10: =IF(J10="",AG9,J10) -> CAD | AH10: =IFERROR(IF(AG10="CAD",O10,O10/K10),0) -> 1081.44 | AI10: =IF(L10-N10=0,VLOOKUP(U10,rate!A$4:B$15,2,FALSE)*AH10,IF(AG10="USD",O10,AH10*Y10)) -> 752.98744 | AJ10: =IFERROR(AI10/AH10,0) -> 0.69628222 | AK10: =-IF(AG10="CAD",IFERROR(VLOOKUP(D10,CAARStatus!$A$1:$Y$1600,16,FALSE),0),0) -> -1081.44 | AL10: =-IF(AG10="USD",IFERROR(VLOOKUP(D10,CAARStatus!$A$1:$Y$1600,11,FALSE),0),0) -> 0 | AM10: =IF(AG10="CAD",AH10+AK10,"") -> 0 | AN10: =IF(AG10="USD",AI10+AL10,"") | AO10: =IF(AC10="Paid","Yes","Pend") -> Yes | AP10: =IF(AND(AO10="Pend",T10<2),"Pend",IF(T10=1,"Yes","XX")) -> Yes | AQ10: =IFERROR(VLOOKUP(Z10,InvBal!$L$4:$P$600,4,FALSE),"Pend") -> Pend | AR10: =IFERROR(VLOOKUP(D10,Manual!$C$1:$E$22,2,FALSE),"Pend") -> Pend | AS10: =IF(OR(AP10="Yes",AQ10="Yes",AR10="Yes"),"Yes","") -> Yes | AT10: =IF(R10="Delivered","Yes","") -> Yes | AU10: =IF(AND(AS10="Yes",AT10="Yes"),"Yes","") -> Yes | AV10: =IFERROR(VLOOKUP(D10,'Receivable Invoice Detail'!$S$1:$U$3014,3,FALSE),0) -> 0 | AW10: =IF(AU10="Yes",AI10-AV10,0) -> 752.98744
A11: 1 | B11: SO16364 | C11: 003247 | D11: INV12837 | E11: Eleazar General & Industrial Supplies Limited | F11: 45663.57 | G11: 45667.613 | H11: 45751 | I11: Ian Trottier | J11: USD | K11: 0.69455773 | L11: 1896.8762 | M11: 0 | N11: 1317.49 | O11: 1317.49 | Q11: 1317.49 | R11: Delivered | T11: =IF(A11="",T10,A11) -> 1 | U11: =IF(F11="",U10,MONTH(F11)) -> 1 | V11: =IF(F11="",V10,YEAR(F11)) -> 2025 | W11: =IF(AC11="Paid",MONTH(AD11),"") -> 4 | X11: =IF(AC11="Paid",YEAR(AD11),"") -> 2025 | Y11: =IF(C11="",Y10,N11/L11) -> 0.69455773 | Z11: =IF(B11="",Z10,B11) -> SO16364 | AA11: =IF(F11="",AA10,F11) -> 45663.57 | AB11: =IF(D11="","No Inv",D11) -> INV12837 | AC11: =IFERROR(VLOOKUP(D11,CAARStatus!$A$2:$AA$1600,22,FALSE),"Not invoiced") -> Paid | AD11: =IF(AC11="Paid",IFERROR(VLOOKUP(D11,CAARStatus!$A$2:$AA$1600,6,FALSE),"Pending"),"Pending") -> 45754 | AE11: =IF(C11="",AE10,C11) -> 003247 | AF11: =IF(E11="",AF10,E11) -> Eleazar General & Industrial Supplies Limited | AG11: =IF(J11="",AG10,J11) -> USD | AH11: =IFERROR(IF(AG11="CAD",O11,O11/K11),0) -> 1896.8762 | AI11: =IF(L11-N11=0,VLOOKUP(U11,rate!A$4:B$15,2,FALSE)*AH11,IF(AG11="USD",O11,AH11*Y11)) -> 1317.49 | AJ11: =IFERROR(AI11/AH11,0) -> 0.69455773 | AK11: =-IF(AG11="CAD",IFERROR(VLOOKUP(D11,CAARStatus!$A$1:$Y$1600,16,FALSE),0),0) -> 0 | AL11: =-IF(AG11="USD",IFERROR(VLOOKUP(D11,CAARStatus!$A$1:$Y$1600,11,FALSE),0),0) -> -1317.49 | AM11: =IF(AG11="CAD",AH11+AK11,"") | AN11: =IF(AG11="USD",AI11+AL11,"") -> 0 | AO11: =IF(AC11="Paid","Yes","Pend") -> Yes | AP11: =IF(AND(AO11="Pend",T11<2),"Pend",IF(T11=1,"Yes","XX")) -> Yes | AQ11: =IFERROR(VLOOKUP(Z11,InvBal!$L$4:$P$600,4,FALSE),"Pend") -> Pend | AR11: =IFERROR(VLOOKUP(D11,Manual!$C$1:$E$22,2,FALSE),"Pend") -> Pend | AS11: =IF(OR(AP11="Yes",AQ11="Yes",AR11="Yes"),"Yes","") -> Yes | AT11: =IF(R11="Delivered","Yes","") -> Yes | AU11: =IF(AND(AS11="Yes",AT11="Yes"),"Yes","") -> Yes | AV11: =IFERROR(VLOOKUP(D11,'Receivable Invoice Detail'!$S$1:$U$3014,3,FALSE),0) -> 0 | AW11: =IF(AU11="Yes",AI11-AV11,0) -> 1317.49
A12: 1 | B12: SO16368 | C12: M-083469 | D12: INV12509 | E12: Grant Aggregate | F12: 45663.694 | G12: 45666.408 | H12: 45667 | I12: Ian Trottier | J12: CAD | K12: 1 | L12: 17048.1 | M12: 0 | N12: 11840.89 | O12: 15086.8 | P12: 1961.3 | Q12: 17048.1 | R12: Delivered | T12: =IF(A12="",T11,A12) -> 1 | U12: =IF(F12="",U11,MONTH(F12)) -> 1 | V12: =IF(F12="",V11,YEAR(F12)) -> 2025 | W12: =IF(AC12="Paid",MONTH(AD12),"") -> 3 | X12: =IF(AC12="Paid",YEAR(AD12),"") -> 2025 | Y12: =IF(C12="",Y11,N12/L12) -> 0.69455773 | Z12: =IF(B12="",Z11,B12) -> SO16368 | AA12: =IF(F12="",AA11,F12) -> 45663.694 | AB12: =IF(D12="","No Inv",D12) -> INV12509 | AC12: =IFERROR(VLOOKUP(D12,CAARStatus!$A$2:$AA$1600,22,FALSE),"Not invoiced") -> Paid | AD12: =IF(AC12="Paid",IFERROR(VLOOKUP(D12,CAARStatus!$A$2:$AA$1600,6,FALSE),"Pending"),"Pending") -> 45721 | AE12: =IF(C12="",AE11,C12) -> M-083469 | AF12: =IF(E12="",AF11,E12) -> Grant Aggregate | AG12: =IF(J12="",AG11,J12) -> CAD | AH12: =IFERROR(IF(AG12="CAD",O12,O12/K12),0) -> 15086.8 | AI12: =IF(L12-N12=0,VLOOKUP(U12,rate!A$4:B$15,2,FALSE)*AH12,IF(AG12="USD",O12,AH12*Y12)) -> 10478.654 | AJ12: =IFERROR(AI12/AH12,0) -> 0.69455773 | AK12: =-IF(AG12="CAD",IFERROR(VLOOKUP(D12,CAARStatus!$A$1:$Y$1600,16,FALSE),0),0) -> -15086.8 | AL12: =-IF(AG12="USD",IFERROR(VLOOKUP(D12,CAARStatus!$A$1:$Y$1600,11,FALSE),0),0) -> 0 | AM12: =IF(AG12="CAD",AH12+AK12,"") -> 0 | AN12: =IF(AG12="USD",AI12+AL12,"") | AO12: =IF(AC12="Paid","Yes","Pend") -> Yes | AP12: =IF(AND(AO12="Pend",T12<2),"Pend",IF(T12=1,"Yes","XX")) -> Yes | AQ12: =IFERROR(VLOOKUP(Z12,InvBal!$L$4:$P$600,4,FALSE),"Pend") -> Pend | AR12: =IFERROR(VLOOKUP(D12,Manual!$C$1:$E$22,2,FALSE),"Pend") -> Pend | AS12: =IF(OR(AP12="Yes",AQ12="Yes",AR12="Yes"),"Yes","") -> Yes | AT12: =IF(R12="Delivered","Yes","") -> Yes | AU12: =IF(AND(AS12="Yes",AT12="Yes"),"Yes","") -> Yes | AV12: =IFERROR(VLOOKUP(D12,'Receivable Invoice Detail'!$S$1:$U$3014,3,FALSE),0) -> 0 | AW12: =IF(AU12="Yes",AI12-AV12,0) -> 10478.654
A13: 1 | B13: SO16369 | C13: PO13146 | D13: INV12493 | E13: Manufacture Sling-Choker (Val-d’Or) Ltée | F13: 45664.409 | G13: 45664.622 | H13: 45665 | I13: Ian Trottier | J13: CAD | K13: 1 | L13: 117.99 | M13: 0 | N13: 82.255857 | O13: 112.37 | P13: 5.62 | Q13: 117.99 | R13: Delivered | T13: =IF(A13="",T12,A13) -> 1 | U13: =IF(F13="",U12,MONTH(F13)) -> 1 | V13: =IF(F13="",V12,YEAR(F13)) -> 2025 | W13: =IF(AC13="Paid",MONTH(AD13),"") -> 2 | X13: =IF(AC13="Paid",YEAR(AD13),"") -> 2025 | Y13: =IF(C13="",Y12,N13/L13) -> 0.69714261 | Z13: =IF(B13="",Z12,B13) -> SO16369 | AA13: =IF(F13="",AA12,F13) -> 45664.409 | AB13: =IF(D13="","No Inv",D13) -> INV12493 | AC13: =IFERROR(VLOOKUP(D13,CAARStatus!$A$2:$AA$1600,22,FALSE),"Not invoiced") -> Paid | AD13: =IF(AC13="Paid",IFERROR(VLOOKUP(D13,CAARStatus!$A$2:$AA$1600,6,FALSE),"Pending"),"Pending") -> 45693 | AE13: =IF(C13="",AE12,C13) -> PO13146 | AF13: =IF(E13="",AF12,E13) -> Manufacture Sling-Choker (Val-d’Or) Ltée | AG13: =IF(J13="",AG12,J13) -> CAD | AH13: =IFERROR(IF(AG13="CAD",O13,O13/K13),0) -> 112.37 | AI13: =IF(L13-N13=0,VLOOKUP(U13,rate!A$4:B$15,2,FALSE)*AH13,IF(AG13="USD",O13,AH13*Y13)) -> 78.337915 | AJ13: =IFERROR(AI13/AH13,0) -> 0.69714261 | AK13: =-IF(AG13="CAD",IFERROR(VLOOKUP(D13,CAARStatus!$A$1:$Y$1600,16,FALSE),0),0) -> -112.37 | AL13: =-IF(AG13="USD",IFERROR(VLOOKUP(D13,CAARStatus!$A$1:$Y$1600,11,FALSE),0),0) -> 0 | AM13: =IF(AG13="CAD",AH13+AK13,"") -> 0 | AN13: =IF(AG13="USD",AI13+AL13,"") | AO13: =IF(AC13="Paid","Yes","Pend") -> Yes | AP13: =IF(AND(AO13="Pend",T13<2),"Pend",IF(T13=1,"Yes","XX")) -> Yes | AQ13: =IFERROR(VLOOKUP(Z13,InvBal!$L$4:$P$600,4,FALSE),"Pend") -> Pend | AR13: =IFERROR(VLOOKUP(D13,Manual!$C$1:$E$22,2,FALSE),"Pend") -> Pend | AS13: =IF(OR(AP13="Yes",AQ13="Yes",AR13="Yes"),"Yes","") -> Yes | AT13: =IF(R13="Delivered","Yes","") -> Yes | AU13: =IF(AND(AS13="Yes",AT13="Yes"),"Yes","") -> Yes | AV13: =IFERROR(VLOOKUP(D13,'Receivable Invoice Detail'!$S$1:$U$3014,3,FALSE),0) -> 0 | AW13: =IF(AU13="Yes",AI13-AV13,0) -> 78.337915
A14: 1 | B14: SO16372 | C14: 2991 | D14: INV12779 | E14: Les Pompes du St-Laurent Inc. | F14: 45664.491 | G14: 45673.632 | H14: 45720 | I14: Ian Trottier | J14: CAD | K14: 1 | L14: 1657.93 | M14: 0 | N14: 1152.8426 | O14: 1578.98 | P14: 78.95 | Q14: 1657.93 | R14: Delivered | T14: =IF(A14="",T13,A14) -> 1 | U14: =IF(F14="",U13,MONTH(F14)) -> 1 | V14: =IF(F14="",V13,YEAR(F14)) -> 2025 | W14: =IF(AC14="Paid",MONTH(AD14),"") -> 4 | X14: =IF(AC14="Paid",YEAR(AD14),"") -> 2025 | Y14: =IF(C14="",Y13,N14/L14) -> 0.69535056 | Z14: =IF(B14="",Z13,B14) -> SO16372 | AA14: =IF(F14="",AA13,F14) -> 45664.491 | AB14: =IF(D14="","No Inv",D14) -> INV12779 | AC14: =IFERROR(VLOOKUP(D14,CAARStatus!$A$2:$AA$1600,22,FALSE),"Not invoiced") -> Paid | AD14: =IF(AC14="Paid",IFERROR(VLOOKUP(D14,CAARStatus!$A$2:$AA$1600,6,FALSE),"Pending"),"Pending") -> 45772 | AE14: =IF(C14="",AE13,C14) -> 2991 | AF14: =IF(E14="",AF13,E14) -> Les Pompes du St-Laurent Inc. | AG14: =IF(J14="",AG13,J14) -> CAD | AH14: =IFERROR(IF(AG14="CAD",O14,O14/K14),0) -> 1578.98 | AI14: =IF(L14-N14=0,VLOOKUP(U14,rate!A$4:B$15,2,FALSE)*AH14,IF(AG14="USD",O14,AH14*Y14)) -> 1097.9446 | AJ14: =IFERROR(AI14/AH14,0) -> 0.69535056 | AK14: =-IF(AG14="CAD",IFERROR(VLOOKUP(D14,CAARStatus!$A$1:$Y$1600,16,FALSE),0),0) -> -1578.98 | AL14: =-IF(AG14="USD",IFERROR(VLOOKUP(D14,CAARStatus!$A$1:$Y$1600,11,FALSE),0),0) -> 0 | AM14: =IF(AG14="CAD",AH14+AK14,"") -> 0 | AN14: =IF(AG14="USD",AI14+AL14,"") | AO14: =IF(AC14="Paid","Yes","Pend") -> Yes | AP14: =IF(AND(AO14="Pend",T14<2),"Pend",IF(T14=1,"Yes","XX")) -> Yes | AQ14: =IFERROR(VLOOKUP(Z14,InvBal!$L$4:$P$600,4,FALSE),"Pend") -> Pend | AR14: =IFERROR(VLOOKUP(D14,Manual!$C$1:$E$22,2,FALSE),"Pend") -> Pend | AS14: =IF(OR(AP14="Yes",AQ14="Yes",AR14="Yes"),"Yes","") -> Yes | AT14: =IF(R14="Delivered","Yes","") -> Yes | AU14: =IF(AND(AS14="Yes",AT14="Yes"),"Yes","") -> Yes | AV14: =IFERROR(VLOOKUP(D14,'Receivable Invoice Detail'!$S$1:$U$3014,3,FALSE),0) -> 0 | AW14: =IF(AU14="Yes",AI14-AV14,0) -> 1097.9446
A15: 1 | B15: SO16374 | C15: 2967 | D15: INV12505 | E15: Les Pompes du St-Laurent Inc. | F15: 45664.533 | G15: 45665.677 | H15: 45666 | I15: Ian Trottier | J15: CAD | K15: 1 | L15: 3783.15 | M15: 0 | N15: 2631.4956 | O15: 3603 | P15: 180.15 | Q15: 3783.15 | R15: Delivered | T15: =IF(A15="",T14,A15) -> 1 | U15: =IF(F15="",U14,MONTH(F15)) -> 1 | V15: =IF(F15="",V14,YEAR(F15)) -> 2025 | W15: =IF(AC15="Paid",MONTH(AD15),"") -> 2 | X15: =IF(AC15="Paid",YEAR(AD15),"") -> 2025 | Y15: =IF(C15="",Y14,N15/L15) -> 0.6955832 | Z15: =IF(B15="",Z14,B15) -> SO16374 | AA15: =IF(F15="",AA14,F15) -> 45664.533 | AB15: =IF(D15="","No Inv",D15) -> INV12505 | AC15: =IFERROR(VLOOKUP(D15,CAARStatus!$A$2:$AA$1600,22,FALSE),"Not invoiced") -> Paid | AD15: =IF(AC15="Paid",IFERROR(VLOOKUP(D15,CAARStatus!$A$2:$AA$1600,6,FALSE),"Pending"),"Pending") -> 45706 | AE15: =IF(C15="",AE14,C15) -> 2967 | AF15: =IF(E15="",AF14,E15) -> Les Pompes du St-Laurent Inc. | AG15: =IF(J15="",AG14,J15) -> CAD | AH15: =IFERROR(IF(AG15="CAD",O15,O15/K15),0) -> 3603 | AI15: =IF(L15-N15=0,VLOOKUP(U15,rate!A$4:B$15,2,FALSE)*AH15,IF(AG15="USD",O15,AH15*Y15)) -> 2506.1863 | AJ15: =IFERROR(AI15/AH15,0) -> 0.6955832 | AK15: =-IF(AG15="CAD",IFERROR(VLOOKUP(D15,CAARStatus!$A$1:$Y$1600,16,FALSE),0),0) -> -3603 | AL15: =-IF(AG15="USD",IFERROR(VLOOKUP(D15,CAARStatus!$A$1:$Y$1600,11,FALSE),0),0) -> 0 | AM15: =IF(AG15="CAD",AH15+AK15,"") -> 0 | AN15: =IF(AG15="USD",AI15+AL15,"") | AO15: =IF(AC15="Paid","Yes","Pend") -> Yes | AP15: =IF(AND(AO15="Pend",T15<2),"Pend",IF(T15=1,"Yes","XX")) -> Yes | AQ15: =IFERROR(VLOOKUP(Z15,InvBal!$L$4:$P$600,4,FALSE),"Pend") -> Pend | AR15: =IFERROR(VLOOKUP(D15,Manual!$C$1:$E$22,2,FALSE),"Pend") -> Pend | AS15: =IF(OR(AP15="Yes",AQ15="Yes",AR15="Yes"),"Yes","") -> Yes | AT15: =IF(R15="Delivered","Yes","") -> Yes | AU15: =IF(AND(AS15="Yes",AT15="Yes"),"Yes","") -> Yes | AV15: =IFERROR(VLOOKUP(D15,'Receivable Invoice Detail'!$S$1:$U$3014,3,FALSE),0) -> 0 | AW15: =IF(AU15="Yes",AI15-AV15,0) -> 2506.1863
A16: 1 | B16: SO16375 | C16: P349794 | D16: INV12504 | E16: Covia Corp - Junction City | F16: 45664.545 | G16: 45665.577 | H16: 45666 | I16: Marlen Martinez | J16: CAD | K16: 1 | L16: 5506 | M16: 0 | N16: 3829.8811 | O16: 5506 | Q16: 5506 | R16: Delivered | T16: =IF(A16="",T15,A16) -> 1 | U16: =IF(F16="",U15,MONTH(F16)) -> 1 | V16: =IF(F16="",V15,YEAR(F16)) -> 2025 | W16: =IF(AC16="Paid",MONTH(AD16),"") -> 4 | X16: =IF(AC16="Paid",YEAR(AD16),"") -> 2025 | Y16: =IF(C16="",Y15,N16/L16) -> 0.6955832 | Z16: =IF(B16="",Z15,B16) -> SO16375 | AA16: =IF(F16="",AA15,F16) -> 45664.545 | AB16: =IF(D16="","No Inv",D16) -> INV12504 | AC16: =IFERROR(VLOOKUP(D16,CAARStatus!$A$2:$AA$1600,22,FALSE),"Not invoiced") -> Paid | AD16: =IF(AC16="Paid",IFERROR(VLOOKUP(D16,CAARStatus!$A$2:$AA$1600,6,FALSE),"Pending"),"Pending") -> 45754 | AE16: =IF(C16="",AE15,C16) -> P349794 | AF16: =IF(E16="",AF15,E16) -> Covia Corp - Junction City | AG16: =IF(J16="",AG15,J16) -> CAD | AH16: =IFERROR(IF(AG16="CAD",O16,O16/K16),0) -> 5506 | AI16: =IF(L16-N16=0,VLOOKUP(U16,rate!A$4:B$15,2,FALSE)*AH16,IF(AG16="USD",O16,AH16*Y16)) -> 3829.8811 | AJ16: =IFERROR(AI16/AH16,0) -> 0.6955832 | AK16: =-IF(AG16="CAD",IFERROR(VLOOKUP(D16,CAARStatus!$A$1:$Y$1600,16,FALSE),0),0) -> -7940.8689 | AL16: =-IF(AG16="USD",IFERROR(VLOOKUP(D16,CAARStatus!$A$1:$Y$1600,11,FALSE),0),0) -> 0 | AM16: =IF(AG16="CAD",AH16+AK16,"") -> -2434.8689 | AN16: =IF(AG16="USD",AI16+AL16,"") | AO16: =IF(AC16="Paid","Yes","Pend") -> Yes | AP16: =IF(AND(AO16="Pend",T16<2),"Pend",IF(T16=1,"Yes","XX")) -> Yes | AQ16: =IFERROR(VLOOKUP(Z16,InvBal!$L$4:$P$600,4,FALSE),"Pend") -> Pend | AR16: =IFERROR(VLOOKUP(D16,Manual!$C$1:$E$22,2,FALSE),"Pend") -> Pend | AS16: =IF(OR(AP16="Yes",AQ16="Yes",AR16="Yes"),"Yes","") -> Yes | AT16: =IF(R16="Delivered","Yes","") -> Yes | AU16: =IF(AND(AS16="Yes",AT16="Yes"),"Yes","") -> Yes | AV16: =IFERROR(VLOOKUP(D16,'Receivable Invoice Detail'!$S$1:$U$3014,3,FALSE),0) -> 0 | AW16: =IF(AU16="Yes",AI16-AV16,0) -> 3829.8811
A17: 1 | B17: SO16376 | C17: 007656 | D17: INV12592 | E17: Sling-Choker Manufacturing - Timmins | F17: 45664.556 | G17: 45664.682 | H17: 45326 | I17: Ian Trottier | J17: CAD | K17: 1 | L17: 13951.67 | M17: 0 | N17: 9726.3036 | O17: 12346.61 | P17: 1605.06 | Q17: 13951.67 | R17: Delivered | T17: =IF(A17="",T16,A17) -> 1 | U17: =IF(F17="",U16,MONTH(F17)) -> 1 | V17: =IF(F17="",V16,YEAR(F17)) -> 2025 | W17: =IF(AC17="Paid",MONTH(AD17),"") -> 2 | X17: =IF(AC17="Paid",YEAR(AD17),"") -> 2025 | Y17: =IF(C17="",Y16,N17/L17) -> 0.69714261 | Z17: =IF(B17="",Z16,B17) -> SO16376 | AA17: =IF(F17="",AA16,F17) -> 45664.556 | AB17: =IF(D17="","No Inv",D17) -> INV12592 | AC17: =IFERROR(VLOOKUP(D17,CAARStatus!$A$2:$AA$1600,22,FALSE),"Not invoiced") -> Paid | AD17: =IF(AC17="Paid",IFERROR(VLOOKUP(D17,CAARStatus!$A$2:$AA$1600,6,FALSE),"Pending"),"Pending") -> 45707 | AE17: =IF(C17="",AE16,C17) -> 007656 | AF17: =IF(E17="",AF16,E17) -> Sling-Choker Manufacturing - Timmins | AG17: =IF(J17="",AG16,J17) -> CAD | AH17: =IFERROR(IF(AG17="CAD",O17,O17/K17),0) -> 12346.61 | AI17: =IF(L17-N17=0,VLOOKUP(U17,rate!A$4:B$15,2,FALSE)*AH17,IF(AG17="USD",O17,AH17*Y17)) -> 8607.3479 | AJ17: =IFERROR(AI17/AH17,0) -> 0.69714261 | AK17: =-IF(AG17="CAD",IFERROR(VLOOKUP(D17,CAARStatus!$A$1:$Y$1600,16,FALSE),0),0) -> -12346.61 | AL17: =-IF(AG17="USD",IFERROR(VLOOKUP(D17,CAARStatus!$A$1:$Y$1600,11,FALSE),0),0) -> 0 | AM17: =IF(AG17="CAD",AH17+AK17,"") -> 0 | AN17: =IF(AG17="USD",AI17+AL17,"") | AO17: =IF(AC17="Paid","Yes","Pend") -> Yes | AP17: =IF(AND(AO17="Pend",T17<2),"Pend",IF(T17=1,"Yes","XX")) -> Yes | AQ17: =IFERROR(VLOOKUP(Z17,InvBal!$L$4:$P$600,4,FALSE),"Pend") -> Pend | AR17: =IFERROR(VLOOKUP(D17,Manual!$C$1:$E$22,2,FALSE),"Pend") -> Pend | AS17: =IF(OR(AP17="Yes",AQ17="Yes",AR17="Yes"),"Yes","") -> Yes | AT17: =IF(R17="Delivered","Yes","") -> Yes | AU17: =IF(AND(AS17="Yes",AT17="Yes"),"Yes","") -> Yes | AV17: =IFERROR(VLOOKUP(D17,'Receivable Invoice Detail'!$S$1:$U$3014,3,FALSE),0) -> 0 | AW17: =IF(AU17="Yes",AI17-AV17,0) -> 8607.3479
A18: 1 | B18: SO16377 | C18: 316223 | D18: INV12597 | E18: Gibraltar Mine (Canada) | F18: 45664.681 | G18: 45664.716 | H18: 45706 | I18: Ian Trottier | J18: CAD | K18: 1 | L18: 5367.86 | M18: 0 | N18: 3742.1639 | O18: 5112.25 | P18: 255.61 | Q18: 5367.86 | R18: Delivered | T18: =IF(A18="",T17,A18) -> 1 | U18: =IF(F18="",U17,MONTH(F18)) -> 1 | V18: =IF(F18="",V17,YEAR(F18)) -> 2025 | W18: =IF(AC18="Paid",MONTH(AD18),"") -> 3 | X18: =IF(AC18="Paid",YEAR(AD18),"") -> 2025 | Y18: =IF(C18="",Y17,N18/L18) -> 0.69714261 | Z18: =IF(B18="",Z17,B18) -> SO16377 | AA18: =IF(F18="",AA17,F18) -> 45664.681 | AB18: =IF(D18="","No Inv",D18) -> INV12597 | AC18: =IFERROR(VLOOKUP(D18,CAARStatus!$A$2:$AA$1600,22,FALSE),"Not invoiced") -> Paid | AD18: =IF(AC18="Paid",IFERROR(VLOOKUP(D18,CAARStatus!$A$2:$AA$1600,6,FALSE),"Pending"),"Pending") -> 45721 | AE18: =IF(C18="",AE17,C18) -> 316223 | AF18: =IF(E18="",AF17,E18) -> Gibraltar Mine (Canada) | AG18: =IF(J18="",AG17,J18) -> CAD | AH18: =IFERROR(IF(AG18="CAD",O18,O18/K18),0) -> 5112.25 | AI18: =IF(L18-N18=0,VLOOKUP(U18,rate!A$4:B$15,2,FALSE)*AH18,IF(AG18="USD",O18,AH18*Y18)) -> 3563.9673 | AJ18: =IFERROR(AI18/AH18,0) -> 0.69714261 | AK18: =-IF(AG18="CAD",IFERROR(VLOOKUP(D18,CAARStatus!$A$1:$Y$1600,16,FALSE),0),0) -> -5112.25 | AL18: =-IF(AG18="USD",IFERROR(VLOOKUP(D18,CAARStatus!$A$1:$Y$1600,11,FALSE),0),0) -> 0 | AM18: =IF(AG18="CAD",AH18+AK18,"") -> 0 | AN18: =IF(AG18="USD",AI18+AL18,"") | AO18: =IF(AC18="Paid","Yes","Pend") -> Yes | AP18: =IF(AND(AO18="Pend",T18<2),"Pend",IF(T18=1,"Yes","XX")) -> Yes | AQ18: =IFERROR(VLOOKUP(Z18,InvBal!$L$4:$P$600,4,FALSE),"Pend") -> Pend | AR18: =IFERROR(VLOOKUP(D18,Manual!$C$1:$E$22,2,FALSE),"Pend") -> Pend | AS18: =IF(OR(AP18="Yes",AQ18="Yes",AR18="Yes"),"Yes","") -> Yes | AT18: =IF(R18="Delivered","Yes","") -> Yes | AU18: =IF(AND(AS18="Yes",AT18="Yes"),"Yes","") -> Yes | AV18: =IFERROR(VLOOKUP(D18,'Receivable Invoice Detail'!$S$1:$U$3014,3,FALSE),0) -> 0 | AW18: =IF(AU18="Yes",AI18-AV18,0) -> 3563.9673
A19: 1 | B19: SO16378 | C19: BC78-00052101 | D19: INV12543 | E19: Motion Industries Inc. (Canada) - Quesnel | F19: 45664.694 | G19: 45665.391 | H19: 45693 | I19: Ian Trottier | J19: CAD | K19: 1 | L19: 1036.94 | M19: 0 | N19: 721.27805 | O19: 987.57 | P19: 49.37 | Q19: 1036.94 | R19: Delivered | T19: =IF(A19="",T18,A19) -> 1 | U19: =IF(F19="",U18,MONTH(F19)) -> 1 | V19: =IF(F19="",V18,YEAR(F19)) -> 2025 | W19: =IF(AC19="Paid",MONTH(AD19),"") -> 2 | X19: =IF(AC19="Paid",YEAR(AD19),"") -> 2025 | Y19: =IF(C19="",Y18,N19/L19) -> 0.6955832 | Z19: =IF(B19="",Z18,B19) -> SO16378 | AA19: =IF(F19="",AA18,F19) -> 45664.694 | AB19: =IF(D19="","No Inv",D19) -> INV12543 | AC19: =IFERROR(VLOOKUP(D19,CAARStatus!$A$2:$AA$1600,22,FALSE),"Not invoiced") -> Paid | AD19: =IF(AC19="Paid",IFERROR(VLOOKUP(D19,CAARStatus!$A$2:$AA$1600,6,FALSE),"Pending"),"Pending") -> 45702 | AE19: =IF(C19="",AE18,C19) -> BC78-00052101 | AF19: =IF(E19="",AF18,E19) -> Motion Industries Inc. (Canada) - Quesnel | AG19: =IF(J19="",AG18,J19) -> CAD | AH19: =IFERROR(IF(AG19="CAD",O19,O19/K19),0) -> 987.57 | AI19: =IF(L19-N19=0,VLOOKUP(U19,rate!A$4:B$15,2,FALSE)*AH19,IF(AG19="USD",O19,AH19*Y19)) -> 686.9371 | AJ19: =IFERROR(AI19/AH19,0) -> 0.6955832 | AK19: =-IF(AG19="CAD",IFERROR(VLOOKUP(D19,CAARStatus!$A$1:$Y$1600,16,FALSE),0),0) -> -987.57 | AL19: =-IF(AG19="USD",IFERROR(VLOOKUP(D19,CAARStatus!$A$1:$Y$1600,11,FALSE),0),0) -> 0 | AM19: =IF(AG19="CAD",AH19+AK19,"") -> 0 | AN19: =IF(AG19="USD",AI19+AL19,"") | AO19: =IF(AC19="Paid","Yes","Pend") -> Yes | AP19: =IF(AND(AO19="Pend",T19<2),"Pend",IF(T19=1,"Yes","XX")) -> Yes | AQ19: =IFERROR(VLOOKUP(Z19,InvBal!$L$4:$P$600,4,FALSE),"Pend") -> Pend | AR19: =IFERROR(VLOOKUP(D19,Manual!$C$1:$E$22,2,FALSE),"Pend") -> Pend | AS19: =IF(OR(AP19="Yes",AQ19="Yes",AR19="Yes"),"Yes","") -> Yes | AT19: =IF(R19="Delivered","Yes","") -> Yes | AU19: =IF(AND(AS19="Yes",AT19="Yes"),"Yes","") -> Yes | AV19: =IFERROR(VLOOKUP(D19,'Receivable Invoice Detail'!$S$1:$U$3014,3,FALSE),0) -> 0 | AW19: =IF(AU19="Yes",AI19-AV19,0) -> 686.9371
A20: 1 | B20: SO16379 | C20: PO-007657 | D20: INV12494 | E20: Sling-Choker Manufacturing - Timmins | F20: 45665.302 | G20: 45665.377 | H20: 45665 | I20: Taylor Cook | J20: CAD | K20: 1 | L20: 2007.42 | M20: 0 | N20: 1396.3276 | O20: 1776.49 | P20: 230.93 | Q20: 2007.42 | R20: Delivered | T20: =IF(A20="",T19,A20) -> 1 | U20: =IF(F20="",U19,MONTH(F20)) -> 1 | V20: =IF(F20="",V19,YEAR(F20)) -> 2025 | W20: =IF(AC20="Paid",MONTH(AD20),"") -> 2 | X20: =IF(AC20="Paid",YEAR(AD20),"") -> 2025 | Y20: =IF(C20="",Y19,N20/L20) -> 0.6955832 | Z20: =IF(B20="",Z19,B20) -> SO16379 | AA20: =IF(F20="",AA19,F20) -> 45665.302 | AB20: =IF(D20="","No Inv",D20) -> INV12494 | AC20: =IFERROR(VLOOKUP(D20,CAARStatus!$A$2:$AA$1600,22,FALSE),"Not invoiced") -> Paid | AD20: =IF(AC20="Paid",IFERROR(VLOOKUP(D20,CAARStatus!$A$2:$AA$1600,6,FALSE),"Pending"),"Pending") -> 45693 | AE20: =IF(C20="",AE19,C20) -> PO-007657 | AF20: =IF(E20="",AF19,E20) -> Sling-Choker Manufacturing - Timmins | AG20: =IF(J20="",AG19,J20) -> CAD | AH20: =IFERROR(IF(AG20="CAD",O20,O20/K20),0) -> 1776.49 | AI20: =IF(L20-N20=0,VLOOKUP(U20,rate!A$4:B$15,2,FALSE)*AH20,IF(AG20="USD",O20,AH20*Y20)) -> 1235.6966 | AJ20: =IFERROR(AI20/AH20,0) -> 0.6955832 | AK20: =-IF(AG20="CAD",IFERROR(VLOOKUP(D20,CAARStatus!$A$1:$Y$1600,16,FALSE),0),0) -> -1776.49 | AL20: =-IF(AG20="USD",IFERROR(VLOOKUP(D20,CAARStatus!$A$1:$Y$1600,11,FALSE),0),0) -> 0 | AM20: =IF(AG20="CAD",AH20+AK20,"") -> 0 | AN20: =IF(AG20="USD",AI20+AL20,"") | AO20: =IF(AC20="Paid","Yes","Pend") -> Yes | AP20: =IF(AND(AO20="Pend",T20<2),"Pend",IF(T20=1,"Yes","XX")) -> Yes | AQ20: =IFERROR(VLOOKUP(Z20,InvBal!$L$4:$P$600,4,FALSE),"Pend") -> Pend | AR20: =IFERROR(VLOOKUP(D20,Manual!$C$1:$E$22,2,FALSE),"Pend") -> Pend | AS20: =IF(OR(AP20="Yes",AQ20="Yes",AR20="Yes"),"Yes","") -> Yes | AT20: =IF(R20="Delivered","Yes","") -> Yes | AU20: =IF(AND(AS20="Yes",AT20="Yes"),"Yes","") -> Yes | AV20: =IFERROR(VLOOKUP(D20,'Receivable Invoice Detail'!$S$1:$U$3014,3,FALSE),0) -> 0 | AW20: =IF(AU20="Yes",AI20-AV20,0) -> 1235.6966
A21: 3 | B21: SO16380 | C21: L63079-DS | D21: INV12496 | E21: Wild Rows Pump & Compression LTD. | F21: 45665.427 | G21: 45665.651 | H21: 45777 | I21: Taylor Cook | J21: CAD | K21: 1 | L21: 4153.74 | M21: 0 | N21: 2889.2718 | O21: 3955.95 | P21: 197.79 | Q21: 4153.74 | R21: Delivered | T21: =IF(A21="",T20,A21) -> 3 | U21: =IF(F21="",U20,MONTH(F21)) -> 1 | V21: =IF(F21="",V20,YEAR(F21)) -> 2025 | W21: =IF(AC21="Paid",MONTH(AD21),"") -> 1 | X21: =IF(AC21="Paid",YEAR(AD21),"") -> 2025 | Y21: =IF(C21="",Y20,N21/L21) -> 0.6955832 | Z21: =IF(B21="",Z20,B21) -> SO16380 | AA21: =IF(F21="",AA20,F21) -> 45665.427 | AB21: =IF(D21="","No Inv",D21) -> INV12496 | AC21: =IFERROR(VLOOKUP(D21,CAARStatus!$A$2:$AA$1600,22,FALSE),"Not invoiced") -> Paid | AD21: =IF(AC21="Paid",IFERROR(VLOOKUP(D21,CAARStatus!$A$2:$AA$1600,6,FALSE),"Pending"),"Pending") -> 45666 | AE21: =IF(C21="",AE20,C21) -> L63079-DS | AF21: =IF(E21="",AF20,E21) -> Wild Rows Pump & Compression LTD. | AG21: =IF(J21="",AG20,J21) -> CAD | AH21: =IFERROR(IF(AG21="CAD",O21,O21/K21),0) -> 3955.95 | AI21: =IF(L21-N21=0,VLOOKUP(U21,rate!A$4:B$15,2,FALSE)*AH21,IF(AG21="USD",O21,AH21*Y21)) -> 2751.6924 | AJ21: =IFERROR(AI21/AH21,0) -> 0.6955832 | AK21: =-IF(AG21="CAD",IFERROR(VLOOKUP(D21,CAARStatus!$A$1:$Y$1600,16,FALSE),0),0) -> -1827.63 | AL21: =-IF(AG21="USD",IFERROR(VLOOKUP(D21,CAARStatus!$A$1:$Y$1600,11,FALSE),0),0) -> 0 | AM21: =IF(AG21="CAD",AH21+AK21,"") -> 2128.32 | AN21: =IF(AG21="USD",AI21+AL21,"") | AO21: =IF(AC21="Paid","Yes","Pend") -> Yes | AP21: =IF(AND(AO21="Pend",T21<2),"Pend",IF(T21=1,"Yes","XX")) -> XX | AQ21: =IFERROR(VLOOKUP(Z21,InvBal!$L$4:$P$600,4,FALSE),"Pend") -> Yes | AR21: =IFERROR(VLOOKUP(D21,Manual!$C$1:$E$22,2,FALSE),"Pend") -> Pend | AS21: =IF(OR(AP21="Yes",AQ21="Yes",AR21="Yes"),"Yes","") -> Yes | AT21: =IF(R21="Delivered","Yes","") -> Yes | AU21: =IF(AND(AS21="Yes",AT21="Yes"),"Yes","") -> Yes | AV21: =IFERROR(VLOOKUP(D21,'Receivable Invoice Detail'!$S$1:$U$3014,3,FALSE),0) -> 0 | AW21: =IF(AU21="Yes",AI21-AV21,0) -> 2751.6924
D22: INV12584 | T22: =IF(A22="",T21,A22) -> 3 | U22: =IF(F22="",U21,MONTH(F22)) -> 1 | V22: =IF(F22="",V21,YEAR(F22)) -> 2025 | W22: =IF(AC22="Paid",MONTH(AD22),"") -> 1 | X22: =IF(AC22="Paid",YEAR(AD22),"") -> 2025 | Y22: =IF(C22="",Y21,N22/L22) -> 0.6955832 | Z22: =IF(B22="",Z21,B22) -> SO16380 | AA22: =IF(F22="",AA21,F22) -> 45665.427 | AB22: =IF(D22="","No Inv",D22) -> INV12584 | AC22: =IFERROR(VLOOKUP(D22,CAARStatus!$A$2:$AA$1600,22,FALSE),"Not invoiced") -> Paid | AD22: =IF(AC22="Paid",IFERROR(VLOOKUP(D22,CAARStatus!$A$2:$AA$1600,6,FALSE),"Pending"),"Pending") -> 45687 | AE22: =IF(C22="",AE21,C22) -> L63079-DS | AF22: =IF(E22="",AF21,E22) -> Wild Rows Pump & Compression LTD. | AG22: =IF(J22="",AG21,J22) -> CAD | AH22: =IFERROR(IF(AG22="CAD",O22,O22/K22),0) -> 0 | AI22: =IF(L22-N22=0,VLOOKUP(U22,rate!A$4:B$15,2,FALSE)*AH22,IF(AG22="USD",O22,AH22*Y22)) -> 0 | AJ22: =IFERROR(AI22/AH22,0) -> 0 | AK22: =-IF(AG22="CAD",IFERROR(VLOOKUP(D22,CAARStatus!$A$1:$Y$1600,16,FALSE),0),0) -> -857.76 | AL22: =-IF(AG22="USD",IFERROR(VLOOKUP(D22,CAARStatus!$A$1:$Y$1600,11,FALSE),0),0) -> 0 | AM22: =IF(AG22="CAD",AH22+AK22,"") -> -857.76 | AN22: =IF(AG22="USD",AI22+AL22,"") | AO22: =IF(AC22="Paid","Yes","Pend") -> Yes | AP22: =IF(AND(AO22="Pend",T22<2),"Pend",IF(T22=1,"Yes","XX")) -> XX | AQ22: =IFERROR(VLOOKUP(Z22,InvBal!$L$4:$P$600,4,FALSE),"Pend") -> Yes | AR22: =IFERROR(VLOOKUP(D22,Manual!$C$1:$E$22,2,FALSE),"Pend") -> Pend | AS22: =IF(OR(AP22="Yes",AQ22="Yes",AR22="Yes"),"Yes","") -> Yes | AT22: =IF(R22="Delivered","Yes","") | AU22: =IF(AND(AS22="Yes",AT22="Yes"),"Yes","") | AV22: =IFERROR(VLOOKUP(D22,'Receivable Invoice Detail'!$S$1:$U$3014,3,FALSE),0) -> 0 | AW22: =IF(AU22="Yes",AI22-AV22,0) -> 0
D23: INV12953 | T23: =IF(A23="",T22,A23) -> 3 | U23: =IF(F23="",U22,MONTH(F23)) -> 1 | V23: =IF(F23="",V22,YEAR(F23)) -> 2025 | W23: =IF(AC23="Paid",MONTH(AD23),"") -> 5 | X23: =IF(AC23="Paid",YEAR(AD23),"") -> 2025 | Y23: =IF(C23="",Y22,N23/L23) -> 0.6955832 | Z23: =IF(B23="",Z22,B23) -> SO16380 | AA23: =IF(F23="",AA22,F23) -> 45665.427 | AB23: =IF(D23="","No Inv",D23) -> INV12953 | AC23: =IFERROR(VLOOKUP(D23,CAARStatus!$A$2:$AA$1600,22,FALSE),"Not invoiced") -> Paid | AD23: =IF(AC23="Paid",IFERROR(VLOOKUP(D23,CAARStatus!$A$2:$AA$1600,6,FALSE),"Pending"),"Pending") -> 45784 | AE23: =IF(C23="",AE22,C23) -> L63079-DS | AF23: =IF(E23="",AF22,E23) -> Wild Rows Pump & Compression LTD. | AG23: =IF(J23="",AG22,J23) -> CAD | AH23: =IFERROR(IF(AG23="CAD",O23,O23/K23),0) -> 0 | AI23: =IF(L23-N23=0,VLOOKUP(U23,rate!A$4:B$15,2,FALSE)*AH23,IF(AG23="USD",O23,AH23*Y23)) -> 0 | AJ23: =IFERROR(AI23/AH23,0) -> 0 | AK23: =-IF(AG23="CAD",IFERROR(VLOOKUP(D23,CAARStatus!$A$1:$Y$1600,16,FALSE),0),0) -> -1270.56 | AL23: =-IF(AG23="USD",IFERROR(VLOOKUP(D23,CAARStatus!$A$1:$Y$1600,11,FALSE),0),0) -> 0 | AM23: =IF(AG23="CAD",AH23+AK23,"") -> -1270.56 | AN23: =IF(AG23="USD",AI23+AL23,"") | AO23: =IF(AC23="Paid","Yes","Pend") -> Yes | AP23: =IF(AND(AO23="Pend",T23<2),"Pend",IF(T23=1,"Yes","XX")) -> XX | AQ23: =IFERROR(VLOOKUP(Z23,InvBal!$L$4:$P$600,4,FALSE),"Pend") -> Yes | AR23: =IFERROR(VLOOKUP(D23,Manual!$C$1:$E$22,2,FALSE),"Pend") -> Pend | AS23: =IF(OR(AP23="Yes",AQ23="Yes",AR23="Yes"),"Yes","") -> Yes | AT23: =IF(R23="Delivered","Yes","") | AU23: =IF(AND(AS23="Yes",AT23="Yes"),"Yes","") | AV23: =IFERROR(VLOOKUP(D23,'Receivable Invoice Detail'!$S$1:$U$3014,3,FALSE),0) -> 0 | AW23: =IF(AU23="Yes",AI23-AV23,0) -> 0
A24: 1 | B24: SO16381 | C24: 6642 | D24: INV12500 | E24: Hyperflo | F24: 45665.433 | G24: 45665.477 | H24: 45666 | I24: Ian Trottier | J24: CAD | K24: 1 | L24: 962.42 | M24: 0 | N24: 669.44319 | O24: 916.59 | P24: 45.83 | Q24: 962.42 | R24: Delivered | T24: =IF(A24="",T23,A24) -> 1 | U24: =IF(F24="",U23,MONTH(F24)) -> 1 | V24: =IF(F24="",V23,YEAR(F24)) -> 2025 | W24: =IF(AC24="Paid",MONTH(AD24),"") -> 2 | X24: =IF(AC24="Paid",YEAR(AD24),"") -> 2025 | Y24: =IF(C24="",Y23,N24/L24) -> 0.6955832 | Z24: =IF(B24="",Z23,B24) -> SO16381 | AA24: =IF(F24="",AA23,F24) -> 45665.433 | AB24: =IF(D24="","No Inv",D24) -> INV12500 | AC24: =IFERROR(VLOOKUP(D24,CAARStatus!$A$2:$AA$1600,22,FALSE),"Not invoiced") -> Paid | AD24: =IF(AC24="Paid",IFERROR(VLOOKUP(D24,CAARStatus!$A$2:$AA$1600,6,FALSE),"Pending"),"Pending") -> 45709 | AE24: =IF(C24="",AE23,C24) -> 6642 | AF24: =IF(E24="",AF23,E24) -> Hyperflo | AG24: =IF(J24="",AG23,J24) -> CAD | AH24: =IFERROR(IF(AG24="CAD",O24,O24/K24),0) -> 916.59 | AI24: =IF(L24-N24=0,VLOOKUP(U24,rate!A$4:B$15,2,FALSE)*AH24,IF(AG24="USD",O24,AH24*Y24)) -> 637.56461 | AJ24: =IFERROR(AI24/AH24,0) -> 0.6955832 | AK24: =-IF(AG24="CAD",IFERROR(VLOOKUP(D24,CAARStatus!$A$1:$Y$1600,16,FALSE),0),0) -> -916.59 | AL24: =-IF(AG24="USD",IFERROR(VLOOKUP(D24,CAARStatus!$A$1:$Y$1600,11,FALSE),0),0) -> 0 | AM24: =IF(AG24="CAD",AH24+AK24,"") -> 0 | AN24: =IF(AG24="USD",AI24+AL24,"") | AO24: =IF(AC24="Paid","Yes","Pend") -> Yes | AP24: =IF(AND(AO24="Pend",T24<2),"Pend",IF(T24=1,"Yes","XX")) -> Yes | AQ24: =IFERROR(VLOOKUP(Z24,InvBal!$L$4:$P$600,4,FALSE),"Pend") -> Pend | AR24: =IFERROR(VLOOKUP(D24,Manual!$C$1:$E$22,2,FALSE),"Pend") -> Pend | AS24: =IF(OR(AP24="Yes",AQ24="Yes",AR24="Yes"),"Yes","") -> Yes | AT24: =IF(R24="Delivered","Yes","") -> Yes | AU24: =IF(AND(AS24="Yes",AT24="Yes"),"Yes","") -> Yes | AV24: =IFERROR(VLOOKUP(D24,'Receivable Invoice Detail'!$S$1:$U$3014,3,FALSE),0) -> 0 | AW24: =IF(AU24="Yes",AI24-AV24,0) -> 637.56461
A25: 1 | B25: SO16382 | C25: 071736 | D25: INV12495 | E25: Hoffman-Kane Distributors, Inc. | F25: 45665.456 | G25: 45665.459 | H25: 45666 | I25: Ian Trottier | J25: USD | K25: 0.69714261 | L25: 197.62097 | M25: 0 | N25: 137.77 | O25: 137.77 | Q25: 137.77 | R25: Delivered | T25: =IF(A25="",T24,A25) -> 1 | U25: =IF(F25="",U24,MONTH(F25)) -> 1 | V25: =IF(F25="",V24,YEAR(F25)) -> 2025 | W25: =IF(AC25="Paid",MONTH(AD25),"") -> 2 | X25: =IF(AC25="Paid",YEAR(AD25),"") -> 2025 | Y25: =IF(C25="",Y24,N25/L25) -> 0.69714261 | Z25: =IF(B25="",Z24,B25) -> SO16382 | AA25: =IF(F25="",AA24,F25) -> 45665.456 | AB25: =IF(D25="","No Inv",D25) -> INV12495 | AC25: =IFERROR(VLOOKUP(D25,CAARStatus!$A$2:$AA$1600,22,FALSE),"Not invoiced") -> Paid | AD25: =IF(AC25="Paid",IFERROR(VLOOKUP(D25,CAARStatus!$A$2:$AA$1600,6,FALSE),"Pending"),"Pending") -> 45715 | AE25: =IF(C25="",AE24,C25) -> 071736 | AF25: =IF(E25="",AF24,E25) -> Hoffman-Kane Distributors, Inc. | AG25: =IF(J25="",AG24,J25) -> USD | AH25: =IFERROR(IF(AG25="CAD",O25,O25/K25),0) -> 197.62097 | AI25: =IF(L25-N25=0,VLOOKUP(U25,rate!A$4:B$15,2,FALSE)*AH25,IF(AG25="USD",O25,AH25*Y25)) -> 137.77 | AJ25: =IFERROR(AI25/AH25,0) -> 0.69714261 | AK25: =-IF(AG25="CAD",IFERROR(VLOOKUP(D25,CAARStatus!$A$1:$Y$1600,16,FALSE),0),0) -> 0 | AL25: =-IF(AG25="USD",IFERROR(VLOOKUP(D25,CAARStatus!$A$1:$Y$1600,11,FALSE),0),0) -> -137.77 | AM25: =IF(AG25="CAD",AH25+AK25,"") | AN25: =IF(AG25="USD",AI25+AL25,"") -> 0 | AO25: =IF(AC25="Paid","Yes","Pend") -> Yes | AP25: =IF(AND(AO25="Pend",T25<2),"Pend",IF(T25=1,"Yes","XX")) -> Yes | AQ25: =IFERROR(VLOOKUP(Z25,InvBal!$L$4:$P$600,4,FALSE),"Pend") -> Pend | AR25: =IFERROR(VLOOKUP(D25,Manual!$C$1:$E$22,2,FALSE),"Pend") -> Pend | AS25: =IF(OR(AP25="Yes",AQ25="Yes",AR25="Yes"),"Yes","") -> Yes | AT25: =IF(R25="Delivered","Yes","") -> Yes | AU25: =IF(AND(AS25="Yes",AT25="Yes"),"Yes","") -> Yes | AV25: =IFERROR(VLOOKUP(D25,'Receivable Invoice Detail'!$S$1:$U$3014,3,FALSE),0) -> 0 | AW25: =IF(AU25="Yes",AI25-AV25,0) -> 137.77
A26: 1 | B26: SO16383 | C26: 4501080579 | D26: INV12761 | E26: Barrick Gold - Pueblo Viejo Dominicana Corporation | F26: 45665.47 | G26: 45666.818 | H26: 45665 | I26: Jeff Bell | J26: USD | K26: 0.6955832 | L26: 15727.809 | M26: 0 | N26: 10940 | O26: 10940 | Q26: 10940 | R26: Delivered | T26: =IF(A26="",T25,A26) -> 1 | U26: =IF(F26="",U25,MONTH(F26)) -> 1 | V26: =IF(F26="",V25,YEAR(F26)) -> 2025 | W26: =IF(AC26="Paid",MONTH(AD26),"") -> 5 | X26: =IF(AC26="Paid",YEAR(AD26),"") -> 2025 | Y26: =IF(C26="",Y25,N26/L26) -> 0.6955832 | Z26: =IF(B26="",Z25,B26) -> SO16383 | AA26: =IF(F26="",AA25,F26) -> 45665.47 | AB26: =IF(D26="","No Inv",D26) -> INV12761 | AC26: =IFERROR(VLOOKUP(D26,CAARStatus!$A$2:$AA$1600,22,FALSE),"Not invoiced") -> Paid | AD26: =IF(AC26="Paid",IFERROR(VLOOKUP(D26,CAARStatus!$A$2:$AA$1600,6,FALSE),"Pending"),"Pending") -> 45786 | AE26: =IF(C26="",AE25,C26) -> 4501080579 | AF26: =IF(E26="",AF25,E26) -> Barrick Gold - Pueblo Viejo Dominicana Corporation | AG26: =IF(J26="",AG25,J26) -> USD | AH26: =IFERROR(IF(AG26="CAD",O26,O26/K26),0) -> 15727.809 | AI26: =IF(L26-N26=0,VLOOKUP(U26,rate!A$4:B$15,2,FALSE)*AH26,IF(AG26="USD",O26,AH26*Y26)) -> 10940 | AJ26: =IFERROR(AI26/AH26,0) -> 0.6955832 | AK26: =-IF(AG26="CAD",IFERROR(VLOOKUP(D26,CAARStatus!$A$1:$Y$1600,16,FALSE),0),0) -> 0 | AL26: =-IF(AG26="USD",IFERROR(VLOOKUP(D26,CAARStatus!$A$1:$Y$1600,11,FALSE),0),0) -> -10940 | AM26: =IF(AG26="CAD",AH26+AK26,"") | AN26: =IF(AG26="USD",AI26+AL26,"") -> 0 | AO26: =IF(AC26="Paid","Yes","Pend") -> Yes | AP26: =IF(AND(AO26="Pend",T26<2),"Pend",IF(T26=1,"Yes","XX")) -> Yes | AQ26: =IFERROR(VLOOKUP(Z26,InvBal!$L$4:$P$600,4,FALSE),"Pend") -> Pend | AR26: =IFERROR(VLOOKUP(D26,Manual!$C$1:$E$22,2,FALSE),"Pend") -> Pend | AS26: =IF(OR(AP26="Yes",AQ26="Yes",AR26="Yes"),"Yes","") -> Yes | AT26: =IF(R26="Delivered","Yes","") -> Yes | AU26: =IF(AND(AS26="Yes",AT26="Yes"),"Yes","") -> Yes | AV26: =IFERROR(VLOOKUP(D26,'Receivable Invoice Detail'!$S$1:$U$3014,3,FALSE),0) -> 0 | AW26: =IF(AU26="Yes",AI26-AV26,0) -> 10940
A27: 1 | B27: SO16384 | C27: 2968 | D27: INV13051 | E27: Les Pompes du St-Laurent Inc. | F27: 45665.494 | G27: 45665.681 | H27: 45791 | I27: Ian Trottier | J27: CAD | K27: 1 | L27: 2094.52 | M27: 0 | N27: 1456.9129 | O27: 1994.78 | P27: 99.74 | Q27: 2094.52 | R27: Delivered | T27: =IF(A27="",T26,A27) -> 1 | U27: =IF(F27="",U26,MONTH(F27)) -> 1 | V27: =IF(F27="",V26,YEAR(F27)) -> 2025 | W27: =IF(AC27="Paid",MONTH(AD27),"") -> 7 | X27: =IF(AC27="Paid",YEAR(AD27),"") -> 2025 | Y27: =IF(C27="",Y26,N27/L27) -> 0.6955832 | Z27: =IF(B27="",Z26,B27) -> SO16384 | AA27: =IF(F27="",AA26,F27) -> 45665.494 | AB27: =IF(D27="","No Inv",D27) -> INV13051 | AC27: =IFERROR(VLOOKUP(D27,CAARStatus!$A$2:$AA$1600,22,FALSE),"Not invoiced") -> Paid | AD27: =IF(AC27="Paid",IFERROR(VLOOKUP(D27,CAARStatus!$A$2:$AA$1600,6,FALSE),"Pending"),"Pending") -> 45848 | AE27: =IF(C27="",AE26,C27) -> 2968 | AF27: =IF(E27="",AF26,E27) -> Les Pompes du St-Laurent Inc. | AG27: =IF(J27="",AG26,J27) -> CAD | AH27: =IFERROR(IF(AG27="CAD",O27,O27/K27),0) -> 1994.78 | AI27: =IF(L27-N27=0,VLOOKUP(U27,rate!A$4:B$15,2,FALSE)*AH27,IF(AG27="USD",O27,AH27*Y27)) -> 1387.5355 | AJ27: =IFERROR(AI27/AH27,0) -> 0.6955832 | AK27: =-IF(AG27="CAD",IFERROR(VLOOKUP(D27,CAARStatus!$A$1:$Y$1600,16,FALSE),0),0) -> -1994.78 | AL27: =-IF(AG27="USD",IFERROR(VLOOKUP(D27,CAARStatus!$A$1:$Y$1600,11,FALSE),0),0) -> 0 | AM27: =IF(AG27="CAD",AH27+AK27,"") -> 0 | AN27: =IF(AG27="USD",AI27+AL27,"") | AO27: =IF(AC27="Paid","Yes","Pend") -> Yes | AP27: =IF(AND(AO27="Pend",T27<2),"Pend",IF(T27=1,"Yes","XX")) -> Yes | AQ27: =IFERROR(VLOOKUP(Z27,InvBal!$L$4:$P$600,4,FALSE),"Pend") -> Pend | AR27: =IFERROR(VLOOKUP(D27,Manual!$C$1:$E$22,2,FALSE),"Pend") -> Pend | AS27: =IF(OR(AP27="Yes",AQ27="Yes",AR27="Yes"),"Yes","") -> Yes | AT27: =IF(R27="Delivered","Yes","") -> Yes | AU27: =IF(AND(AS27="Yes",AT27="Yes"),"Yes","") -> Yes | AV27: =IFERROR(VLOOKUP(D27,'Receivable Invoice Detail'!$S$1:$U$3014,3,FALSE),0) -> 0 | AW27: =IF(AU27="Yes",AI27-AV27,0) -> 1387.5355
A28: 1 | B28: SO16385 | C28: 11627 | D28: INV12579 | E28: Les Pompes Diaspec Inc. | F28: 45665.501 | G28: 45686.418 | H28: 45687 | I28: Ian Trottier | J28: CAD | K28: 1 | L28: 12217.92 | M28: 12217.92 | N28: 12217.92 | O28: 11636.11 | P28: 581.81 | Q28: 12217.92 | R28: Delivered | T28: =IF(A28="",T27,A28) -> 1 | U28: =IF(F28="",U27,MONTH(F28)) -> 1 | V28: =IF(F28="",V27,YEAR(F28)) -> 2025 | W28: =IF(AC28="Paid",MONTH(AD28),"") -> 2 | X28: =IF(AC28="Paid",YEAR(AD28),"") -> 2025 | Y28: =IF(C28="",Y27,N28/L28) -> 1 | Z28: =IF(B28="",Z27,B28) -> SO16385 | AA28: =IF(F28="",AA27,F28) -> 45665.501 | AB28: =IF(D28="","No Inv",D28) -> INV12579 | AC28: =IFERROR(VLOOKUP(D28,CAARStatus!$A$2:$AA$1600,22,FALSE),"Not invoiced") -> Paid | AD28: =IF(AC28="Paid",IFERROR(VLOOKUP(D28,CAARStatus!$A$2:$AA$1600,6,FALSE),"Pending"),"Pending") -> 45714 | AE28: =IF(C28="",AE27,C28) -> 11627 | AF28: =IF(E28="",AF27,E28) -> Les Pompes Diaspec Inc. | AG28: =IF(J28="",AG27,J28) -> CAD | AH28: =IFERROR(IF(AG28="CAD",O28,O28/K28),0) -> 11636.11 | AI28: =IF(L28-N28=0,VLOOKUP(U28,rate!A$4:B$15,2,FALSE)*AH28,IF(AG28="USD",O28,AH28*Y28)) -> 8083.3509 | AJ28: =IFERROR(AI28/AH28,0) -> 0.69467811 | AK28: =-IF(AG28="CAD",IFERROR(VLOOKUP(D28,CAARStatus!$A$1:$Y$1600,16,FALSE),0),0) -> -11636.11 | AL28: =-IF(AG28="USD",IFERROR(VLOOKUP(D28,CAARStatus!$A$1:$Y$1600,11,FALSE),0),0) -> 0 | AM28: =IF(AG28="CAD",AH28+AK28,"") -> 0 | AN28: =IF(AG28="USD",AI28+AL28,"") | AO28: =IF(AC28="Paid","Yes","Pend") -> Yes | AP28: =IF(AND(AO28="Pend",T28<2),"Pend",IF(T28=1,"Yes","XX")) -> Yes | AQ28: =IFERROR(VLOOKUP(Z28,InvBal!$L$4:$P$600,4,FALSE),"Pend") -> Pend | AR28: =IFERROR(VLOOKUP(D28,Manual!$C$1:$E$22,2,FALSE),"Pend") -> Pend | AS28: =IF(OR(AP28="Yes",AQ28="Yes",AR28="Yes"),"Yes","") -> Yes | AT28: =IF(R28="Delivered","Yes","") -> Yes | AU28: =IF(AND(AS28="Yes",AT28="Yes"),"Yes","") -> Yes | AV28: =IFERROR(VLOOKUP(D28,'Receivable Invoice Detail'!$S$1:$U$3014,3,FALSE),0) -> 0 | AW28: =IF(AU28="Yes",AI28-AV28,0) -> 8083.3509
A29: 1 | B29: SO16389 | C29: 6645 | D29: INV12501 | E29: Hyperflo | F29: 45665.569 | G29: 45665.636 | H29: 45666 | I29: Taylor Cook | J29: CAD | K29: 1 | L29: 224.6 | M29: 0 | N29: 156.22799 | O29: 213.9 | P29: 10.7 | Q29: 224.6 | R29: Delivered | T29: =IF(A29="",T28,A29) -> 1 | U29: =IF(F29="",U28,MONTH(F29)) -> 1 | V29: =IF(F29="",V28,YEAR(F29)) -> 2025 | W29: =IF(AC29="Paid",MONTH(AD29),"") -> 2 | X29: =IF(AC29="Paid",YEAR(AD29),"") -> 2025 | Y29: =IF(C29="",Y28,N29/L29) -> 0.6955832 | Z29: =IF(B29="",Z28,B29) -> SO16389 | AA29: =IF(F29="",AA28,F29) -> 45665.569 | AB29: =IF(D29="","No Inv",D29) -> INV12501 | AC29: =IFERROR(VLOOKUP(D29,CAARStatus!$A$2:$AA$1600,22,FALSE),"Not invoiced") -> Paid | AD29: =IF(AC29="Paid",IFERROR(VLOOKUP(D29,CAARStatus!$A$2:$AA$1600,6,FALSE),"Pending"),"Pending") -> 45709 | AE29: =IF(C29="",AE28,C29) -> 6645 | AF29: =IF(E29="",AF28,E29) -> Hyperflo | AG29: =IF(J29="",AG28,J29) -> CAD | AH29: =IFERROR(IF(AG29="CAD",O29,O29/K29),0) -> 213.9 | AI29: =IF(L29-N29=0,VLOOKUP(U29,rate!A$4:B$15,2,FALSE)*AH29,IF(AG29="USD",O29,AH29*Y29)) -> 148.78525 | AJ29: =IFERROR(AI29/AH29,0) -> 0.6955832 | AK29: =-IF(AG29="CAD",IFERROR(VLOOKUP(D29,CAARStatus!$A$1:$Y$1600,16,FALSE),0),0) -> -213.9 | AL29: =-IF(AG29="USD",IFERROR(VLOOKUP(D29,CAARStatus!$A$1:$Y$1600,11,FALSE),0),0) -> 0 | AM29: =IF(AG29="CAD",AH29+AK29,"") -> 0 | AN29: =IF(AG29="USD",AI29+AL29,"") | AO29: =IF(AC29="Paid","Yes","Pend") -> Yes | AP29: =IF(AND(AO29="Pend",T29<2),"Pend",IF(T29=1,"Yes","XX")) -> Yes | AQ29: =IFERROR(VLOOKUP(Z29,InvBal!$L$4:$P$600,4,FALSE),"Pend") -> Pend | AR29: =IFERROR(VLOOKUP(D29,Manual!$C$1:$E$22,2,FALSE),"Pend") -> Pend | AS29: =IF(OR(AP29="Yes",AQ29="Yes",AR29="Yes"),"Yes","") -> Yes | AT29: =IF(R29="Delivered","Yes","") -> Yes | AU29: =IF(AND(AS29="Yes",AT29="Yes"),"Yes","") -> Yes | AV29: =IFERROR(VLOOKUP(D29,'Receivable Invoice Detail'!$S$1:$U$3014,3,FALSE),0) -> 0 | AW29: =IF(AU29="Yes",AI29-AV29,0) -> 148.78525
A30: 2 | B30: SO16390 | C30: 2969 | D30: INV12631 | E30: Les Pompes du St-Laurent Inc. | F30: 45665.671 | G30: 45665.674 | H30: 45688 | I30: Ian Trottier | J30: CAD | K30: 1 | L30: 972.43 | M30: 0 | N30: 676.40597 | O30: 926.12 | P30: 46.31 | Q30: 972.43 | R30: Delivered | T30: =IF(A30="",T29,A30) -> 2 | U30: =IF(F30="",U29,MONTH(F30)) -> 1 | V30: =IF(F30="",V29,YEAR(F30)) -> 2025 | W30: =IF(AC30="Paid",MONTH(AD30),"") -> 4 | X30: =IF(AC30="Paid",YEAR(AD30),"") -> 2025 | Y30: =IF(C30="",Y29,N30/L30) -> 0.6955832 | Z30: =IF(B30="",Z29,B30) -> SO16390 | AA30: =IF(F30="",AA29,F30) -> 45665.671 | AB30: =IF(D30="","No Inv",D30) -> INV12631 | AC30: =IFERROR(VLOOKUP(D30,CAARStatus!$A$2:$AA$1600,22,FALSE),"Not invoiced") -> Paid | AD30: =IF(AC30="Paid",IFERROR(VLOOKUP(D30,CAARStatus!$A$2:$AA$1600,6,FALSE),"Pending"),"Pending") -> 45750 | AE30: =IF(C30="",AE29,C30) -> 2969 | AF30: =IF(E30="",AF29,E30) -> Les Pompes du St-Laurent Inc. | AG30: =IF(J30="",AG29,J30) -> CAD | AH30: =IFERROR(IF(AG30="CAD",O30,O30/K30),0) -> 926.12 | AI30: =IF(L30-N30=0,VLOOKUP(U30,rate!A$4:B$15,2,FALSE)*AH30,IF(AG30="USD",O30,AH30*Y30)) -> 644.19352 | AJ30: =IFERROR(AI30/AH30,0) -> 0.6955832 | AK30: =-IF(AG30="CAD",IFERROR(VLOOKUP(D30,CAARStatus!$A$1:$Y$1600,16,FALSE),0),0) -> -463.06 | AL30: =-IF(AG30="USD",IFERROR(VLOOKUP(D30,CAARStatus!$A$1:$Y$1600,11,FALSE),0),0) -> 0 | AM30: =IF(AG30="CAD",AH30+AK30,"") -> 463.06 | AN30: =IF(AG30="USD",AI30+AL30,"") | AO30: =IF(AC30="Paid","Yes","Pend") -> Yes | AP30: =IF(AND(AO30="Pend",T30<2),"Pend",IF(T30=1,"Yes","XX")) -> XX | AQ30: =IFERROR(VLOOKUP(Z30,InvBal!$L$4:$P$600,4,FALSE),"Pend") -> Yes | AR30: =IFERROR(VLOOKUP(D30,Manual!$C$1:$E$22,2,FALSE),"Pend") -> Pend | AS30: =IF(OR(AP30="Yes",AQ30="Yes",AR30="Yes"),"Yes","") -> Yes | AT30: =IF(R30="Delivered","Yes","") -> Yes | AU30: =IF(AND(AS30="Yes",AT30="Yes"),"Yes","") -> Yes | AV30: =IFERROR(VLOOKUP(D30,'Receivable Invoice Detail'!$S$1:$U$3014,3,FALSE),0) -> 0 | AW30: =IF(AU30="Yes",AI30-AV30,0) -> 644.19352
D31: INV12506 | T31: =IF(A31="",T30,A31) -> 2 | U31: =IF(F31="",U30,MONTH(F31)) -> 1 | V31: =IF(F31="",V30,YEAR(F31)) -> 2025 | W31: =IF(AC31="Paid",MONTH(AD31),"") -> 2 | X31: =IF(AC31="Paid",YEAR(AD31),"") -> 2025 | Y31: =IF(C31="",Y30,N31/L31) -> 0.6955832 | Z31: =IF(B31="",Z30,B31) -> SO16390 | AA31: =IF(F31="",AA30,F31) -> 45665.671 | AB31: =IF(D31="","No Inv",D31) -> INV12506 | AC31: =IFERROR(VLOOKUP(D31,CAARStatus!$A$2:$AA$1600,22,FALSE),"Not invoiced") -> Paid | AD31: =IF(AC31="Paid",IFERROR(VLOOKUP(D31,CAARStatus!$A$2:$AA$1600,6,FALSE),"Pending"),"Pending") -> 45706 | AE31: =IF(C31="",AE30,C31) -> 2969 | AF31: =IF(E31="",AF30,E31) -> Les Pompes du St-Laurent Inc. | AG31: =IF(J31="",AG30,J31) -> CAD | AH31: =IFERROR(IF(AG31="CAD",O31,O31/K31),0) -> 0 | AI31: =IF(L31-N31=0,VLOOKUP(U31,rate!A$4:B$15,2,FALSE)*AH31,IF(AG31="USD",O31,AH31*Y31)) -> 0 | AJ31: =IFERROR(AI31/AH31,0) -> 0 | AK31: =-IF(AG31="CAD",IFERROR(VLOOKUP(D31,CAARStatus!$A$1:$Y$1600,16,FALSE),0),0) -> -463.06 | AL31: =-IF(AG31="USD",IFERROR(VLOOKUP(D31,CAARStatus!$A$1:$Y$1600,11,FALSE),0),0) -> 0 | AM31: =IF(AG31="CAD",AH31+AK31,"") -> -463.06 | AN31: =IF(AG31="USD",AI31+AL31,"") | AO31: =IF(AC31="Paid","Yes","Pend") -> Yes | AP31: =IF(AND(AO31="Pend",T31<2),"Pend",IF(T31=1,"Yes","XX")) -> XX | AQ31: =IFERROR(VLOOKUP(Z31,InvBal!$L$4:$P$600,4,FALSE),"Pend") -> Yes | AR31: =IFERROR(VLOOKUP(D31,Manual!$C$1:$E$22,2,FALSE),"Pend") -> Pend | AS31: =IF(OR(AP31="Yes",AQ31="Yes",AR31="Yes"),"Yes","") -> Yes | AT31: =IF(R31="Delivered","Yes","") | AU31: =IF(AND(AS31="Yes",AT31="Yes"),"Yes","") | AV31: =IFERROR(VLOOKUP(D31,'Receivable Invoice Detail'!$S$1:$U$3014,3,FALSE),0) -> 0 | AW31: =IF(AU31="Yes",AI31-AV31,0) -> 0
A32: 1 | B32: SO16392 | C32: 4500574897 | D32: INV12706 | E32: Resolute Forest Products - Kenogami | F32: 45666.438 | G32: 45671.64 | H32: 45744 | I32: Ian Trottier | J32: CAD | K32: 1 | L32: 7778.54 | M32: 0 | N32: 5412.4629 | O32: 7408.13 | P32: 370.41 | Q32: 7778.54 | R32: Delivered | T32: =IF(A32="",T31,A32) -> 1 | U32: =IF(F32="",U31,MONTH(F32)) -> 1 | V32: =IF(F32="",V31,YEAR(F32)) -> 2025 | W32: =IF(AC32="Paid",MONTH(AD32),"") -> 5 | X32: =IF(AC32="Paid",YEAR(AD32),"") -> 2025 | Y32: =IF(C32="",Y31,N32/L32) -> 0.6958199 | Z32: =IF(B32="",Z31,B32) -> SO16392 | AA32: =IF(F32="",AA31,F32) -> 45666.438 | AB32: =IF(D32="","No Inv",D32) -> INV12706 | AC32: =IFERROR(VLOOKUP(D32,CAARStatus!$A$2:$AA$1600,22,FALSE),"Not invoiced") -> Paid | AD32: =IF(AC32="Paid",IFERROR(VLOOKUP(D32,CAARStatus!$A$2:$AA$1600,6,FALSE),"Pending"),"Pending") -> 45779 | AE32: =IF(C32="",AE31,C32) -> 4500574897 | AF32: =IF(E32="",AF31,E32) -> Resolute Forest Products - Kenogami | AG32: =IF(J32="",AG31,J32) -> CAD | AH32: =IFERROR(IF(AG32="CAD",O32,O32/K32),0) -> 7408.13 | AI32: =IF(L32-N32=0,VLOOKUP(U32,rate!A$4:B$15,2,FALSE)*AH32,IF(AG32="USD",O32,AH32*Y32)) -> 5154.7243 | AJ32: =IFERROR(AI32/AH32,0) -> 0.6958199 | AK32: =-IF(AG32="CAD",IFERROR(VLOOKUP(D32,CAARStatus!$A$1:$Y$1600,16,FALSE),0),0) -> -7408.13 | AL32: =-IF(AG32="USD",IFERROR(VLOOKUP(D32,CAARStatus!$A$1:$Y$1600,11,FALSE),0),0) -> 0 | AM32: =IF(AG32="CAD",AH32+AK32,"") -> 0 | AN32: =IF(AG32="USD",AI32+AL32,"") | AO32: =IF(AC32="Paid","Yes","Pend") -> Yes | AP32: =IF(AND(AO32="Pend",T32<2),"Pend",IF(T32=1,"Yes","XX")) -> Yes | AQ32: =IFERROR(VLOOKUP(Z32,InvBal!$L$4:$P$600,4,FALSE),"Pend") -> Pend | AR32: =IFERROR(VLOOKUP(D32,Manual!$C$1:$E$22,2,FALSE),"Pend") -> Pend | AS32: =IF(OR(AP32="Yes",AQ32="Yes",AR32="Yes"),"Yes","") -> Yes | AT32: =IF(R32="Delivered","Yes","") -> Yes | AU32: =IF(AND(AS32="Yes",AT32="Yes"),"Yes","") -> Yes | AV32: =IFERROR(VLOOKUP(D32,'Receivable Invoice Detail'!$S$1:$U$3014,3,FALSE),0) -> 0 | AW32: =IF(AU32="Yes",AI32-AV32,0) -> 5154.7243
A33: 2 | B33: SO16393 | C33: 2051 | D33: INV12704 | E33: FMI Products | F33: 45666.497 | G33: 45671.44 | H33: 45706 | I33: Ian Trottier | J33: CAD | K33: 1 | L33: 2482.17 | M33: 0 | N33: 1727.1433 | O33: 2363.97 | P33: 118.2 | Q33: 2482.17 | R33: Delivered | T33: =IF(A33="",T32,A33) -> 2 | U33: =IF(F33="",U32,MONTH(F33)) -> 1 | V33: =IF(F33="",V32,YEAR(F33)) -> 2025 | W33: =IF(AC33="Paid",MONTH(AD33),"") -> 4 | X33: =IF(AC33="Paid",YEAR(AD33),"") -> 2025 | Y33: =IF(C33="",Y32,N33/L33) -> 0.6958199 | Z33: =IF(B33="",Z32,B33) -> SO16393 | AA33: =IF(F33="",AA32,F33) -> 45666.497 | AB33: =IF(D33="","No Inv",D33) -> INV12704 | AC33: =IFERROR(VLOOKUP(D33,CAARStatus!$A$2:$AA$1600,22,FALSE),"Not invoiced") -> Paid | AD33: =IF(AC33="Paid",IFERROR(VLOOKUP(D33,CAARStatus!$A$2:$AA$1600,6,FALSE),"Pending"),"Pending") -> 45750 | AE33: =IF(C33="",AE32,C33) -> 2051 | AF33: =IF(E33="",AF32,E33) -> FMI Products | AG33: =IF(J33="",AG32,J33) -> CAD | AH33: =IFERROR(IF(AG33="CAD",O33,O33/K33),0) -> 2363.97 | AI33: =IF(L33-N33=0,VLOOKUP(U33,rate!A$4:B$15,2,FALSE)*AH33,IF(AG33="USD",O33,AH33*Y33)) -> 1644.8974 | AJ33: =IFERROR(AI33/AH33,0) -> 0.6958199 | AK33: =-IF(AG33="CAD",IFERROR(VLOOKUP(D33,CAARStatus!$A$1:$Y$1600,16,FALSE),0),0) -> -1662.14 | AL33: =-IF(AG33="USD",IFERROR(VLOOKUP(D33,CAARStatus!$A$1:$Y$1600,11,FALSE),0),0) -> 0 | AM33: =IF(AG33="CAD",AH33+AK33,"") -> 701.83 | AN33: =IF(AG33="USD",AI33+AL33,"") | AO33: =IF(AC33="Paid","Yes","Pend") -> Yes | AP33: =IF(AND(AO33="Pend",T33<2),"Pend",IF(T33=1,"Yes","XX")) -> XX | AQ33: =IFERROR(VLOOKUP(Z33,InvBal!$L$4:$P$600,4,FALSE),"Pend") -> Yes | AR33: =IFERROR(VLOOKUP(D33,Manual!$C$1:$E$22,2,FALSE),"Pend") -> Pend | AS33: =IF(OR(AP33="Yes",AQ33="Yes",AR33="Yes"),"Yes","") -> Yes | AT33: =IF(R33="Delivered","Yes","") -> Yes | AU33: =IF(AND(AS33="Yes",AT33="Yes"),"Yes","") -> Yes | AV33: =IFERROR(VLOOKUP(D33,'Receivable Invoice Detail'!$S$1:$U$3014,3,FALSE),0) -> 0 | AW33: =IF(AU33="Yes",AI33-AV33,0) -> 1644.8974
D34: INV12541 | T34: =IF(A34="",T33,A34) -> 2 | U34: =IF(F34="",U33,MONTH(F34)) -> 1 | V34: =IF(F34="",V33,YEAR(F34)) -> 2025 | W34: =IF(AC34="Paid",MONTH(AD34),"") -> 2 | X34: =IF(AC34="Paid",YEAR(AD34),"") -> 2025 | Y34: =IF(C34="",Y33,N34/L34) -> 0.6958199 | Z34: =IF(B34="",Z33,B34) -> SO16393 | AA34: =IF(F34="",AA33,F34) -> 45666.497 | AB34: =IF(D34="","No Inv",D34) -> INV12541 | AC34: =IFERROR(VLOOKUP(D34,CAARStatus!$A$2:$AA$1600,22,FALSE),"Not invoiced") -> Paid | AD34: =IF(AC34="Paid",IFERROR(VLOOKUP(D34,CAARStatus!$A$2:$AA$1600,6,FALSE),"Pending"),"Pending") -> 45709 | AE34: =IF(C34="",AE33,C34) -> 2051 | AF34: =IF(E34="",AF33,E34) -> FMI Products | AG34: =IF(J34="",AG33,J34) -> CAD | AH34: =IFERROR(IF(AG34="CAD",O34,O34/K34),0) -> 0 | AI34: =IF(L34-N34=0,VLOOKUP(U34,rate!A$4:B$15,2,FALSE)*AH34,IF(AG34="USD",O34,AH34*Y34)) -> 0 | AJ34: =IFERROR(AI34/AH34,0) -> 0 | AK34: =-IF(AG34="CAD",IFERROR(VLOOKUP(D34,CAARStatus!$A$1:$Y$1600,16,FALSE),0),0) -> -701.83 | AL34: =-IF(AG34="USD",IFERROR(VLOOKUP(D34,CAARStatus!$A$1:$Y$1600,11,FALSE),0),0) -> 0 | AM34: =IF(AG34="CAD",AH34+AK34,"") -> -701.83 | AN34: =IF(AG34="USD",AI34+AL34,"") | AO34: =IF(AC34="Paid","Yes","Pend") -> Yes | AP34: =IF(AND(AO34="Pend",T34<2),"Pend",IF(T34=1,"Yes","XX")) -> XX | AQ34: =IFERROR(VLOOKUP(Z34,InvBal!$L$4:$P$600,4,FALSE),"Pend") -> Yes | AR34: =IFERROR(VLOOKUP(D34,Manual!$C$1:$E$22,2,FALSE),"Pend") -> Pend | AS34: =IF(OR(AP34="Yes",AQ34="Yes",AR34="Yes"),"Yes","") -> Yes | AT34: =IF(R34="Delivered","Yes","") | AU34: =IF(AND(AS34="Yes",AT34="Yes"),"Yes","") | AV34: =IFERROR(VLOOKUP(D34,'Receivable Invoice Detail'!$S$1:$U$3014,3,FALSE),0) -> 0 | AW34: =IF(AU34="Yes",AI34-AV34,0) -> 0
A35: 1 | B35: SO16397 | C35: 5345945 | D35: INV12846 | E35: Corrosion Fluid Products Corp. | F35: 45666.711 | G35: 45719.694 | H35: 45733 | I35: Ian Trottier | J35: USD | K35: 0.69136666 | L35: 1339.7088 | M35: 0 | N35: 926.23 | O35: 926.23 | Q35: 926.23 | R35: Delivered | T35: =IF(A35="",T34,A35) -> 1 | U35: =IF(F35="",U34,MONTH(F35)) -> 1 | V35: =IF(F35="",V34,YEAR(F35)) -> 2025 | W35: =IF(AC35="Paid",MONTH(AD35),"") -> 5 | X35: =IF(AC35="Paid",YEAR(AD35),"") -> 2025 | Y35: =IF(C35="",Y34,N35/L35) -> 0.69136666 | Z35: =IF(B35="",Z34,B35) -> SO16397 | AA35: =IF(F35="",AA34,F35) -> 45666.711 | AB35: =IF(D35="","No Inv",D35) -> INV12846 | AC35: =IFERROR(VLOOKUP(D35,CAARStatus!$A$2:$AA$1600,22,FALSE),"Not invoiced") -> Paid | AD35: =IF(AC35="Paid",IFERROR(VLOOKUP(D35,CAARStatus!$A$2:$AA$1600,6,FALSE),"Pending"),"Pending") -> 45792 | AE35: =IF(C35="",AE34,C35) -> 5345945 | AF35: =IF(E35="",AF34,E35) -> Corrosion Fluid Products Corp. | AG35: =IF(J35="",AG34,J35) -> USD | AH35: =IFERROR(IF(AG35="CAD",O35,O35/K35),0) -> 1339.7088 | AI35: =IF(L35-N35=0,VLOOKUP(U35,rate!A$4:B$15,2,FALSE)*AH35,IF(AG35="USD",O35,AH35*Y35)) -> 926.23 | AJ35: =IFERROR(AI35/AH35,0) -> 0.69136666 | AK35: =-IF(AG35="CAD",IFERROR(VLOOKUP(D35,CAARStatus!$A$1:$Y$1600,16,FALSE),0),0) -> 0 | AL35: =-IF(AG35="USD",IFERROR(VLOOKUP(D35,CAARStatus!$A$1:$Y$1600,11,FALSE),0),0) -> -926.23 | AM35: =IF(AG35="CAD",AH35+AK35,"") | AN35: =IF(AG35="USD",AI35+AL35,"") -> 0 | AO35: =IF(AC35="Paid","Yes","Pend") -> Yes | AP35: =IF(AND(AO35="Pend",T35<2),"Pend",IF(T35=1,"Yes","XX")) -> Yes | AQ35: =IFERROR(VLOOKUP(Z35,InvBal!$L$4:$P$600,4,FALSE),"Pend") -> Pend | AR35: =IFERROR(VLOOKUP(D35,Manual!$C$1:$E$22,2,FALSE),"Pend") -> Pend | AS35: =IF(OR(AP35="Yes",AQ35="Yes",AR35="Yes"),"Yes","") -> Yes | AT35: =IF(R35="Delivered","Yes","") -> Yes | AU35: =IF(AND(AS35="Yes",AT35="Yes"),"Yes","") -> Yes | AV35: =IFERROR(VLOOKUP(D35,'Receivable Invoice Detail'!$S$1:$U$3014,3,FALSE),0) -> 0 | AW35: =IF(AU35="Yes",AI35-AV35,0) -> 926.23
A36: 1 | B36: SO16399 | C36: 08840 | D36: INV12536 | E36: Tantalum Mining Corporation of Canada | F36: 45667.393 | G36: 45672.575 | H36: 45673 | I36: Taylor Cook | J36: CAD | K36: 1 | L36: 904.12 | M36: 904.12 | N36: 904.12 | O36: 861.07 | P36: 43.05 | Q36: 904.12 | R36: Delivered | T36: =IF(A36="",T35,A36) -> 1 | U36: =IF(F36="",U35,MONTH(F36)) -> 1 | V36: =IF(F36="",V35,YEAR(F36)) -> 2025 | W36: =IF(AC36="Paid",MONTH(AD36),"") -> 2 | X36: =IF(AC36="Paid",YEAR(AD36),"") -> 2025 | Y36: =IF(C36="",Y35,N36/L36) -> 1 | Z36: =IF(B36="",Z35,B36) -> SO16399 | AA36: =IF(F36="",AA35,F36) -> 45667.393 | AB36: =IF(D36="","No Inv",D36) -> INV12536 | AC36: =IFERROR(VLOOKUP(D36,CAARStatus!$A$2:$AA$1600,22,FALSE),"Not invoiced") -> Paid | AD36: =IF(AC36="Paid",IFERROR(VLOOKUP(D36,CAARStatus!$A$2:$AA$1600,6,FALSE),"Pending"),"Pending") -> 45715 | AE36: =IF(C36="",AE35,C36) -> 08840 | AF36: =IF(E36="",AF35,E36) -> Tantalum Mining Corporation of Canada | AG36: =IF(J36="",AG35,J36) -> CAD | AH36: =IFERROR(IF(AG36="CAD",O36,O36/K36),0) -> 861.07 | AI36: =IF(L36-N36=0,VLOOKUP(U36,rate!A$4:B$15,2,FALSE)*AH36,IF(AG36="USD",O36,AH36*Y36)) -> 598.16648 | AJ36: =IFERROR(AI36/AH36,0) -> 0.69467811 | AK36: =-IF(AG36="CAD",IFERROR(VLOOKUP(D36,CAARStatus!$A$1:$Y$1600,16,FALSE),0),0) -> -861.07 | AL36: =-IF(AG36="USD",IFERROR(VLOOKUP(D36,CAARStatus!$A$1:$Y$1600,11,FALSE),0),0) -> 0 | AM36: =IF(AG36="CAD",AH36+AK36,"") -> 0 | AN36: =IF(AG36="USD",AI36+AL36,"") | AO36: =IF(AC36="Paid","Yes","Pend") -> Yes | AP36: =IF(AND(AO36="Pend",T36<2),"Pend",IF(T36=1,"Yes","XX")) -> Yes | AQ36: =IFERROR(VLOOKUP(Z36,InvBal!$L$4:$P$600,4,FALSE),"Pend") -> Pend | AR36: =IFERROR(VLOOKUP(D36,Manual!$C$1:$E$22,2,FALSE),"Pend") -> Pend | AS36: =IF(OR(AP36="Yes",AQ36="Yes",AR36="Yes"),"Yes","") -> Yes | AT36: =IF(R36="Delivered","Yes","") -> Yes | AU36: =IF(AND(AS36="Yes",AT36="Yes"),"Yes","") -> Yes | AV36: =IFERROR(VLOOKUP(D36,'Receivable Invoice Detail'!$S$1:$U$3014,3,FALSE),0) -> 0 | AW36: =IF(AU36="Yes",AI36-AV36,0) -> 598.16648
A37: 1 | B37: SO16400 | C37: 9569096 | D37: INV12662 | E37: DXP Enterprises, Inc. - Pumping Solutions, Inc. - Hayward California | F37: 45667.397 | G37: 45672.521 | H37: 45707 | I37: Taylor Cook | J37: USD | K37: 0.6958199 | L37: 3105.4444 | M37: 0 | N37: 2160.83 | O37: 2160.83 | Q37: 2160.83 | R37: Delivered | T37: =IF(A37="",T36,A37) -> 1 | U37: =IF(F37="",U36,MONTH(F37)) -> 1 | V37: =IF(F37="",V36,YEAR(F37)) -> 2025 | W37: =IF(AC37="Paid",MONTH(AD37),"") -> 4 | X37: =IF(AC37="Paid",YEAR(AD37),"") -> 2025 | Y37: =IF(C37="",Y36,N37/L37) -> 0.6958199 | Z37: =IF(B37="",Z36,B37) -> SO16400 | AA37: =IF(F37="",AA36,F37) -> 45667.397 | AB37: =IF(D37="","No Inv",D37) -> INV12662 | AC37: =IFERROR(VLOOKUP(D37,CAARStatus!$A$2:$AA$1600,22,FALSE),"Not invoiced") -> Paid | AD37: =IF(AC37="Paid",IFERROR(VLOOKUP(D37,CAARStatus!$A$2:$AA$1600,6,FALSE),"Pending"),"Pending") -> 45754 | AE37: =IF(C37="",AE36,C37) -> 9569096 | AF37: =IF(E37="",AF36,E37) -> DXP Enterprises, Inc. - Pumping Solutions, Inc. - Hayward California | AG37: =IF(J37="",AG36,J37) -> USD | AH37: =IFERROR(IF(AG37="CAD",O37,O37/K37),0) -> 3105.4444 | AI37: =IF(L37-N37=0,VLOOKUP(U37,rate!A$4:B$15,2,FALSE)*AH37,IF(AG37="USD",O37,AH37*Y37)) -> 2160.83 | AJ37: =IFERROR(AI37/AH37,0) -> 0.6958199 | AK37: =-IF(AG37="CAD",IFERROR(VLOOKUP(D37,CAARStatus!$A$1:$Y$1600,16,FALSE),0),0) -> 0 | AL37: =-IF(AG37="USD",IFERROR(VLOOKUP(D37,CAARStatus!$A$1:$Y$1600,11,FALSE),0),0) -> -2160.83 | AM37: =IF(AG37="CAD",AH37+AK37,"") | AN37: =IF(AG37="USD",AI37+AL37,"") -> 0 | AO37: =IF(AC37="Paid","Yes","Pend") -> Yes | AP37: =IF(AND(AO37="Pend",T37<2),"Pend",IF(T37=1,"Yes","XX")) -> Yes | AQ37: =IFERROR(VLOOKUP(Z37,InvBal!$L$4:$P$600,4,FALSE),"Pend") -> Pend | AR37: =IFERROR(VLOOKUP(D37,Manual!$C$1:$E$22,2,FALSE),"Pend") -> Pend | AS37: =IF(OR(AP37="Yes",AQ37="Yes",AR37="Yes"),"Yes","") -> Yes | AT37: =IF(R37="Delivered","Yes","") -> Yes | AU37: =IF(AND(AS37="Yes",AT37="Yes"),"Yes","") -> Yes | AV37: =IFERROR(VLOOKUP(D37,'Receivable Invoice Detail'!$S$1:$U$3014,3,FALSE),0) -> 0 | AW37: =IF(AU37="Yes",AI37-AV37,0) -> 2160.83
A38: 1 | B38: SO16401 | C38: FC10-00114698 | D38: INV12574 | E38: Motion Industries Inc. (U.S.) - Lakeland | F38: 45667.413 | G38: 45670.587 | H38: 45671 | I38: Taylor Cook | J38: USD | K38: 0.69462239 | L38: 120.92901 | M38: 0 | N38: 84 | O38: 84 | Q38: 84 | R38: Delivered | T38: =IF(A38="",T37,A38) -> 1 | U38: =IF(F38="",U37,MONTH(F38)) -> 1 | V38: =IF(F38="",V37,YEAR(F38)) -> 2025 | W38: =IF(AC38="Paid",MONTH(AD38),"") -> 2 | X38: =IF(AC38="Paid",YEAR(AD38),"") -> 2025 | Y38: =IF(C38="",Y37,N38/L38) -> 0.69462239 | Z38: =IF(B38="",Z37,B38) -> SO16401 | AA38: =IF(F38="",AA37,F38) -> 45667.413 | AB38: =IF(D38="","No Inv",D38) -> INV12574 | AC38: =IFERROR(VLOOKUP(D38,CAARStatus!$A$2:$AA$1600,22,FALSE),"Not invoiced") -> Paid | AD38: =IF(AC38="Paid",IFERROR(VLOOKUP(D38,CAARStatus!$A$2:$AA$1600,6,FALSE),"Pending"),"Pending") -> 45716 | AE38: =IF(C38="",AE37,C38) -> FC10-00114698 | AF38: =IF(E38="",AF37,E38) -> Motion Industries Inc. (U.S.) - Lakeland | AG38: =IF(J38="",AG37,J38) -> USD | AH38: =IFERROR(IF(AG38="CAD",O38,O38/K38),0) -> 120.92901 | AI38: =IF(L38-N38=0,VLOOKUP(U38,rate!A$4:B$15,2,FALSE)*AH38,IF(AG38="USD",O38,AH38*Y38)) -> 84 | AJ38: =IFERROR(AI38/AH38,0) -> 0.69462239 | AK38: =-IF(AG38="CAD",IFERROR(VLOOKUP(D38,CAARStatus!$A$1:$Y$1600,16,FALSE),0),0) -> 0 | AL38: =-IF(AG38="USD",IFERROR(VLOOKUP(D38,CAARStatus!$A$1:$Y$1600,11,FALSE),0),0) -> -84 | AM38: =IF(AG38="CAD",AH38+AK38,"") | AN38: =IF(AG38="USD",AI38+AL38,"") -> 0 | AO38: =IF(AC38="Paid","Yes","Pend") -> Yes | AP38: =IF(AND(AO38="Pend",T38<2),"Pend",IF(T38=1,"Yes","XX")) -> Yes | AQ38: =IFERROR(VLOOKUP(Z38,InvBal!$L$4:$P$600,4,FALSE),"Pend") -> Pend | AR38: =IFERROR(VLOOKUP(D38,Manual!$C$1:$E$22,2,FALSE),"Pend") -> Pend | AS38: =IF(OR(AP38="Yes",AQ38="Yes",AR38="Yes"),"Yes","") -> Yes | AT38: =IF(R38="Delivered","Yes","") -> Yes | AU38: =IF(AND(AS38="Yes",AT38="Yes"),"Yes","") -> Yes | AV38: =IFERROR(VLOOKUP(D38,'Receivable Invoice Detail'!$S$1:$U$3014,3,FALSE),0) -> 0 | AW38: =IF(AU38="Yes",AI38-AV38,0) -> 84
A39: 1 | B39: SO16402 | C39: 2243614 | D39: INV12530 | E39: Zijin Mining - Rosebel Goldmines N.V. | F39: 45667.485 | G39: 45670.436 | H39: 45710 | I39: Amanda Qiao | J39: USD | K39: 0.69462239 | L39: 5373.711 | M39: 0 | N39: 3732.7 | O39: 3732.7 | Q39: 3732.7 | R39: Delivered | T39: =IF(A39="",T38,A39) -> 1 | U39: =IF(F39="",U38,MONTH(F39)) -> 1 | V39: =IF(F39="",V38,YEAR(F39)) -> 2025 | W39: =IF(AC39="Paid",MONTH(AD39),"") -> 3 | X39: =IF(AC39="Paid",YEAR(AD39),"") -> 2025 | Y39: =IF(C39="",Y38,N39/L39) -> 0.69462239 | Z39: =IF(B39="",Z38,B39) -> SO16402 | AA39: =IF(F39="",AA38,F39) -> 45667.485 | AB39: =IF(D39="","No Inv",D39) -> INV12530 | AC39: =IFERROR(VLOOKUP(D39,CAARStatus!$A$2:$AA$1600,22,FALSE),"Not invoiced") -> Paid | AD39: =IF(AC39="Paid",IFERROR(VLOOKUP(D39,CAARStatus!$A$2:$AA$1600,6,FALSE),"Pending"),"Pending") -> 45741 | AE39: =IF(C39="",AE38,C39) -> 2243614 | AF39: =IF(E39="",AF38,E39) -> Zijin Mining - Rosebel Goldmines N.V. | AG39: =IF(J39="",AG38,J39) -> USD | AH39: =IFERROR(IF(AG39="CAD",O39,O39/K39),0) -> 5373.711 | AI39: =IF(L39-N39=0,VLOOKUP(U39,rate!A$4:B$15,2,FALSE)*AH39,IF(AG39="USD",O39,AH39*Y39)) -> 3732.7 | AJ39: =IFERROR(AI39/AH39,0) -> 0.69462239 | AK39: =-IF(AG39="CAD",IFERROR(VLOOKUP(D39,CAARStatus!$A$1:$Y$1600,16,FALSE),0),0) -> 0 | AL39: =-IF(AG39="USD",IFERROR(VLOOKUP(D39,CAARStatus!$A$1:$Y$1600,11,FALSE),0),0) -> -3732.7 | AM39: =IF(AG39="CAD",AH39+AK39,"") | AN39: =IF(AG39="USD",AI39+AL39,"") -> 0 | AO39: =IF(AC39="Paid","Yes","Pend") -> Yes | AP39: =IF(AND(AO39="Pend",T39<2),"Pend",IF(T39=1,"Yes","XX")) -> Yes | AQ39: =IFERROR(VLOOKUP(Z39,InvBal!$L$4:$P$600,4,FALSE),"Pend") -> Pend | AR39: =IFERROR(VLOOKUP(D39,Manual!$C$1:$E$22,2,FALSE),"Pend") -> Pend | AS39: =IF(OR(AP39="Yes",AQ39="Yes",AR39="Yes"),"Yes","") -> Yes | AT39: =IF(R39="Delivered","Yes","") -> Yes | AU39: =IF(AND(AS39="Yes",AT39="Yes"),"Yes","") -> Yes | AV39: =IFERROR(VLOOKUP(D39,'Receivable Invoice Detail'!$S$1:$U$3014,3,FALSE),0) -> 250 | AW39: =IF(AU39="Yes",AI39-AV39,0) -> 3482.7
A40: 1 | B40: SO16403 | C40: MB21-00185834 | D40: INV12508 | E40: Motion Industries Inc. (Canada) - Winnipeg | F40: 45667.524 | G40: 45667.608 | H40: 45670 | I40: Taylor Cook | J40: CAD | K40: 1 | L40: 540.3 | M40: 0 | N40: 374.24329 | O40: 540.3 | Q40: 540.3 | R40: Delivered | T40: =IF(A40="",T39,A40) -> 1 | U40: =IF(F40="",U39,MONTH(F40)) -> 1 | V40: =IF(F40="",V39,YEAR(F40)) -> 2025 | W40: =IF(AC40="Paid",MONTH(AD40),"") -> 2 | X40: =IF(AC40="Paid",YEAR(AD40),"") -> 2025 | Y40: =IF(C40="",Y39,N40/L40) -> 0.69265832 | Z40: =IF(B40="",Z39,B40) -> SO16403 | AA40: =IF(F40="",AA39,F40) -> 45667.524 | AB40: =IF(D40="","No Inv",D40) -> INV12508 | AC40: =IFERROR(VLOOKUP(D40,CAARStatus!$A$2:$AA$1600,22,FALSE),"Not invoiced") -> Paid | AD40: =IF(AC40="Paid",IFERROR(VLOOKUP(D40,CAARStatus!$A$2:$AA$1600,6,FALSE),"Pending"),"Pending") -> 45700 | AE40: =IF(C40="",AE39,C40) -> MB21-00185834 | AF40: =IF(E40="",AF39,E40) -> Motion Industries Inc. (Canada) - Winnipeg | AG40: =IF(J40="",AG39,J40) -> CAD | AH40: =IFERROR(IF(AG40="CAD",O40,O40/K40),0) -> 540.3 | AI40: =IF(L40-N40=0,VLOOKUP(U40,rate!A$4:B$15,2,FALSE)*AH40,IF(AG40="USD",O40,AH40*Y40)) -> 374.24329 | AJ40: =IFERROR(AI40/AH40,0) -> 0.69265832 | AK40: =-IF(AG40="CAD",IFERROR(VLOOKUP(D40,CAARStatus!$A$1:$Y$1600,16,FALSE),0),0) -> -540.3 | AL40: =-IF(AG40="USD",IFERROR(VLOOKUP(D40,CAARStatus!$A$1:$Y$1600,11,FALSE),0),0) -> 0 | AM40: =IF(AG40="CAD",AH40+AK40,"") -> 0 | AN40: =IF(AG40="USD",AI40+AL40,"") | AO40: =IF(AC40="Paid","Yes","Pend") -> Yes | AP40: =IF(AND(AO40="Pend",T40<2),"Pend",IF(T40=1,"Yes","XX")) -> Yes | AQ40: =IFERROR(VLOOKUP(Z40,InvBal!$L$4:$P$600,4,FALSE),"Pend") -> Pend | AR40: =IFERROR(VLOOKUP(D40,Manual!$C$1:$E$22,2,FALSE),"Pend") -> Pend | AS40: =IF(OR(AP40="Yes",AQ40="Yes",AR40="Yes"),"Yes","") -> Yes | AT40: =IF(R40="Delivered","Yes","") -> Yes | AU40: =IF(AND(AS40="Yes",AT40="Yes"),"Yes","") -> Yes | AV40: =IFERROR(VLOOKUP(D40,'Receivable Invoice Detail'!$S$1:$U$3014,3,FALSE),0) -> 0 | AW40: =IF(AU40="Yes",AI40-AV40,0) -> 374.24329
A41: 1 | B41: SO16405 | C41: 2100484115 | D41: INV12513 | E41: Wajax Limited - Sorel-Tracy | F41: 45667.625 | G41: 45667.701 | H41: 45670 | I41: Taylor Cook | J41: CAD | K41: 1 | L41: 2138.66 | M41: 0 | N41: 1481.3607 | O41: 2036.82 | P41: 101.84 | Q41: 2138.66 | R41: Delivered | T41: =IF(A41="",T40,A41) -> 1 | U41: =IF(F41="",U40,MONTH(F41)) -> 1 | V41: =IF(F41="",V40,YEAR(F41)) -> 2025 | W41: =IF(AC41="Paid",MONTH(AD41),"") -> 2 | X41: =IF(AC41="Paid",YEAR(AD41),"") -> 2025 | Y41: =IF(C41="",Y40,N41/L41) -> 0.69265832 | Z41: =IF(B41="",Z40,B41) -> SO16405 | AA41: =IF(F41="",AA40,F41) -> 45667.625 | AB41: =IF(D41="","No Inv",D41) -> INV12513 | AC41: =IFERROR(VLOOKUP(D41,CAARStatus!$A$2:$AA$1600,22,FALSE),"Not invoiced") -> Paid | AD41: =IF(AC41="Paid",IFERROR(VLOOKUP(D41,CAARStatus!$A$2:$AA$1600,6,FALSE),"Pending"),"Pending") -> 45707 | AE41: =IF(C41="",AE40,C41) -> 2100484115 | AF41: =IF(E41="",AF40,E41) -> Wajax Limited - Sorel-Tracy | AG41: =IF(J41="",AG40,J41) -> CAD | AH41: =IFERROR(IF(AG41="CAD",O41,O41/K41),0) -> 2036.82 | AI41: =IF(L41-N41=0,VLOOKUP(U41,rate!A$4:B$15,2,FALSE)*AH41,IF(AG41="USD",O41,AH41*Y41)) -> 1410.8203 | AJ41: =IFERROR(AI41/AH41,0) -> 0.69265832 | AK41: =-IF(AG41="CAD",IFERROR(VLOOKUP(D41,CAARStatus!$A$1:$Y$1600,16,FALSE),0),0) -> -2036.82 | AL41: =-IF(AG41="USD",IFERROR(VLOOKUP(D41,CAARStatus!$A$1:$Y$1600,11,FALSE),0),0) -> 0 | AM41: =IF(AG41="CAD",AH41+AK41,"") -> 0 | AN41: =IF(AG41="USD",AI41+AL41,"") | AO41: =IF(AC41="Paid","Yes","Pend") -> Yes | AP41: =IF(AND(AO41="Pend",T41<2),"Pend",IF(T41=1,"Yes","XX")) -> Yes | AQ41: =IFERROR(VLOOKUP(Z41,InvBal!$L$4:$P$600,4,FALSE),"Pend") -> Pend | AR41: =IFERROR(VLOOKUP(D41,Manual!$C$1:$E$22,2,FALSE),"Pend") -> Pend | AS41: =IF(OR(AP41="Yes",AQ41="Yes",AR41="Yes"),"Yes","") -> Yes | AT41: =IF(R41="Delivered","Yes","") -> Yes | AU41: =IF(AND(AS41="Yes",AT41="Yes"),"Yes","") -> Yes | AV41: =IFERROR(VLOOKUP(D41,'Receivable Invoice Detail'!$S$1:$U$3014,3,FALSE),0) -> 0 | AW41: =IF(AU41="Yes",AI41-AV41,0) -> 1410.8203
A42: 1 | B42: SO16406 | C42: 2981 | D42: INV12635 | E42: Les Pompes du St-Laurent Inc. | F42: 45667.649 | G42: 45670.593 | H42: 45698 | I42: Ian Trottier | J42: CAD | K42: 1 | L42: 2358.51 | M42: 0 | N42: 1636.6784 | O42: 2246.2 | P42: 112.31 | Q42: 2358.51 | R42: Delivered | T42: =IF(A42="",T41,A42) -> 1 | U42: =IF(F42="",U41,MONTH(F42)) -> 1 | V42: =IF(F42="",V41,YEAR(F42)) -> 2025 | W42: =IF(AC42="Paid",MONTH(AD42),"") -> 4 | X42: =IF(AC42="Paid",YEAR(AD42),"") -> 2025 | Y42: =IF(C42="",Y41,N42/L42) -> 0.6939459 | Z42: =IF(B42="",Z41,B42) -> SO16406 | AA42: =IF(F42="",AA41,F42) -> 45667.649 | AB42: =IF(D42="","No Inv",D42) -> INV12635 | AC42: =IFERROR(VLOOKUP(D42,CAARStatus!$A$2:$AA$1600,22,FALSE),"Not invoiced") -> Paid | AD42: =IF(AC42="Paid",IFERROR(VLOOKUP(D42,CAARStatus!$A$2:$AA$1600,6,FALSE),"Pending"),"Pending") -> 45750 | AE42: =IF(C42="",AE41,C42) -> 2981 | AF42: =IF(E42="",AF41,E42) -> Les Pompes du St-Laurent Inc. | AG42: =IF(J42="",AG41,J42) -> CAD | AH42: =IFERROR(IF(AG42="CAD",O42,O42/K42),0) -> 2246.2 | AI42: =IF(L42-N42=0,VLOOKUP(U42,rate!A$4:B$15,2,FALSE)*AH42,IF(AG42="USD",O42,AH42*Y42)) -> 1558.7413 | AJ42: =IFERROR(AI42/AH42,0) -> 0.6939459 | AK42: =-IF(AG42="CAD",IFERROR(VLOOKUP(D42,CAARStatus!$A$1:$Y$1600,16,FALSE),0),0) -> -2246.2 | AL42: =-IF(AG42="USD",IFERROR(VLOOKUP(D42,CAARStatus!$A$1:$Y$1600,11,FALSE),0),0) -> 0 | AM42: =IF(AG42="CAD",AH42+AK42,"") -> 0 | AN42: =IF(AG42="USD",AI42+AL42,"") | AO42: =IF(AC42="Paid","Yes","Pend") -> Yes | AP42: =IF(AND(AO42="Pend",T42<2),"Pend",IF(T42=1,"Yes","XX")) -> Yes | AQ42: =IFERROR(VLOOKUP(Z42,InvBal!$L$4:$P$600,4,FALSE),"Pend") -> Pend | AR42: =IFERROR(VLOOKUP(D42,Manual!$C$1:$E$22,2,FALSE),"Pend") -> Pend | AS42: =IF(OR(AP42="Yes",AQ42="Yes",AR42="Yes"),"Yes","") -> Yes | AT42: =IF(R42="Delivered","Yes","") -> Yes | AU42: =IF(AND(AS42="Yes",AT42="Yes"),"Yes","") -> Yes | AV42: =IFERROR(VLOOKUP(D42,'Receivable Invoice Detail'!$S$1:$U$3014,3,FALSE),0) -> 0 | AW42: =IF(AU42="Yes",AI42-AV42,0) -> 1558.7413
A43: 1 | B43: SO16408 | C43: P-11425 | D43: INV12519 | E43: Cartledge & Associates Inc. | F43: 45670.403 | G43: 45671.538 | H43: 45672 | I43: Ian Trottier | J43: USD | K43: 0.6939459 | L43: 4614.279 | M43: 0 | N43: 3202.06 | O43: 3202.06 | Q43: 3202.06 | R43: Delivered | T43: =IF(A43="",T42,A43) -> 1 | U43: =IF(F43="",U42,MONTH(F43)) -> 1 | V43: =IF(F43="",V42,YEAR(F43)) -> 2025 | W43: =IF(AC43="Paid",MONTH(AD43),"") -> 2 | X43: =IF(AC43="Paid",YEAR(AD43),"") -> 2025 | Y43: =IF(C43="",Y42,N43/L43) -> 0.6939459 | Z43: =IF(B43="",Z42,B43) -> SO16408 | AA43: =IF(F43="",AA42,F43) -> 45670.403 | AB43: =IF(D43="","No Inv",D43) -> INV12519 | AC43: =IFERROR(VLOOKUP(D43,CAARStatus!$A$2:$AA$1600,22,FALSE),"Not invoiced") -> Paid | AD43: =IF(AC43="Paid",IFERROR(VLOOKUP(D43,CAARStatus!$A$2:$AA$1600,6,FALSE),"Pending"),"Pending") -> 45715 | AE43: =IF(C43="",AE42,C43) -> P-11425 | AF43: =IF(E43="",AF42,E43) -> Cartledge & Associates Inc. | AG43: =IF(J43="",AG42,J43) -> USD | AH43: =IFERROR(IF(AG43="CAD",O43,O43/K43),0) -> 4614.279 | AI43: =IF(L43-N43=0,VLOOKUP(U43,rate!A$4:B$15,2,FALSE)*AH43,IF(AG43="USD",O43,AH43*Y43)) -> 3202.06 | AJ43: =IFERROR(AI43/AH43,0) -> 0.6939459 | AK43: =-IF(AG43="CAD",IFERROR(VLOOKUP(D43,CAARStatus!$A$1:$Y$1600,16,FALSE),0),0) -> 0 | AL43: =-IF(AG43="USD",IFERROR(VLOOKUP(D43,CAARStatus!$A$1:$Y$1600,11,FALSE),0),0) -> -3202.06 | AM43: =IF(AG43="CAD",AH43+AK43,"") | AN43: =IF(AG43="USD",AI43+AL43,"") -> 0 | AO43: =IF(AC43="Paid","Yes","Pend") -> Yes | AP43: =IF(AND(AO43="Pend",T43<2),"Pend",IF(T43=1,"Yes","XX")) -> Yes | AQ43: =IFERROR(VLOOKUP(Z43,InvBal!$L$4:$P$600,4,FALSE),"Pend") -> Pend | AR43: =IFERROR(VLOOKUP(D43,Manual!$C$1:$E$22,2,FALSE),"Pend") -> Pend | AS43: =IF(OR(AP43="Yes",AQ43="Yes",AR43="Yes"),"Yes","") -> Yes | AT43: =IF(R43="Delivered","Yes","") -> Yes | AU43: =IF(AND(AS43="Yes",AT43="Yes"),"Yes","") -> Yes | AV43: =IFERROR(VLOOKUP(D43,'Receivable Invoice Detail'!$S$1:$U$3014,3,FALSE),0) -> 589 | AW43: =IF(AU43="Yes",AI43-AV43,0) -> 2613.06
A44: 1 | B44: SO16409 | C44: PO-038220 | D44: INV12515 | E44: Southeast Pump Specialist, Inc. | F44: 45670.409 | G44: 45670.43 | H44: 45671 | I44: Ian Trottier | J44: USD | K44: 0.69462239 | L44: 4344.1589 | M44: 0 | N44: 3017.55 | O44: 3017.55 | Q44: 3017.55 | R44: Delivered | T44: =IF(A44="",T43,A44) -> 1 | U44: =IF(F44="",U43,MONTH(F44)) -> 1 | V44: =IF(F44="",V43,YEAR(F44)) -> 2025 | W44: =IF(AC44="Paid",MONTH(AD44),"") -> 4 | X44: =IF(AC44="Paid",YEAR(AD44),"") -> 2025 | Y44: =IF(C44="",Y43,N44/L44) -> 0.69462239 | Z44: =IF(B44="",Z43,B44) -> SO16409 | AA44: =IF(F44="",AA43,F44) -> 45670.409 | AB44: =IF(D44="","No Inv",D44) -> INV12515 | AC44: =IFERROR(VLOOKUP(D44,CAARStatus!$A$2:$AA$1600,22,FALSE),"Not invoiced") -> Paid | AD44: =IF(AC44="Paid",IFERROR(VLOOKUP(D44,CAARStatus!$A$2:$AA$1600,6,FALSE),"Pending"),"Pending") -> 45754 | AE44: =IF(C44="",AE43,C44) -> PO-038220 | AF44: =IF(E44="",AF43,E44) -> Southeast Pump Specialist, Inc. | AG44: =IF(J44="",AG43,J44) -> USD | AH44: =IFERROR(IF(AG44="CAD",O44,O44/K44),0) -> 4344.1589 | AI44: =IF(L44-N44=0,VLOOKUP(U44,rate!A$4:B$15,2,FALSE)*AH44,IF(AG44="USD",O44,AH44*Y44)) -> 3017.55 | AJ44: =IFERROR(AI44/AH44,0) -> 0.69462239 | AK44: =-IF(AG44="CAD",IFERROR(VLOOKUP(D44,CAARStatus!$A$1:$Y$1600,16,FALSE),0),0) -> 0 | AL44: =-IF(AG44="USD",IFERROR(VLOOKUP(D44,CAARStatus!$A$1:$Y$1600,11,FALSE),0),0) -> -3017.55 | AM44: =IF(AG44="CAD",AH44+AK44,"") | AN44: =IF(AG44="USD",AI44+AL44,"") -> 0 | AO44: =IF(AC44="Paid","Yes","Pend") -> Yes | AP44: =IF(AND(AO44="Pend",T44<2),"Pend",IF(T44=1,"Yes","XX")) -> Yes | AQ44: =IFERROR(VLOOKUP(Z44,InvBal!$L$4:$P$600,4,FALSE),"Pend") -> Pend | AR44: =IFERROR(VLOOKUP(D44,Manual!$C$1:$E$22,2,FALSE),"Pend") -> Pend | AS44: =IF(OR(AP44="Yes",AQ44="Yes",AR44="Yes"),"Yes","") -> Yes | AT44: =IF(R44="Delivered","Yes","") -> Yes | AU44: =IF(AND(AS44="Yes",AT44="Yes"),"Yes","") -> Yes | AV44: =IFERROR(VLOOKUP(D44,'Receivable Invoice Detail'!$S$1:$U$3014,3,FALSE),0) -> 603 | AW44: =IF(AU44="Yes",AI44-AV44,0) -> 2414.55
A45: 1 | B45: SO16411 | C45: 2982 | D45: INV12535 | E45: Les Pompes du St-Laurent Inc. | F45: 45670.481 | G45: 45670.62 | H45: 45671 | I45: Ian Trottier | J45: CAD | K45: 1 | L45: 2776.1 | M45: 0 | N45: 1926.4632 | O45: 2643.9 | P45: 132.2 | Q45: 2776.1 | R45: Delivered | T45: =IF(A45="",T44,A45) -> 1 | U45: =IF(F45="",U44,MONTH(F45)) -> 1 | V45: =IF(F45="",V44,YEAR(F45)) -> 2025 | W45: =IF(AC45="Paid",MONTH(AD45),"") -> 2 | X45: =IF(AC45="Paid",YEAR(AD45),"") -> 2025 | Y45: =IF(C45="",Y44,N45/L45) -> 0.6939459 | Z45: =IF(B45="",Z44,B45) -> SO16411 | AA45: =IF(F45="",AA44,F45) -> 45670.481 | AB45: =IF(D45="","No Inv",D45) -> INV12535 | AC45: =IFERROR(VLOOKUP(D45,CAARStatus!$A$2:$AA$1600,22,FALSE),"Not invoiced") -> Paid | AD45: =IF(AC45="Paid",IFERROR(VLOOKUP(D45,CAARStatus!$A$2:$AA$1600,6,FALSE),"Pending"),"Pending") -> 45706 | AE45: =IF(C45="",AE44,C45) -> 2982 | AF45: =IF(E45="",AF44,E45) -> Les Pompes du St-Laurent Inc. | AG45: =IF(J45="",AG44,J45) -> CAD | AH45: =IFERROR(IF(AG45="CAD",O45,O45/K45),0) -> 2643.9 | AI45: =IF(L45-N45=0,VLOOKUP(U45,rate!A$4:B$15,2,FALSE)*AH45,IF(AG45="USD",O45,AH45*Y45)) -> 1834.7236 | AJ45: =IFERROR(AI45/AH45,0) -> 0.6939459 | AK45: =-IF(AG45="CAD",IFERROR(VLOOKUP(D45,CAARStatus!$A$1:$Y$1600,16,FALSE),0),0) -> -2643.9 | AL45: =-IF(AG45="USD",IFERROR(VLOOKUP(D45,CAARStatus!$A$1:$Y$1600,11,FALSE),0),0) -> 0 | AM45: =IF(AG45="CAD",AH45+AK45,"") -> 0 | AN45: =IF(AG45="USD",AI45+AL45,"") | AO45: =IF(AC45="Paid","Yes","Pend") -> Yes | AP45: =IF(AND(AO45="Pend",T45<2),"Pend",IF(T45=1,"Yes","XX")) -> Yes | AQ45: =IFERROR(VLOOKUP(Z45,InvBal!$L$4:$P$600,4,FALSE),"Pend") -> Pend | AR45: =IFERROR(VLOOKUP(D45,Manual!$C$1:$E$22,2,FALSE),"Pend") -> Pend | AS45: =IF(OR(AP45="Yes",AQ45="Yes",AR45="Yes"),"Yes","") -> Yes | AT45: =IF(R45="Delivered","Yes","") -> Yes | AU45: =IF(AND(AS45="Yes",AT45="Yes"),"Yes","") -> Yes | AV45: =IFERROR(VLOOKUP(D45,'Receivable Invoice Detail'!$S$1:$U$3014,3,FALSE),0) -> 0 | AW45: =IF(AU45="Yes",AI45-AV45,0) -> 1834.7236
A46: 1 | B46: SO16412 | C46: 4500554481 | D46: INV12539 | E46: Glencore Canada Corporation - Rouyn-Noranda, Glencore Canada Corp. | F46: 45670.526 | G46: 45670.532 | H46: 45670 | I46: Ian Trottier | J46: CAD | K46: 1 | L46: 2453.49 | M46: 0 | N46: 1702.5893 | O46: 2336.66 | P46: 116.83 | Q46: 2453.49 | R46: Delivered | T46: =IF(A46="",T45,A46) -> 1 | U46: =IF(F46="",U45,MONTH(F46)) -> 1 | V46: =IF(F46="",V45,YEAR(F46)) -> 2025 | W46: =IF(AC46="Paid",MONTH(AD46),"") -> 2 | X46: =IF(AC46="Paid",YEAR(AD46),"") -> 2025 | Y46: =IF(C46="",Y45,N46/L46) -> 0.6939459 | Z46: =IF(B46="",Z45,B46) -> SO16412 | AA46: =IF(F46="",AA45,F46) -> 45670.526 | AB46: =IF(D46="","No Inv",D46) -> INV12539 | AC46: =IFERROR(VLOOKUP(D46,CAARStatus!$A$2:$AA$1600,22,FALSE),"Not invoiced") -> Paid | AD46: =IF(AC46="Paid",IFERROR(VLOOKUP(D46,CAARStatus!$A$2:$AA$1600,6,FALSE),"Pending"),"Pending") -> 45716 | AE46: =IF(C46="",AE45,C46) -> 4500554481 | AF46: =IF(E46="",AF45,E46) -> Glencore Canada Corporation - Rouyn-Noranda, Glencore Canada Corp. | AG46: =IF(J46="",AG45,J46) -> CAD | AH46: =IFERROR(IF(AG46="CAD",O46,O46/K46),0) -> 2336.66 | AI46: =IF(L46-N46=0,VLOOKUP(U46,rate!A$4:B$15,2,FALSE)*AH46,IF(AG46="USD",O46,AH46*Y46)) -> 1621.5156 | AJ46: =IFERROR(AI46/AH46,0) -> 0.6939459 | AK46: =-IF(AG46="CAD",IFERROR(VLOOKUP(D46,CAARStatus!$A$1:$Y$1600,16,FALSE),0),0) -> -2336.66 | AL46: =-IF(AG46="USD",IFERROR(VLOOKUP(D46,CAARStatus!$A$1:$Y$1600,11,FALSE),0),0) -> 0 | AM46: =IF(AG46="CAD",AH46+AK46,"") -> 0 | AN46: =IF(AG46="USD",AI46+AL46,"") | AO46: =IF(AC46="Paid","Yes","Pend") -> Yes | AP46: =IF(AND(AO46="Pend",T46<2),"Pend",IF(T46=1,"Yes","XX")) -> Yes | AQ46: =IFERROR(VLOOKUP(Z46,InvBal!$L$4:$P$600,4,FALSE),"Pend") -> Pend | AR46: =IFERROR(VLOOKUP(D46,Manual!$C$1:$E$22,2,FALSE),"Pend") -> Pend | AS46: =IF(OR(AP46="Yes",AQ46="Yes",AR46="Yes"),"Yes","") -> Yes | AT46: =IF(R46="Delivered","Yes","") -> Yes | AU46: =IF(AND(AS46="Yes",AT46="Yes"),"Yes","") -> Yes | AV46: =IFERROR(VLOOKUP(D46,'Receivable Invoice Detail'!$S$1:$U$3014,3,FALSE),0) -> 0 | AW46: =IF(AU46="Yes",AI46-AV46,0) -> 1621.5156
A47: 1 | B47: SO16413 | C47: AZ52-00108614 | D47: INV12516 | E47: Motion Industries Inc. (U.S.) - Tucson | F47: 45670.539 | G47: 45671.513 | H47: 45672 | I47: Ian Trottier | J47: USD | K47: 0.6939459 | L47: 478.65402 | M47: 0 | N47: 332.16 | O47: 332.16 | Q47: 332.16 | R47: Delivered | T47: =IF(A47="",T46,A47) -> 1 | U47: =IF(F47="",U46,MONTH(F47)) -> 1 | V47: =IF(F47="",V46,YEAR(F47)) -> 2025 | W47: =IF(AC47="Paid",MONTH(AD47),"") -> 2 | X47: =IF(AC47="Paid",YEAR(AD47),"") -> 2025 | Y47: =IF(C47="",Y46,N47/L47) -> 0.6939459 | Z47: =IF(B47="",Z46,B47) -> SO16413 | AA47: =IF(F47="",AA46,F47) -> 45670.539 | AB47: =IF(D47="","No Inv",D47) -> INV12516 | AC47: =IFERROR(VLOOKUP(D47,CAARStatus!$A$2:$AA$1600,22,FALSE),"Not invoiced") -> Paid | AD47: =IF(AC47="Paid",IFERROR(VLOOKUP(D47,CAARStatus!$A$2:$AA$1600,6,FALSE),"Pending"),"Pending") -> 45702 | AE47: =IF(C47="",AE46,C47) -> AZ52-00108614 | AF47: =IF(E47="",AF46,E47) -> Motion Industries Inc. (U.S.) - Tucson | AG47: =IF(J47="",AG46,J47) -> USD | AH47: =IFERROR(IF(AG47="CAD",O47,O47/K47),0) -> 478.65402 | AI47: =IF(L47-N47=0,VLOOKUP(U47,rate!A$4:B$15,2,FALSE)*AH47,IF(AG47="USD",O47,AH47*Y47)) -> 332.16 | AJ47: =IFERROR(AI47/AH47,0) -> 0.6939459 | AK47: =-IF(AG47="CAD",IFERROR(VLOOKUP(D47,CAARStatus!$A$1:$Y$1600,16,FALSE),0),0) -> 0 | AL47: =-IF(AG47="USD",IFERROR(VLOOKUP(D47,CAARStatus!$A$1:$Y$1600,11,FALSE),0),0) -> -332.16 | AM47: =IF(AG47="CAD",AH47+AK47,"") | AN47: =IF(AG47="USD",AI47+AL47,"") -> 0 | AO47: =IF(AC47="Paid","Yes","Pend") -> Yes | AP47: =IF(AND(AO47="Pend",T47<2),"Pend",IF(T47=1,"Yes","XX")) -> Yes | AQ47: =IFERROR(VLOOKUP(Z47,InvBal!$L$4:$P$600,4,FALSE),"Pend") -> Pend | AR47: =IFERROR(VLOOKUP(D47,Manual!$C$1:$E$22,2,FALSE),"Pend") -> Pend | AS47: =IF(OR(AP47="Yes",AQ47="Yes",AR47="Yes"),"Yes","") -> Yes | AT47: =IF(R47="Delivered","Yes","") -> Yes | AU47: =IF(AND(AS47="Yes",AT47="Yes"),"Yes","") -> Yes | AV47: =IFERROR(VLOOKUP(D47,'Receivable Invoice Detail'!$S$1:$U$3014,3,FALSE),0) -> 0 | AW47: =IF(AU47="Yes",AI47-AV47,0) -> 332.16
A48: 1 | B48: SO16414 | C48: 0203793 - JRF | D48: INV12626 | E48: Electric Pump | F48: 45670.543 | G48: 45674.552 | H48: 45676 | I48: Taylor Cook | J48: USD | K48: 0.69535056 | L48: 102.85459 | M48: 0 | N48: 71.52 | O48: 71.52 | Q48: 71.52 | R48: Delivered | T48: =IF(A48="",T47,A48) -> 1 | U48: =IF(F48="",U47,MONTH(F48)) -> 1 | V48: =IF(F48="",V47,YEAR(F48)) -> 2025 | W48: =IF(AC48="Paid",MONTH(AD48),"") -> 3 | X48: =IF(AC48="Paid",YEAR(AD48),"") -> 2025 | Y48: =IF(C48="",Y47,N48/L48) -> 0.69535056 | Z48: =IF(B48="",Z47,B48) -> SO16414 | AA48: =IF(F48="",AA47,F48) -> 45670.543 | AB48: =IF(D48="","No Inv",D48) -> INV12626 | AC48: =IFERROR(VLOOKUP(D48,CAARStatus!$A$2:$AA$1600,22,FALSE),"Not invoiced") -> Paid | AD48: =IF(AC48="Paid",IFERROR(VLOOKUP(D48,CAARStatus!$A$2:$AA$1600,6,FALSE),"Pending"),"Pending") -> 45743 | AE48: =IF(C48="",AE47,C48) -> 0203793 - JRF | AF48: =IF(E48="",AF47,E48) -> Electric Pump | AG48: =IF(J48="",AG47,J48) -> USD | AH48: =IFERROR(IF(AG48="CAD",O48,O48/K48),0) -> 102.85459 | AI48: =IF(L48-N48=0,VLOOKUP(U48,rate!A$4:B$15,2,FALSE)*AH48,IF(AG48="USD",O48,AH48*Y48)) -> 71.52 | AJ48: =IFERROR(AI48/AH48,0) -> 0.69535056 | AK48: =-IF(AG48="CAD",IFERROR(VLOOKUP(D48,CAARStatus!$A$1:$Y$1600,16,FALSE),0),0) -> 0 | AL48: =-IF(AG48="USD",IFERROR(VLOOKUP(D48,CAARStatus!$A$1:$Y$1600,11,FALSE),0),0) -> -71.52 | AM48: =IF(AG48="CAD",AH48+AK48,"") | AN48: =IF(AG48="USD",AI48+AL48,"") -> 0 | AO48: =IF(AC48="Paid","Yes","Pend") -> Yes | AP48: =IF(AND(AO48="Pend",T48<2),"Pend",IF(T48=1,"Yes","XX")) -> Yes | AQ48: =IFERROR(VLOOKUP(Z48,InvBal!$L$4:$P$600,4,FALSE),"Pend") -> Pend | AR48: =IFERROR(VLOOKUP(D48,Manual!$C$1:$E$22,2,FALSE),"Pend") -> Pend | AS48: =IF(OR(AP48="Yes",AQ48="Yes",AR48="Yes"),"Yes","") -> Yes | AT48: =IF(R48="Delivered","Yes","") -> Yes | AU48: =IF(AND(AS48="Yes",AT48="Yes"),"Yes","") -> Yes | AV48: =IFERROR(VLOOKUP(D48,'Receivable Invoice Detail'!$S$1:$U$3014,3,FALSE),0) -> 0 | AW48: =IF(AU48="Yes",AI48-AV48,0) -> 71.52
A49: 1 | B49: SO16417 | C49: 1042 | D49: INV12872 | E49: Mill-Right Mine Services Inc. | F49: 45670.66 | G49: 45672.474 | H49: 45749 | I49: Jeff Bell | J49: USD | K49: 0.6958199 | L49: 5734.2425 | M49: 0 | N49: 3990 | O49: 3990 | Q49: 3990 | R49: Delivered | T49: =IF(A49="",T48,A49) -> 1 | U49: =IF(F49="",U48,MONTH(F49)) -> 1 | V49: =IF(F49="",V48,YEAR(F49)) -> 2025 | W49: =IF(AC49="Paid",MONTH(AD49),"") -> 5 | X49: =IF(AC49="Paid",YEAR(AD49),"") -> 2025 | Y49: =IF(C49="",Y48,N49/L49) -> 0.6958199 | Z49: =IF(B49="",Z48,B49) -> SO16417 | AA49: =IF(F49="",AA48,F49) -> 45670.66 | AB49: =IF(D49="","No Inv",D49) -> INV12872 | AC49: =IFERROR(VLOOKUP(D49,CAARStatus!$A$2:$AA$1600,22,FALSE),"Not invoiced") -> Paid | AD49: =IF(AC49="Paid",IFERROR(VLOOKUP(D49,CAARStatus!$A$2:$AA$1600,6,FALSE),"Pending"),"Pending") -> 45806 | AE49: =IF(C49="",AE48,C49) -> 1042 | AF49: =IF(E49="",AF48,E49) -> Mill-Right Mine Services Inc. | AG49: =IF(J49="",AG48,J49) -> USD | AH49: =IFERROR(IF(AG49="CAD",O49,O49/K49),0) -> 5734.2425 | AI49: =IF(L49-N49=0,VLOOKUP(U49,rate!A$4:B$15,2,FALSE)*AH49,IF(AG49="USD",O49,AH49*Y49)) -> 3990 | AJ49: =IFERROR(AI49/AH49,0) -> 0.6958199 | AK49: =-IF(AG49="CAD",IFERROR(VLOOKUP(D49,CAARStatus!$A$1:$Y$1600,16,FALSE),0),0) -> 0 | AL49: =-IF(AG49="USD",IFERROR(VLOOKUP(D49,CAARStatus!$A$1:$Y$1600,11,FALSE),0),0) -> -3990 | AM49: =IF(AG49="CAD",AH49+AK49,"") | AN49: =IF(AG49="USD",AI49+AL49,"") -> 0 | AO49: =IF(AC49="Paid","Yes","Pend") -> Yes | AP49: =IF(AND(AO49="Pend",T49<2),"Pend",IF(T49=1,"Yes","XX")) -> Yes | AQ49: =IFERROR(VLOOKUP(Z49,InvBal!$L$4:$P$600,4,FALSE),"Pend") -> Pend | AR49: =IFERROR(VLOOKUP(D49,Manual!$C$1:$E$22,2,FALSE),"Pend") -> Pend | AS49: =IF(OR(AP49="Yes",AQ49="Yes",AR49="Yes"),"Yes","") -> Yes | AT49: =IF(R49="Delivered","Yes","") -> Yes | AU49: =IF(AND(AS49="Yes",AT49="Yes"),"Yes","") -> Yes | AV49: =IFERROR(VLOOKUP(D49,'Receivable Invoice Detail'!$S$1:$U$3014,3,FALSE),0) -> 0 | AW49: =IF(AU49="Yes",AI49-AV49,0) -> 3990
A50: 1 | B50: SO16422 | C50: 316424 | D50: INV12701 | E50: Gibraltar Mine (Canada) | F50: 45671.433 | G50: 45671.691 | H50: 45727 | I50: Ian Trottier | J50: CAD | K50: 1 | L50: 6106.39 | M50: 0 | N50: 4248.9477 | O50: 5815.61 | P50: 290.78 | Q50: 6106.39 | R50: Delivered | T50: =IF(A50="",T49,A50) -> 1 | U50: =IF(F50="",U49,MONTH(F50)) -> 1 | V50: =IF(F50="",V49,YEAR(F50)) -> 2025 | W50: =IF(AC50="Paid",MONTH(AD50),"") -> 4 | X50: =IF(AC50="Paid",YEAR(AD50),"") -> 2025 | Y50: =IF(C50="",Y49,N50/L50) -> 0.6958199 | Z50: =IF(B50="",Z49,B50) -> SO16422 | AA50: =IF(F50="",AA49,F50) -> 45671.433 | AB50: =IF(D50="","No Inv",D50) -> INV12701 | AC50: =IFERROR(VLOOKUP(D50,CAARStatus!$A$2:$AA$1600,22,FALSE),"Not invoiced") -> Paid | AD50: =IF(AC50="Paid",IFERROR(VLOOKUP(D50,CAARStatus!$A$2:$AA$1600,6,FALSE),"Pending"),"Pending") -> 45749 | AE50: =IF(C50="",AE49,C50) -> 316424 | AF50: =IF(E50="",AF49,E50) -> Gibraltar Mine (Canada) | AG50: =IF(J50="",AG49,J50) -> CAD | AH50: =IFERROR(IF(AG50="CAD",O50,O50/K50),0) -> 5815.61 | AI50: =IF(L50-N50=0,VLOOKUP(U50,rate!A$4:B$15,2,FALSE)*AH50,IF(AG50="USD",O50,AH50*Y50)) -> 4046.6172 | AJ50: =IFERROR(AI50/AH50,0) -> 0.6958199 | AK50: =-IF(AG50="CAD",IFERROR(VLOOKUP(D50,CAARStatus!$A$1:$Y$1600,16,FALSE),0),0) -> -5815.61 | AL50: =-IF(AG50="USD",IFERROR(VLOOKUP(D50,CAARStatus!$A$1:$Y$1600,11,FALSE),0),0) -> 0 | AM50: =IF(AG50="CAD",AH50+AK50,"") -> 0 | AN50: =IF(AG50="USD",AI50+AL50,"") | AO50: =IF(AC50="Paid","Yes","Pend") -> Yes | AP50: =IF(AND(AO50="Pend",T50<2),"Pend",IF(T50=1,"Yes","XX")) -> Yes | AQ50: =IFERROR(VLOOKUP(Z50,InvBal!$L$4:$P$600,4,FALSE),"Pend") -> Pend | AR50: =IFERROR(VLOOKUP(D50,Manual!$C$1:$E$22,2,FALSE),"Pend") -> Pend | AS50: =IF(OR(AP50="Yes",AQ50="Yes",AR50="Yes"),"Yes","") -> Yes | AT50: =IF(R50="Delivered","Yes","") -> Yes | AU50: =IF(AND(AS50="Yes",AT50="Yes"),"Yes","") -> Yes | AV50: =IFERROR(VLOOKUP(D50,'Receivable Invoice Detail'!$S$1:$U$3014,3,FALSE),0) -> 0 | AW50: =IF(AU50="Yes",AI50-AV50,0) -> 4046.6172
A51: 1 | B51: SO16423 | C51: P350633 | D51: INV12544 | E51: Covia Corp - Camden | F51: 45671.519 | G51: 45673.685 | H51: 45677 | I51: Marlen Martinez | J51: CAD | K51: 1 | L51: 5986 | M51: 0 | N51: 4162.3685 | O51: 5986 | Q51: 5986 | R51: Delivered | T51: =IF(A51="",T50,A51) -> 1 | U51: =IF(F51="",U50,MONTH(F51)) -> 1 | V51: =IF(F51="",V50,YEAR(F51)) -> 2025 | W51: =IF(AC51="Paid",MONTH(AD51),"") -> 5 | X51: =IF(AC51="Paid",YEAR(AD51),"") -> 2025 | Y51: =IF(C51="",Y50,N51/L51) -> 0.69535056 | Z51: =IF(B51="",Z50,B51) -> SO16423 | AA51: =IF(F51="",AA50,F51) -> 45671.519 | AB51: =IF(D51="","No Inv",D51) -> INV12544 | AC51: =IFERROR(VLOOKUP(D51,CAARStatus!$A$2:$AA$1600,22,FALSE),"Not invoiced") -> Paid | AD51: =IF(AC51="Paid",IFERROR(VLOOKUP(D51,CAARStatus!$A$2:$AA$1600,6,FALSE),"Pending"),"Pending") -> 45779 | AE51: =IF(C51="",AE50,C51) -> P350633 | AF51: =IF(E51="",AF50,E51) -> Covia Corp - Camden | AG51: =IF(J51="",AG50,J51) -> CAD | AH51: =IFERROR(IF(AG51="CAD",O51,O51/K51),0) -> 5986 | AI51: =IF(L51-N51=0,VLOOKUP(U51,rate!A$4:B$15,2,FALSE)*AH51,IF(AG51="USD",O51,AH51*Y51)) -> 4162.3685 | AJ51: =IFERROR(AI51/AH51,0) -> 0.69535056 | AK51: =-IF(AG51="CAD",IFERROR(VLOOKUP(D51,CAARStatus!$A$1:$Y$1600,16,FALSE),0),0) -> -8565.0102 | AL51: =-IF(AG51="USD",IFERROR(VLOOKUP(D51,CAARStatus!$A$1:$Y$1600,11,FALSE),0),0) -> 0 | AM51: =IF(AG51="CAD",AH51+AK51,"") -> -2579.0102 | AN51: =IF(AG51="USD",AI51+AL51,"") | AO51: =IF(AC51="Paid","Yes","Pend") -> Yes | AP51: =IF(AND(AO51="Pend",T51<2),"Pend",IF(T51=1,"Yes","XX")) -> Yes | AQ51: =IFERROR(VLOOKUP(Z51,InvBal!$L$4:$P$600,4,FALSE),"Pend") -> Pend | AR51: =IFERROR(VLOOKUP(D51,Manual!$C$1:$E$22,2,FALSE),"Pend") -> Pend | AS51: =IF(OR(AP51="Yes",AQ51="Yes",AR51="Yes"),"Yes","") -> Yes | AT51: =IF(R51="Delivered","Yes","") -> Yes | AU51: =IF(AND(AS51="Yes",AT51="Yes"),"Yes","") -> Yes | AV51: =IFERROR(VLOOKUP(D51,'Receivable Invoice Detail'!$S$1:$U$3014,3,FALSE),0) -> 386 | AW51: =IF(AU51="Yes",AI51-AV51,0) -> 3776.3685
A52: 1 | B52: SO16424 | C52: M-083550 | D52: INV12643 | E52: Grant Aggregate | F52: 45671.533 | G52: 45698.559 | H52: 45699 | I52: Ian Trottier | J52: CAD | K52: 1 | L52: 24293.77 | M52: 0 | N52: 16965.429 | O52: 21498.92 | P52: 2794.85 | Q52: 24293.77 | R52: Delivered | T52: =IF(A52="",T51,A52) -> 1 | U52: =IF(F52="",U51,MONTH(F52)) -> 1 | V52: =IF(F52="",V51,YEAR(F52)) -> 2025 | W52: =IF(AC52="Paid",MONTH(AD52),"") -> 3 | X52: =IF(AC52="Paid",YEAR(AD52),"") -> 2025 | Y52: =IF(C52="",Y51,N52/L52) -> 0.69834486 | Z52: =IF(B52="",Z51,B52) -> SO16424 | AA52: =IF(F52="",AA51,F52) -> 45671.533 | AB52: =IF(D52="","No Inv",D52) -> INV12643 | AC52: =IFERROR(VLOOKUP(D52,CAARStatus!$A$2:$AA$1600,22,FALSE),"Not invoiced") -> Paid | AD52: =IF(AC52="Paid",IFERROR(VLOOKUP(D52,CAARStatus!$A$2:$AA$1600,6,FALSE),"Pending"),"Pending") -> 45743 | AE52: =IF(C52="",AE51,C52) -> M-083550 | AF52: =IF(E52="",AF51,E52) -> Grant Aggregate | AG52: =IF(J52="",AG51,J52) -> CAD | AH52: =IFERROR(IF(AG52="CAD",O52,O52/K52),0) -> 21498.92 | AI52: =IF(L52-N52=0,VLOOKUP(U52,rate!A$4:B$15,2,FALSE)*AH52,IF(AG52="USD",O52,AH52*Y52)) -> 15013.66 | AJ52: =IFERROR(AI52/AH52,0) -> 0.69834486 | AK52: =-IF(AG52="CAD",IFERROR(VLOOKUP(D52,CAARStatus!$A$1:$Y$1600,16,FALSE),0),0) -> -21498.92 | AL52: =-IF(AG52="USD",IFERROR(VLOOKUP(D52,CAARStatus!$A$1:$Y$1600,11,FALSE),0),0) -> 0 | AM52: =IF(AG52="CAD",AH52+AK52,"") -> 0 | AN52: =IF(AG52="USD",AI52+AL52,"") | AO52: =IF(AC52="Paid","Yes","Pend") -> Yes | AP52: =IF(AND(AO52="Pend",T52<2),"Pend",IF(T52=1,"Yes","XX")) -> Yes | AQ52: =IFERROR(VLOOKUP(Z52,InvBal!$L$4:$P$600,4,FALSE),"Pend") -> Pend | AR52: =IFERROR(VLOOKUP(D52,Manual!$C$1:$E$22,2,FALSE),"Pend") -> Pend | AS52: =IF(OR(AP52="Yes",AQ52="Yes",AR52="Yes"),"Yes","") -> Yes | AT52: =IF(R52="Delivered","Yes","") -> Yes | AU52: =IF(AND(AS52="Yes",AT52="Yes"),"Yes","") -> Yes | AV52: =IFERROR(VLOOKUP(D52,'Receivable Invoice Detail'!$S$1:$U$3014,3,FALSE),0) -> 0 | AW52: =IF(AU52="Yes",AI52-AV52,0) -> 15013.66
A53: 1 | B53: SO16426 | C53: 16114 - Paid in Full $956.16 on February 28th 2025. | D53: INV12695 | E53: Industrial Rigging & Supply | F53: 45671.563 | G53: 45715.641 | H53: 45716 | I53: Ian Trottier | J53: CAD | K53: 1 | L53: 956.16 | M53: 0 | N53: 663.0616 | O53: 846.16 | P53: 110 | Q53: 956.16 | R53: Delivered | T53: =IF(A53="",T52,A53) -> 1 | U53: =IF(F53="",U52,MONTH(F53)) -> 1 | V53: =IF(F53="",V52,YEAR(F53)) -> 2025 | W53: =IF(AC53="Paid",MONTH(AD53),"") -> 2 | X53: =IF(AC53="Paid",YEAR(AD53),"") -> 2025 | Y53: =IF(C53="",Y52,N53/L53) -> 0.69346301 | Z53: =IF(B53="",Z52,B53) -> SO16426 | AA53: =IF(F53="",AA52,F53) -> 45671.563 | AB53: =IF(D53="","No Inv",D53) -> INV12695 | AC53: =IFERROR(VLOOKUP(D53,CAARStatus!$A$2:$AA$1600,22,FALSE),"Not invoiced") -> Paid | AD53: =IF(AC53="Paid",IFERROR(VLOOKUP(D53,CAARStatus!$A$2:$AA$1600,6,FALSE),"Pending"),"Pending") -> 45716 | AE53: =IF(C53="",AE52,C53) -> 16114 - Paid in Full $956.16 on February 28th 2025. | AF53: =IF(E53="",AF52,E53) -> Industrial Rigging & Supply | AG53: =IF(J53="",AG52,J53) -> CAD | AH53: =IFERROR(IF(AG53="CAD",O53,O53/K53),0) -> 846.16 | AI53: =IF(L53-N53=0,VLOOKUP(U53,rate!A$4:B$15,2,FALSE)*AH53,IF(AG53="USD",O53,AH53*Y53)) -> 586.78066 | AJ53: =IFERROR(AI53/AH53,0) -> 0.69346301 | AK53: =-IF(AG53="CAD",IFERROR(VLOOKUP(D53,CAARStatus!$A$1:$Y$1600,16,FALSE),0),0) -> -846.16 | AL53: =-IF(AG53="USD",IFERROR(VLOOKUP(D53,CAARStatus!$A$1:$Y$1600,11,FALSE),0),0) -> 0 | AM53: =IF(AG53="CAD",AH53+AK53,"") -> 0 | AN53: =IF(AG53="USD",AI53+AL53,"") | AO53: =IF(AC53="Paid","Yes","Pend") -> Yes | AP53: =IF(AND(AO53="Pend",T53<2),"Pend",IF(T53=1,"Yes","XX")) -> Yes | AQ53: =IFERROR(VLOOKUP(Z53,InvBal!$L$4:$P$600,4,FALSE),"Pend") -> Pend | AR53: =IFERROR(VLOOKUP(D53,Manual!$C$1:$E$22,2,FALSE),"Pend") -> Pend | AS53: =IF(OR(AP53="Yes",AQ53="Yes",AR53="Yes"),"Yes","") -> Yes | AT53: =IF(R53="Delivered","Yes","") -> Yes | AU53: =IF(AND(AS53="Yes",AT53="Yes"),"Yes","") -> Yes | AV53: =IFERROR(VLOOKUP(D53,'Receivable Invoice Detail'!$S$1:$U$3014,3,FALSE),0) -> 0 | AW53: =IF(AU53="Yes",AI53-AV53,0) -> 586.78066
A54: 1 | B54: SO16427 | C54: 6662 | D54: INV12811 | E54: Hyperflo | F54: 45671.576 | G54: 45672.537 | H54: 45749 | I54: Ian Trottier | J54: CAD | K54: 1 | L54: 5081.07 | M54: 5081.07 | N54: 5081.07 | O54: 4839.11 | P54: 241.96 | Q54: 5081.07 | R54: Delivered | T54: =IF(A54="",T53,A54) -> 1 | U54: =IF(F54="",U53,MONTH(F54)) -> 1 | V54: =IF(F54="",V53,YEAR(F54)) -> 2025 | W54: =IF(AC54="Paid",MONTH(AD54),"") -> 5 | X54: =IF(AC54="Paid",YEAR(AD54),"") -> 2025 | Y54: =IF(C54="",Y53,N54/L54) -> 1 | Z54: =IF(B54="",Z53,B54) -> SO16427 | AA54: =IF(F54="",AA53,F54) -> 45671.576 | AB54: =IF(D54="","No Inv",D54) -> INV12811 | AC54: =IFERROR(VLOOKUP(D54,CAARStatus!$A$2:$AA$1600,22,FALSE),"Not invoiced") -> Paid | AD54: =IF(AC54="Paid",IFERROR(VLOOKUP(D54,CAARStatus!$A$2:$AA$1600,6,FALSE),"Pending"),"Pending") -> 45797 | AE54: =IF(C54="",AE53,C54) -> 6662 | AF54: =IF(E54="",AF53,E54) -> Hyperflo | AG54: =IF(J54="",AG53,J54) -> CAD | AH54: =IFERROR(IF(AG54="CAD",O54,O54/K54),0) -> 4839.11 | AI54: =IF(L54-N54=0,VLOOKUP(U54,rate!A$4:B$15,2,FALSE)*AH54,IF(AG54="USD",O54,AH54*Y54)) -> 3361.6238 | AJ54: =IFERROR(AI54/AH54,0) -> 0.69467811 | AK54: =-IF(AG54="CAD",IFERROR(VLOOKUP(D54,CAARStatus!$A$1:$Y$1600,16,FALSE),0),0) -> -4839.11 | AL54: =-IF(AG54="USD",IFERROR(VLOOKUP(D54,CAARStatus!$A$1:$Y$1600,11,FALSE),0),0) -> 0 | AM54: =IF(AG54="CAD",AH54+AK54,"") -> 0 | AN54: =IF(AG54="USD",AI54+AL54,"") | AO54: =IF(AC54="Paid","Yes","Pend") -> Yes | AP54: =IF(AND(AO54="Pend",T54<2),"Pend",IF(T54=1,"Yes","XX")) -> Yes | AQ54: =IFERROR(VLOOKUP(Z54,InvBal!$L$4:$P$600,4,FALSE),"Pend") -> Pend | AR54: =IFERROR(VLOOKUP(D54,Manual!$C$1:$E$22,2,FALSE),"Pend") -> Pend | AS54: =IF(OR(AP54="Yes",AQ54="Yes",AR54="Yes"),"Yes","") -> Yes | AT54: =IF(R54="Delivered","Yes","") -> Yes | AU54: =IF(AND(AS54="Yes",AT54="Yes"),"Yes","") -> Yes | AV54: =IFERROR(VLOOKUP(D54,'Receivable Invoice Detail'!$S$1:$U$3014,3,FALSE),0) -> 0 | AW54: =IF(AU54="Yes",AI54-AV54,0) -> 3361.6238
A55: 1 | B55: SO16429 | C55: 13188 | D55: INV12538 | E55: Manufacture Sling-Choker (Val-d’Or) Ltée | F55: 45671.673 | G55: 45672.589 | H55: 45673 | I55: Taylor Cook | J55: CAD | K55: 1 | L55: 917.08 | M55: 917.08 | N55: 917.08 | O55: 873.41 | P55: 43.67 | Q55: 917.08 | R55: Delivered | T55: =IF(A55="",T54,A55) -> 1 | U55: =IF(F55="",U54,MONTH(F55)) -> 1 | V55: =IF(F55="",V54,YEAR(F55)) -> 2025 | W55: =IF(AC55="Paid",MONTH(AD55),"") -> 2 | X55: =IF(AC55="Paid",YEAR(AD55),"") -> 2025 | Y55: =IF(C55="",Y54,N55/L55) -> 1 | Z55: =IF(B55="",Z54,B55) -> SO16429 | AA55: =IF(F55="",AA54,F55) -> 45671.673 | AB55: =IF(D55="","No Inv",D55) -> INV12538 | AC55: =IFERROR(VLOOKUP(D55,CAARStatus!$A$2:$AA$1600,22,FALSE),"Not invoiced") -> Paid | AD55: =IF(AC55="Paid",IFERROR(VLOOKUP(D55,CAARStatus!$A$2:$AA$1600,6,FALSE),"Pending"),"Pending") -> 45707 | AE55: =IF(C55="",AE54,C55) -> 13188 | AF55: =IF(E55="",AF54,E55) -> Manufacture Sling-Choker (Val-d’Or) Ltée | AG55: =IF(J55="",AG54,J55) -> CAD | AH55: =IFERROR(IF(AG55="CAD",O55,O55/K55),0) -> 873.41 | AI55: =IF(L55-N55=0,VLOOKUP(U55,rate!A$4:B$15,2,FALSE)*AH55,IF(AG55="USD",O55,AH55*Y55)) -> 606.73881 | AJ55: =IFERROR(AI55/AH55,0) -> 0.69467811 | AK55: =-IF(AG55="CAD",IFERROR(VLOOKUP(D55,CAARStatus!$A$1:$Y$1600,16,FALSE),0),0) -> -873.41 | AL55: =-IF(AG55="USD",IFERROR(VLOOKUP(D55,CAARStatus!$A$1:$Y$1600,11,FALSE),0),0) -> 0 | AM55: =IF(AG55="CAD",AH55+AK55,"") -> 0 | AN55: =IF(AG55="USD",AI55+AL55,"") | AO55: =IF(AC55="Paid","Yes","Pend") -> Yes | AP55: =IF(AND(AO55="Pend",T55<2),"Pend",IF(T55=1,"Yes","XX")) -> Yes | AQ55: =IFERROR(VLOOKUP(Z55,InvBal!$L$4:$P$600,4,FALSE),"Pend") -> Pend | AR55: =IFERROR(VLOOKUP(D55,Manual!$C$1:$E$22,2,FALSE),"Pend") -> Pend | AS55: =IF(OR(AP55="Yes",AQ55="Yes",AR55="Yes"),"Yes","") -> Yes | AT55: =IF(R55="Delivered","Yes","") -> Yes | AU55: =IF(AND(AS55="Yes",AT55="Yes"),"Yes","") -> Yes | AV55: =IFERROR(VLOOKUP(D55,'Receivable Invoice Detail'!$S$1:$U$3014,3,FALSE),0) -> 0 | AW55: =IF(AU55="Yes",AI55-AV55,0) -> 606.73881
A56: 0 | B56: SO16430 | C56: 3374 | E56: Les Pompes du St-Laurent Inc. | F56: 45671.754 | G56: 45961.598 | H56: 46045 | I56: Ian Trottier | J56: CAD | K56: 1 | L56: 12682.02 | M56: 0 | N56: 9050.9156 | O56: 12078.11 | P56: 603.91 | Q56: 12682.02 | R56: Processing | T56: =IF(A56="",T55,A56) -> 0 | U56: =IF(F56="",U55,MONTH(F56)) -> 1 | V56: =IF(F56="",V55,YEAR(F56)) -> 2025 | W56: =IF(AC56="Paid",MONTH(AD56),"") | X56: =IF(AC56="Paid",YEAR(AD56),"") | Y56: =IF(C56="",Y55,N56/L56) -> 0.71368091 | Z56: =IF(B56="",Z55,B56) -> SO16430 | AA56: =IF(F56="",AA55,F56) -> 45671.754 | AB56: =IF(D56="","No Inv",D56) -> No Inv | AC56: =IFERROR(VLOOKUP(D56,CAARStatus!$A$2:$AA$1600,22,FALSE),"Not invoiced") -> Not invoiced | AD56: =IF(AC56="Paid",IFERROR(VLOOKUP(D56,CAARStatus!$A$2:$AA$1600,6,FALSE),"Pending"),"Pending") -> Pending | AE56: =IF(C56="",AE55,C56) -> 3374 | AF56: =IF(E56="",AF55,E56) -> Les Pompes du St-Laurent Inc. | AG56: =IF(J56="",AG55,J56) -> CAD | AH56: =IFERROR(IF(AG56="CAD",O56,O56/K56),0) -> 12078.11 | AI56: =IF(L56-N56=0,VLOOKUP(U56,rate!A$4:B$15,2,FALSE)*AH56,IF(AG56="USD",O56,AH56*Y56)) -> 8619.9165 | AJ56: =IFERROR(AI56/AH56,0) -> 0.71368091 | AK56: =-IF(AG56="CAD",IFERROR(VLOOKUP(D56,CAARStatus!$A$1:$Y$1600,16,FALSE),0),0) -> 0 | AL56: =-IF(AG56="USD",IFERROR(VLOOKUP(D56,CAARStatus!$A$1:$Y$1600,11,FALSE),0),0) -> 0 | AM56: =IF(AG56="CAD",AH56+AK56,"") -> 12078.11 | AN56: =IF(AG56="USD",AI56+AL56,"") | AO56: =IF(AC56="Paid","Yes","Pend") -> Pend | AP56: =IF(AND(AO56="Pend",T56<2),"Pend",IF(T56=1,"Yes","XX")) -> Pend | AQ56: =IFERROR(VLOOKUP(Z56,InvBal!$L$4:$P$600,4,FALSE),"Pend") -> Pend | AR56: =IFERROR(VLOOKUP(D56,Manual!$C$1:$E$22,2,FALSE),"Pend") -> Pend | AS56: =IF(OR(AP56="Yes",AQ56="Yes",AR56="Yes"),"Yes","") | AT56: =IF(R56="Delivered","Yes","") | AU56: =IF(AND(AS56="Yes",AT56="Yes"),"Yes","") | AV56: =IFERROR(VLOOKUP(D56,'Receivable Invoice Detail'!$S$1:$U$3014,3,FALSE),0) -> 0 | AW56: =IF(AU56="Yes",AI56-AV56,0) -> 0
A57: 1 | B57: SO16432 | C57: OP-1500441 | D57: INV12563 | E57: Agnico Eagle Mines Ltd. - Rouyn-Noranda, LaRonde secteur Penna (11102) | F57: 45672.439 | G57: 45679.399 | H57: 45680 | I57: Ian Trottier | J57: CAD | K57: 1 | L57: 523.72 | M57: 523.72 | N57: 523.72 | O57: 498.78 | P57: 24.94 | Q57: 523.72 | R57: Delivered | T57: =IF(A57="",T56,A57) -> 1 | U57: =IF(F57="",U56,MONTH(F57)) -> 1 | V57: =IF(F57="",V56,YEAR(F57)) -> 2025 | W57: =IF(AC57="Paid",MONTH(AD57),"") -> 2 | X57: =IF(AC57="Paid",YEAR(AD57),"") -> 2025 | Y57: =IF(C57="",Y56,N57/L57) -> 1 | Z57: =IF(B57="",Z56,B57) -> SO16432 | AA57: =IF(F57="",AA56,F57) -> 45672.439 | AB57: =IF(D57="","No Inv",D57) -> INV12563 | AC57: =IFERROR(VLOOKUP(D57,CAARStatus!$A$2:$AA$1600,22,FALSE),"Not invoiced") -> Paid | AD57: =IF(AC57="Paid",IFERROR(VLOOKUP(D57,CAARStatus!$A$2:$AA$1600,6,FALSE),"Pending"),"Pending") -> 45715 | AE57: =IF(C57="",AE56,C57) -> OP-1500441 | AF57: =IF(E57="",AF56,E57) -> Agnico Eagle Mines Ltd. - Rouyn-Noranda, LaRonde secteur Penna (11102) | AG57: =IF(J57="",AG56,J57) -> CAD | AH57: =IFERROR(IF(AG57="CAD",O57,O57/K57),0) -> 498.78 | AI57: =IF(L57-N57=0,VLOOKUP(U57,rate!A$4:B$15,2,FALSE)*AH57,IF(AG57="USD",O57,AH57*Y57)) -> 346.49155 | AJ57: =IFERROR(AI57/AH57,0) -> 0.69467811 | AK57: =-IF(AG57="CAD",IFERROR(VLOOKUP(D57,CAARStatus!$A$1:$Y$1600,16,FALSE),0),0) -> -498.78 | AL57: =-IF(AG57="USD",IFERROR(VLOOKUP(D57,CAARStatus!$A$1:$Y$1600,11,FALSE),0),0) -> 0 | AM57: =IF(AG57="CAD",AH57+AK57,"") -> 0 | AN57: =IF(AG57="USD",AI57+AL57,"") | AO57: =IF(AC57="Paid","Yes","Pend") -> Yes | AP57: =IF(AND(AO57="Pend",T57<2),"Pend",IF(T57=1,"Yes","XX")) -> Yes | AQ57: =IFERROR(VLOOKUP(Z57,InvBal!$L$4:$P$600,4,FALSE),"Pend") -> Pend | AR57: =IFERROR(VLOOKUP(D57,Manual!$C$1:$E$22,2,FALSE),"Pend") -> Pend | AS57: =IF(OR(AP57="Yes",AQ57="Yes",AR57="Yes"),"Yes","") -> Yes | AT57: =IF(R57="Delivered","Yes","") -> Yes | AU57: =IF(AND(AS57="Yes",AT57="Yes"),"Yes","") -> Yes | AV57: =IFERROR(VLOOKUP(D57,'Receivable Invoice Detail'!$S$1:$U$3014,3,FALSE),0) -> 0 | AW57: =IF(AU57="Yes",AI57-AV57,0) -> 346.49155
A58: 1 | B58: SO16433 | C58: 03260 | D58: INV12602 | E58: Eleazar General & Industrial Supplies Limited | F58: 45672.525 | G58: 45684.628 | H58: 45685 | I58: Ian Trottier | J58: USD | K58: 0.69723104 | L58: 4777.1969 | M58: 0 | N58: 3330.81 | O58: 3330.81 | Q58: 3330.81 | R58: Delivered | T58: =IF(A58="",T57,A58) -> 1 | U58: =IF(F58="",U57,MONTH(F58)) -> 1 | V58: =IF(F58="",V57,YEAR(F58)) -> 2025 | W58: =IF(AC58="Paid",MONTH(AD58),"") -> 1 | X58: =IF(AC58="Paid",YEAR(AD58),"") -> 2025 | Y58: =IF(C58="",Y57,N58/L58) -> 0.69723104 | Z58: =IF(B58="",Z57,B58) -> SO16433 | AA58: =IF(F58="",AA57,F58) -> 45672.525 | AB58: =IF(D58="","No Inv",D58) -> INV12602 | AC58: =IFERROR(VLOOKUP(D58,CAARStatus!$A$2:$AA$1600,22,FALSE),"Not invoiced") -> Paid | AD58: =IF(AC58="Paid",IFERROR(VLOOKUP(D58,CAARStatus!$A$2:$AA$1600,6,FALSE),"Pending"),"Pending") -> 45688 | AE58: =IF(C58="",AE57,C58) -> 03260 | AF58: =IF(E58="",AF57,E58) -> Eleazar General & Industrial Supplies Limited | AG58: =IF(J58="",AG57,J58) -> USD | AH58: =IFERROR(IF(AG58="CAD",O58,O58/K58),0) -> 4777.1969 | AI58: =IF(L58-N58=0,VLOOKUP(U58,rate!A$4:B$15,2,FALSE)*AH58,IF(AG58="USD",O58,AH58*Y58)) -> 3330.81 | AJ58: =IFERROR(AI58/AH58,0) -> 0.69723104 | AK58: =-IF(AG58="CAD",IFERROR(VLOOKUP(D58,CAARStatus!$A$1:$Y$1600,16,FALSE),0),0) -> 0 | AL58: =-IF(AG58="USD",IFERROR(VLOOKUP(D58,CAARStatus!$A$1:$Y$1600,11,FALSE),0),0) -> -3330.81 | AM58: =IF(AG58="CAD",AH58+AK58,"") | AN58: =IF(AG58="USD",AI58+AL58,"") -> 0 | AO58: =IF(AC58="Paid","Yes","Pend") -> Yes | AP58: =IF(AND(AO58="Pend",T58<2),"Pend",IF(T58=1,"Yes","XX")) -> Yes | AQ58: =IFERROR(VLOOKUP(Z58,InvBal!$L$4:$P$600,4,FALSE),"Pend") -> Pend | AR58: =IFERROR(VLOOKUP(D58,Manual!$C$1:$E$22,2,FALSE),"Pend") -> Pend | AS58: =IF(OR(AP58="Yes",AQ58="Yes",AR58="Yes"),"Yes","") -> Yes | AT58: =IF(R58="Delivered","Yes","") -> Yes | AU58: =IF(AND(AS58="Yes",AT58="Yes"),"Yes","") -> Yes | AV58: =IFERROR(VLOOKUP(D58,'Receivable Invoice Detail'!$S$1:$U$3014,3,FALSE),0) -> 0 | AW58: =IF(AU58="Yes",AI58-AV58,0) -> 3330.81
A59: 1 | B59: SO16434 | C59: 6335 | D59: INV12595 | E59: ProPart Pompes du Canada 9425-4380 Quebec Inc | F59: 45672.552 | G59: 45684.574 | H59: 45685 | I59: Ian Trottier | J59: CAD | K59: 1 | L59: 5733.49 | M59: 0 | N59: 3984.3183 | O59: 5460.46 | P59: 273.03 | Q59: 5733.49 | R59: Delivered | T59: =IF(A59="",T58,A59) -> 1 | U59: =IF(F59="",U58,MONTH(F59)) -> 1 | V59: =IF(F59="",V58,YEAR(F59)) -> 2025 | W59: =IF(AC59="Paid",MONTH(AD59),"") -> 3 | X59: =IF(AC59="Paid",YEAR(AD59),"") -> 2025 | Y59: =IF(C59="",Y58,N59/L59) -> 0.69492025 | Z59: =IF(B59="",Z58,B59) -> SO16434 | AA59: =IF(F59="",AA58,F59) -> 45672.552 | AB59: =IF(D59="","No Inv",D59) -> INV12595 | AC59: =IFERROR(VLOOKUP(D59,CAARStatus!$A$2:$AA$1600,22,FALSE),"Not invoiced") -> Paid | AD59: =IF(AC59="Paid",IFERROR(VLOOKUP(D59,CAARStatus!$A$2:$AA$1600,6,FALSE),"Pending"),"Pending") -> 45740 | AE59: =IF(C59="",AE58,C59) -> 6335 | AF59: =IF(E59="",AF58,E59) -> ProPart Pompes du Canada 9425-4380 Quebec Inc | AG59: =IF(J59="",AG58,J59) -> CAD | AH59: =IFERROR(IF(AG59="CAD",O59,O59/K59),0) -> 5460.46 | AI59: =IF(L59-N59=0,VLOOKUP(U59,rate!A$4:B$15,2,FALSE)*AH59,IF(AG59="USD",O59,AH59*Y59)) -> 3794.5842 | AJ59: =IFERROR(AI59/AH59,0) -> 0.69492025 | AK59: =-IF(AG59="CAD",IFERROR(VLOOKUP(D59,CAARStatus!$A$1:$Y$1600,16,FALSE),0),0) -> -5460.46 | AL59: =-IF(AG59="USD",IFERROR(VLOOKUP(D59,CAARStatus!$A$1:$Y$1600,11,FALSE),0),0) -> 0 | AM59: =IF(AG59="CAD",AH59+AK59,"") -> 0 | AN59: =IF(AG59="USD",AI59+AL59,"") | AO59: =IF(AC59="Paid","Yes","Pend") -> Yes | AP59: =IF(AND(AO59="Pend",T59<2),"Pend",IF(T59=1,"Yes","XX")) -> Yes | AQ59: =IFERROR(VLOOKUP(Z59,InvBal!$L$4:$P$600,4,FALSE),"Pend") -> Pend | AR59: =IFERROR(VLOOKUP(D59,Manual!$C$1:$E$22,2,FALSE),"Pend") -> Pend | AS59: =IF(OR(AP59="Yes",AQ59="Yes",AR59="Yes"),"Yes","") -> Yes | AT59: =IF(R59="Delivered","Yes","") -> Yes | AU59: =IF(AND(AS59="Yes",AT59="Yes"),"Yes","") -> Yes | AV59: =IFERROR(VLOOKUP(D59,'Receivable Invoice Detail'!$S$1:$U$3014,3,FALSE),0) -> 0 | AW59: =IF(AU59="Yes",AI59-AV59,0) -> 3794.5842
A60: 1 | B60: SO16435 | C60: 2100393819 | D60: INV12551 | E60: Wajax Limited - Noranda | F60: 45672.552 | G60: 45672.641 | H60: 45673 | I60: Ian Trottier | J60: CAD | K60: 1 | L60: 2043.9 | M60: 2043.9 | N60: 2043.9 | O60: 1946.57 | P60: 97.33 | Q60: 2043.9 | R60: Delivered | T60: =IF(A60="",T59,A60) -> 1 | U60: =IF(F60="",U59,MONTH(F60)) -> 1 | V60: =IF(F60="",V59,YEAR(F60)) -> 2025 | W60: =IF(AC60="Paid",MONTH(AD60),"") -> 2 | X60: =IF(AC60="Paid",YEAR(AD60),"") -> 2025 | Y60: =IF(C60="",Y59,N60/L60) -> 1 | Z60: =IF(B60="",Z59,B60) -> SO16435 | AA60: =IF(F60="",AA59,F60) -> 45672.552 | AB60: =IF(D60="","No Inv",D60) -> INV12551 | AC60: =IFERROR(VLOOKUP(D60,CAARStatus!$A$2:$AA$1600,22,FALSE),"Not invoiced") -> Paid | AD60: =IF(AC60="Paid",IFERROR(VLOOKUP(D60,CAARStatus!$A$2:$AA$1600,6,FALSE),"Pending"),"Pending") -> 45714 | AE60: =IF(C60="",AE59,C60) -> 2100393819 | AF60: =IF(E60="",AF59,E60) -> Wajax Limited - Noranda | AG60: =IF(J60="",AG59,J60) -> CAD | AH60: =IFERROR(IF(AG60="CAD",O60,O60/K60),0) -> 1946.57 | AI60: =IF(L60-N60=0,VLOOKUP(U60,rate!A$4:B$15,2,FALSE)*AH60,IF(AG60="USD",O60,AH60*Y60)) -> 1352.2396 | AJ60: =IFERROR(AI60/AH60,0) -> 0.69467811 | AK60: =-IF(AG60="CAD",IFERROR(VLOOKUP(D60,CAARStatus!$A$1:$Y$1600,16,FALSE),0),0) -> -1946.57 | AL60: =-IF(AG60="USD",IFERROR(VLOOKUP(D60,CAARStatus!$A$1:$Y$1600,11,FALSE),0),0) -> 0 | AM60: =IF(AG60="CAD",AH60+AK60,"") -> 0 | AN60: =IF(AG60="USD",AI60+AL60,"") | AO60: =IF(AC60="Paid","Yes","Pend") -> Yes | AP60: =IF(AND(AO60="Pend",T60<2),"Pend",IF(T60=1,"Yes","XX")) -> Yes | AQ60: =IFERROR(VLOOKUP(Z60,InvBal!$L$4:$P$600,4,FALSE),"Pend") -> Pend | AR60: =IFERROR(VLOOKUP(D60,Manual!$C$1:$E$22,2,FALSE),"Pend") -> Pend | AS60: =IF(OR(AP60="Yes",AQ60="Yes",AR60="Yes"),"Yes","") -> Yes | AT60: =IF(R60="Delivered","Yes","") -> Yes | AU60: =IF(AND(AS60="Yes",AT60="Yes"),"Yes","") -> Yes | AV60: =IFERROR(VLOOKUP(D60,'Receivable Invoice Detail'!$S$1:$U$3014,3,FALSE),0) -> 0 | AW60: =IF(AU60="Yes",AI60-AV60,0) -> 1352.2396
